Workbook
Name Slicer_Measure: #N/A
Name Slicer_Measure2: #N/A
Name Slicer_Org_name: #N/A
Name Slicer_Organisation_name: #N/A
Name Slicer_Organisation_name1: #N/A
Name Slicer_Region: #N/A
Name Slicer_Region1: #N/A
Name Slicer_Staff_Group: #N/A
Name Slicer_Staff_Group2: #N/A

Sheet Introduction
B1: Experimental Statistics
B5: Supplementary Data Quality Review and Exploratory Analysis of HES A&E Activity and Reported Workforce Statistics
B6: Hospital Episode Statistics (HES) & NHS Hospital & Community Health Service (HCHS) workforce statistics
B7: Interactive Provider Analysis
B8: Publication Date: 13th September 2018
B10: This following supplementary analysis classified as experimental statistics is part of the wider Hospital Accident and Emergency Activity 2017-18 statistical release. It seeks to assist users of the data in understanding the data quality of reported time spent within A&E within HES data by enabling through an interactive visualisation the distribution of reported HES A&E data against calculated national and provider level figures. It also enables such distributions to be viewed at specific NHS Commissioning Region level to be selected to understand potential regional variations in reported activity. Additional exploratory analysis is also presented using HCHS workforce data held within NHS Digital to explore how workforce data held within NHS Digital maybe used to support future data reporting requirements and presenting results of preliminary investigations exploring relationships between A&E activity and staffing. Data is presented so as to enable A&E activity alongside corresponding workforce data relating specifically to staff employed within an A&E setting to be reviewed at specific provider/s level. Please note this analysis and its associated results are neither intended or suitable for any performance monitoring use. The A&E Attendances and Emergency Admissions Monthly Situation Reports (MSitAE) data collected by NHSE are the Official Data source which are used for such purposes. HES A&E data has been used in the additional exploratory analysis in preference to the MSitAE because of its greater scope to investigate other potential variables that may be of interest in the future such as patient age and Casemix. Hospital A&E activity is included as part of the Hospital Accident and Emergency Statistics reports. Workforce data is extracted from NHS's HR and Payroll system. Links to these statistics are available here:
B11: https://digital.nhs.uk/data-and-information/publications/statistical/hospital-accident--emergency-activity
B12: https://digital.nhs.uk/data-and-information/publications/statistical/nhs-workforce-statistics
B13: Experimental statistics are official statistics which are published in order to involve users and stakeholders in their development and as a means to build in quality at an early stage. It is important that users understand that limitations may apply to the interpretation of this data. More details are given in the footnotes tab within this document. Find out more about Experimental Statistics at https://gss.civilservice.gov.uk/wp-content/uploads/2016/02/Guidance-on- Experimental-Statistics_1.0.pdf
B15: To use this file: Select the measure and staff group you wish to view from the selection box at the top of the 'National' sheet; Select the provider you wish to view from the selection box at the top of the 'Provider' sheet; the graph/data will automatically update to show information relating to your selection. The 'Footnotes' page contains definitions for the text used.
B16: Feedback on the content, functionality and layout of this report is welcome. Feedback can be sent to enquiries@nhsdigital.nhs.uk, quoting ‘Accident and Emergency Statistics' in the subject title.
B17: Underlying data are contained on hidden sheets in this workbook. In order to assure functionality these sheets are password-protected but the underlying data are made available as a machine readable file on the publication page for this release.
... B37: or email: psi@nationalarchives.gsi.gov.uk

Sheet Notes and Definitions
B1: Experimental Statistics
B8: Supplementary Data Quality Review and Exploratory Analysis of HES A&E Activity and Reported Workforce Statistics
B9: Hospital Episode Statistics (HES) & NHS Hospital & Community Health Service (HCHS) workforce statistics
B11: Please note this analysis and its associated results are neither intended or suitable for any performance monitoring use. The A&E Attendances and Emergency Admissions Monthly Situation Reports (MSitAE) data collected by NHSE are the Official Data source which are used for such purposes.
B13: Notes and Definitions
B15: This supplmentary analysis undertaken by NHS Digital seeks to assist users of the data in understanding the data quality of reported time spent within A&E within HES data by enabling through an interactive visualisation the distribution of reported HES A&E data against calculated national and provider level figures. Additional exploratory analysis is also presented using HCHS workforce data limited to staff directly recorded as being employed within an A&E setting held within NHS Digital to explore how workforce data held within NHS Digital maybe used to support future data reporting requirements and presenting results of preliminary investigations exploring relationships between A&E activity and staffing . A small number of experimental measures have been used within this analysis the description and details of which are listed below. These statistics have been published in order to involve users and stakeholders in their development and as a means to build in quality at an early stage and we welcome feedback on their construction via email sent to enquiries@nhsdigital.nhs.uk, quoting ‘Accident and Emergency Statistics' in the subject title.
B16: Please note that the footnotes displayed here are not extensive and do not include information relating to data quality or data collection processes. For a complete set of data quality information, this can be accessed via: HES Data Quality https://digital.nhs.uk/data-and-information/data-tools-and-services/data-services/hospital-episode-statistics/the-processing-cycle-and-hes-data-quality HCHS Data Quality https://files.digital.nhs.uk/EF/316A87/NHS%20Workforce%20Statistics%2C%20March%202018%20Bulletin.pdf
B17: This report uses activity that was submitted for the reporting period of April 2017 to March 2018.
B18: This report only includes providers that are present in both the HES A&E activity data and NHS Digitals HCHS Workforce publication reports (for organisations reporting staff employed specifically in an A&E setting).
B20: Terminology and Definitions
B21: Workforce data used within this analysis has been restricted to only count staff reported as being employed within an A&E setting within HCHS data. The following descriptions therefore relate solely to this pre defined cohort. Staff Group - These are aggregate grouping of people performing specific workforce roles within the English NHS used in HCHS Workforce Data published by NHS Digital: The following Staffing Groups have been used in this analyses: Doctor: (Stability Index only) All HCHS Doctors this includes Consultants Consultant: (Staff per attendance only) These are Consultant Doctors (including directors of Public Health) Doctor (excl. Consultant): (Staff per attendance only) All HCHS Doctors, excluding Consultant Doctors Nurses: All nurses and health visitors Care Providers (excl. Doctors and Nurses): Ambulance staff; scientific, therapeutic & technical staff; support to doctors, nurses and midwives; support to ambulance staff; support to ST&T staff Please note that the following Staff Groups have been excluded from this analysis: General functions; Hotel, property & estates; Senior managers; Managers; Other staff or those with unknown classification Additionally there are staff that work in providers that are excluded from this analysis, due to not being collected within the Workforce publication. Such as physiotherapists, wardens.
B22: Staff FTE Number of full time equivalent staff, by Staff Group, by Provider, in Accident and Emergency, in NHS Trusts. This is taken as the average over the 4 quarters for financial year 2017-18 from workforce publications (Jun, Sep, Dec 2017 and Mar 2018) to smooth the counts over the year.
... B29: Copyright © 2018, Health and Social Care Information Centre. NHS Digital is the trading name of the Health and Social Care Information Centre.

Sheet National
B1: Experimental Statistics
B6: Supplementary Data Quality Review and Exploratory Analysis of HES A&E Activity and Reported Workforce Statistics
B7: Hospital Episode Statistics (HES) & NHS Hospital & Community Health Service (HCHS) workforce statistics
B8: Please note this analysis and its associated results are neither intended or suitable for any performance monitoring use. The A&E Attendances and Emergency Admissions Monthly Situation Reports (MSitAE) data collected by NHSE are the Official Data source which are used for such purposes.
B11: =Org_Control!A6&", Staff Group (" &Org_Control!B6& ") - Annual 2017 - 18" -> Staff per Attendance / TTS 4 Hour, Staff Group (Consultant) - Annual 2017 - 18 | I11: =Org2_Control!A6&", Staff Group (" &Org2_Control!B6& ") - Annual 2017 - 18" -> Staff per Attendance / TTS 4 Hour, Staff Group (Consultant) - Annual 2017 - 18
B12: Use filters to update one or both scatter plots to facilitate comparison between metrics. National shown as orange.
B13: Avoid removing filter from Measure or Staff Group as this will lose meaning
B40: Remove filter to show all Providers and/or Regions | I40: Remove filter to show all Providers and/or Regions
A50: Key Findings
B52: Number of Staff (FTE) per 1,000 Attendance
A53: - | B53: Nationally for every 1,000 attendances in 2017-18 to A&E there are: 0.75 FTE Nurses 0.09 FTE Consultants 0.24 FTE Doctors (excluding consultants) 0.40 FTE Care Providers (Excluding Doctors and Nurses)
A54: - | B54: Less variation is observed between organisations for the number of whole time equivalent of Consultants and Other Doctors in A&E than is the case for Nurses and Care Provider Groups. The number of organisations within 0.1 FTE per 1,000 attendances for each staff group are: 6 organisations for Nurses (out of 143) 85 organisations for Consultants (out of 135) 7 organisations for Doctors (excluding consultants) (out of 139) 6 organisations for Care Providers (Excluding Doctors and Nurses) (out of 144)
A55: - | B55: Analysis to identify possible relationships between the reported number of staff per 1,000 attendance and the average duration of a patient attendance within A&E demonstrates no strong correlation between these variables across all staff groups.
B56: Staff Stability Index
A57: - | B57: Nationally turnover of staff within A&E departments is lowest amongst Doctors and highest amongst Nurses. The following stability index scores were recorded for each staff group are: 84 per cent for Doctors 77 per cent for Care Providers 73 per cent for Nurses
A58: - | B58: Less variation is observed between organisations for turnover of Doctors in A&E than is the case for Nurses and Care Providers. The number of organisations within 10 per cent of the national stability index score for each staff group are: 86 organisations for Doctors (out of 139) 105 organisations for Care Providers (out of 144) 110 organisations for Nurses (out of 143)
A59: - | B59: Analysis to identify possible relationships between the turnover of staff in A&E and the average duration of a patient attendance within A&E demonstrates no strong correlation between these variables across all staff groups.
B61: Regions
A62: - | B62: There is less observed variation between A&E staff turnover amongst Nurses for Organisations within the London Comissioning Region than in the other NHS Regions. The range in the organisational stability index scores for Nurses in each of the Comissioning Regions are: 19 per cent for London (62% to 81%) 30 per cent for South of England (56% to 86%) 57 per cent for North of England (33% to 90%) 52 per cent for Midlands and East of England (38% to 90%)
A63: - | B63: Less variation is observed between organisations for the number of Care Provider staff per 1,000 A&E attendances in the London Comissioning Region than for other NHS Comissioning Regions. The range of values observed in organisations between each of the NHS Comissioning Regions are: 0.73 for London (0.05 to 0.78) 1.07 for South of England (0.01 to 1.08) 1.24 for North of England (0.10 to 1.34) 0.98 for Midlands and East of England (0.06 to 1.04)

Sheet Provider
B1: Experimental Statistics
B4: Supplementary Data Quality Review and Exploratory Analysis of HES A&E Activity and Reported Workforce Statistics
B5: Hospital Episode Statistics (HES) & NHS Hospital & Community Health Service (HCHS) workforce statistics
B7: Please note this analysis and its associated results are neither intended or suitable for any performance monitoring use. The A&E Attendances and Emergency Admissions Monthly Situation Reports (MSitAE) data collected by NHSE are the Official Data source which are used for such purposes.
B10: Select a Provider to update the summary information below | F10: ="Summary for " &Pivot_table2!A5&" ("&Pivot_table2!B5& ")" -> Summary for Aintree University Hospital NHS Foundation Trust (REM)
F12: ="In 2017-18, there were "&TEXT(Pivot_table2!C5,"00,000")& " A&E attendances of which " &TEXT(Pivot_table2!D5,"0%")& " the total time spent within A&E was 4 hours or less, and "&TEXT(Pivot_table2!E5,"0%")& " had a total time spent within A&E in excess of 12 hours until discharge, transfer or admission." -> In 2017-18, there were 167,270 A&E attendances of which 83% the total time spent within A&E was 4 hours or less, and 2% had a total time spent within A&E in excess of 12 hours until discharge, transfer or admission.
B17: Summary table of Number of FTE Staff, Staff per Attendance Rate and Stability Index, Limited to staff activity recorded as employed within the A&E setting for Selected Provider and Nationally
C19: All Staff | D19: Nurses | E19: Care Providers | F19: Consultants | G19: Doctors (excl. Consultant)
B20: Provider FTE Staff | C20: =SUM(D20:G20) -> 176.93302 | D20: =Pivot_table2!H5 -> 99.479993 | E20: =Pivot_table2!I5 -> 41.416663 | F20: =Pivot_table2!F5 -> 15 | G20: =Pivot_table2!G5 -> 21.036365
B21: Provider Staff per Att Rate | C21: =Pivot_table2!J5 -> 1.057769 | D21: =Pivot_table2!M5 -> 0.59472704 | E21: =Pivot_table2!N5 -> 0.24760365 | F21: =Pivot_table2!K5 -> 0.089675375 | G21: =Pivot_table2!L5 -> 0.12576293
B22: National FTE Staff | C22: 27030.835 | D22: 13739.296 | E22: 7297.8952 | F22: 1642.0239 | G22: 4351.6203
B23: National Staff per Att Rate | C23: 1.4719916 | D23: 0.74818732 | E23: 0.3974143 | F23: 0.089418081 | G23: 0.2369719
C24: All Staff | D24: Nurses | E24: Care Providers | F24: Doctors (All)
B25: Provider Stability Index | C25: =Pivot_table2!Q5 -> 0.75324675 | D25: =Pivot_table2!R5 -> 0.7173913 | E25: =Pivot_table2!O5 -> 0.79545455 | F25: =Pivot_table2!P5 -> 0.83333333
B26: National Stability Index | C26: 0.75814184 | D26: 0.726593 | E26: 0.77174 | F26: 0.84366472

Sheet data
H1: Measure | I1: Stability Index / 4 Hour Wait
A2: Org | B2: Measure | C2: Staff Group | D2: Date Period | E2: Rates | F2: 4 hour wait | H2: Date Period | I2: Annual 2017/18 Total
A3: Trust 1 | B3: Stability Index / 12 Hour Wait | C3: Doctors | D3: Annual 2017/18 Total | E3: 0.50793651 | F3: 0.66911765 | H3: Staff Group | I3: Doctors
A4: Trust 1 | B4: Stability Index / 12 Hour Wait | C4: Clinical Staff | D4: Annual 2017/18 Total | E4: 0.1025641 | F4: 0.36065574
A5: Trust 1 | B5: Stability Index / 12 Hour Wait | C5: Support Staff | D5: Annual 2017/18 Total | E5: 0.15116279 | F5: 0.34868421 | H5: Count of Org | I5: Column Labels
A6: Trust 1 | B6: Stability Index / 4 Hour Wait | C6: Doctors | D6: Annual 2017/18 Total | E6: 0.16551724 | F6: 0.68627451 | H6: Row Labels | I6: 0.10447761 | J6: 0.12565445 | K6: 0.2979798 | L6: 0.34810127 | M6: 0.68627451 | N6: Grand Total
A7: Trust 1 | B7: Stability Index / 12 Hour Wait | C7: Clinical Staff | D7: Q1 2017/18 | E7: 0.18125 | F7: 0.65277778 | H7: 0.16551724 | M7: 1 | N7: 1
A8: Trust 1 | B8: Stability Index / 12 Hour Wait | C8: Support Staff | D8: Q1 2017/18 | E8: 0.14503817 | F8: 0.10606061 | H8: 0.2585034 | L8: 1 | N8: 1
A9: Trust 1 | B9: Staff Per Attendance / 12 Hour Wait | C9: Doctors | D9: Annual 2017/18 Total | E9: 0.47120419 | F9: 0.032258065 | H9: 0.58778626 | I9: 1 | N9: 1
A10: Trust 1 | B10: Stability Index / 12 Hour Wait | C10: Clinical Staff | D10: Q2 2017/18 | E10: 0.041666667 | F10: 0.35114504 | H10: 0.70175439 | J10: 1 | N10: 1
A11: Trust 1 | B11: Stability Index / 12 Hour Wait | C11: Support Staff | D11: Q2 2017/18 | E11: 0.4084507 | F11: 0.31343284 | H11: 0.75221239 | K11: 1 | N11: 1
A12: Trust 1 | B12: Staff Per Attendance / 4 Hour Wait | C12: Doctors | D12: Annual 2017/18 Total | E12: 0.29245283 | F12: 0.52631579 | H12: Grand Total | I12: 1 | J12: 1 | K12: 1 | L12: 1 | M12: 1 | N12: 5
A13: Trust 1 | B13: Stability Index / 12 Hour Wait | C13: Clinical Staff | D13: Q3 2017/25 | E13: 0.36065574 | F13: 0.79508197
A14: Trust 1 | B14: Stability Index / 12 Hour Wait | C14: Support Staff | D14: Q3 2017/29 | E14: 0.48795181 | F14: 0.62280702
A15: Trust 2 | B15: Stability Index / 12 Hour Wait | C15: Doctors | D15: Annual 2017/18 Total | E15: 0.51111111 | F15: 0.776
A16: Trust 1 | B16: Stability Index / 12 Hour Wait | C16: Clinical Staff | D16: Q4 2017/25 | E16: 0.22772277 | F16: 0.65277778
A17: Trust 1 | B17: Stability Index / 12 Hour Wait | C17: Support Staff | D17: Q4 2017/29 | E17: 0.44247788 | F17: 0.42857143
A18: Trust 2 | B18: Stability Index / 4 Hour Wait | C18: Doctors | D18: Annual 2017/18 Total | E18: 0.58778626 | F18: 0.10447761
A19: Trust 1 | B19: Stability Index / 4 Hour Wait | C19: Clinical Staff | D19: Annual 2017/18 Total | E19: 0.8411215 | F19: 0.18181818
A20: Trust 1 | B20: Stability Index / 4 Hour Wait | C20: Support Staff | D20: Annual 2017/18 Total | E20: 0.17277487 | F20: 0.085470085
A21: Trust 2 | B21: Staff Per Attendance / 12 Hour Wait | C21: Doctors | D21: Annual 2017/18 Total | E21: 0.087837838 | F21: 0.45728643
A22: Trust 1 | B22: Stability Index / 4 Hour Wait | C22: Clinical Staff | D22: Q1 2017/18 | E22: 0.092307692 | F22: 0.18238994
A23: Trust 1 | B23: Stability Index / 4 Hour Wait | C23: Support Staff | D23: Q1 2017/18 | E23: 0.11458333 | F23: 0.36423841
A24: Trust 2 | B24: Staff Per Attendance / 4 Hour Wait | C24: Doctors | D24: Annual 2017/18 Total | E24: 0.14124294 | F24: 0.2601626
... A302: Trust 5 | B302: Staff Per Attendance / 4 Hour Wait | C302: Support Staff | D302: Q4 2017/26 | E302: 0.52147239 | F302: 0.60625

Sheet Staff FTE_1
A1: Org name | B1: Org code | C1: Consultant | D1: Doctor (excl. Consultant) | E1: Nurse | F1: Clinical (excl. Doctor and Nurse) | G1: 4hr % | H1: 12hr %
A2: Aintree University Hospital NHS Foundation Trust | B2: REM | C2: 0.089674839 | D2: 0.12576218 | E2: 0.59472349 | F2: 0.24760217 | G2: 0.82522374 | H2: 0.020254557
A3: Airedale NHS Foundation Trust | B3: RCF | C3: 0.1322084 | D3: 0.30222558 | E3: 0.67101548 | F3: 0.49978268 | G3: 0.9188136 | H3: 0.0010611464
A4: Alder Hey Children's NHS Foundation Trust | B4: RBS | C4: 0.13675784 | D4: 0.086424283 | E4: 0.71978515 | F4: 0.09528569 | G4: 0.94863242 | H4: 5.0033356e-05
A5: Ashford and St. Peter's Hospitals NHS Foundation Trust | B5: RTK | C5: 0.066733235 | D5: 0.14088127 | E5: 0.690598 | F5: 0.28933487 | G5: 0.8499738 | H5: 0.030153536
A6: Barking, Havering and Redbridge University Hospitals NHS Trust | B6: RF4 | C6: 0.032908655 | D6: 0.14671775 | E6: 0.54991198 | F6: 0.25461738 | G6: 0.79653049 | H6: 0.025982167
A7: Barnsley Hospital NHS Foundation Trust | B7: RFF | C7: 0.14782713 | D7: 0.25809054 | E7: 0.75515597 | F7: 0.45850386 | G7: 0.90477248 | H7: 0.0049221344
A8: Barts Health NHS Trust | B8: R1H | C8: 0.10633967 | D8: 0.27671184 | E8: 0.68619463 | F8: 0.32095069 | G8: 0.81488207 | H8: 0.012760761
A9: Basildon and Thurrock University Hospitals NHS Foundation Trust | B9: RDD | C9: 0.068707412 | D9: 0.26674642 | E9: 0.46739888 | F9: 0.38368373 | G9: 0.85812324 | H9: 0.025745071
A10: Bedford Hospital NHS Trust | B10: RC1 | C10: 0.072432276 | D10: 0.28090142 | E10: 0.64754491 | F10: 0.23266126 | G10: 0.90379677 | H10: 0.0024890364
A11: Birmingham Women's and Children's NHS Foundation Trust | B11: RQ3 | C11: 0.093394785 | D11: 0.3168077 | E11: 0.83334744 | F11: 0.27065599 | G11: 0.92844071 | H11: 0.00052049228
A12: Blackpool Teaching Hospitals NHS Foundation Trust | B12: RXL | C12: 0.087850461 | D12: 0.3752257 | E12: 0.98986025 | F12: 0.57979747 | G12: 0.59016702 | H12: 0.072863376
A13: Bolton NHS Foundation Trust | B13: RMC | C13: 0.091906079 | D13: 0.2594386 | E13: 0.86695128 | F13: 0.26093075 | G13: 0.8150832 | H13: 0.0062566831
... A34: East Kent Hospitals University NHS Foundation Trust | B34: RVV | C34: 0.056241532 | D34: 0.16880448 | E34: 0.96172063 | F34: 0.7183408 | G34: 0.70319299 | H34: 0.050474218
A35: East Lancashire Hospitals NHS Trust | B35: RXR | C35: #DIV/0! | D35: 0.067950203 | E35: 0.098166436 | F35: 0.13602656 | G35: 0.79475256 | H35: 0.01634297
A36: East Sussex Healthcare NHS Trust | B36: RXC | C36: 0.073545018 | D36: 0.28200216 | E36: 0.79949735 | F36: 0.44982572 | G36: 0.78580464 | H36: 0.040556947
A37: Epsom and St Helier University Hospitals NHS Trust | B37: RVR | C37: 0.076228413 | D37: 0.26517756 | E37: 0.65112388 | F37: 0.25869632 | G37: 0.92594491 | H37: 0.007544991
A38: Frimley Health NHS Foundation Trust | B38: RDU | C38: 0.095993558 | D38: 0.30161925 | E38: 0.83782846 | F38: 0.35178608 | G38: 0.88981919 | H38: 0.011706659
A39: Gateshead Health NHS Foundation Trust | B39: RR7 | C39: 0.07006631 | D39: 0.1990864 | E39: 0.60301377 | F39: 0.28269296 | G39: 0.946174 | H39: 0.00026800612
A40: George Eliot Hospital NHS Trust | B40: RLT | C40: 0.066389527 | D40: 0.07569647 | E40: 0.70670733 | F40: 0.34623891 | G40: 0.87775641 | H40: 0.023614817
A41: Gloucestershire Hospitals NHS Foundation Trust | B41: RTE | C41: 0.13663717 | D41: 0.21946903 | E41: 0.82636027 | F41: 0.33903451 | G41: 0.86700177 | H41: 0.0028743363
A42: Great Western Hospitals NHS Foundation Trust | B42: RN3 | C42: 0.088328564 | D42: 0.20343789 | E42: 0.5420521 | F42: 0.42059019 | G42: 0.84341256 | H42: 0.02840914
A43: Guy's and St Thomas' NHS Foundation Trust | B43: RJ1 | C43: 0.13430039 | D43: 0.37362923 | E43: 0.94034988 | F43: 0.27941774 | G43: 0.86287063 | H43: 0.00073292615
A44: Hampshire Hospitals NHS Foundation Trust | B44: RN5 | C44: 0.092877507 | D44: 0.24181299 | E44: 0.84292384 | F44: 0.39984479 | G44: 0.86811394 | H44: 0.0095704213
A45: Harrogate and District NHS Foundation Trust | B45: RCD | C45: 0.12276447 | D45: 0.45623042 | E45: 0.64255173 | F45: 0.39426079 | G45: 0.94180055 | H45: 0.00018187329
A46: Hillingdon Hospitals NHS Foundation Trust | B46: RAS | C46: 0.10035896 | D46: 0.30293537 | E46: 0.8411746 | F46: 0.37905928 | G46: 0.74292177 | H46: 0.031753786
A47: Homerton University Hospital NHS Foundation Trust | B47: RQX | C47: 0.081845726 | D47: 0.27844205 | E47: 0.52752993 | F47: 0.18960087 | G47: 0.73223891 | H47: 0.032020795
A48: Hounslow and Richmond Community Healthcare NHS Trust | B48: RY9 | C48: #DIV/0! | D48: 0.00044521353 | E48: 0.057071879 | F48: 0.047995298 | G48: 0.99276479 | H48: 5.2239781e-05
A49: Hull and East Yorkshire Hospitals NHS Trust | B49: RWA | C49: 0.11071066 | D49: 0.24823672 | E49: 0.62872303 | F49: 0.21149717 | G49: 0.87165739 | H49: 0.0048167653
A50: Imperial College Healthcare NHS Trust | B50: RYJ | C50: 0.1058276 | D50: 0.32465808 | E50: 0.67880692 | F50: 0.2477713 | G50: 0.8313508 | H50: 0.015411665
A51: Ipswich Hospital NHS Trust | B51: RGQ | C51: 0.13890548 | D51: 0.36335394 | E51: 0.84506412 | F51: 0.44500312 | G51: 0.90717909 | H51: 0.00034760317
A52: Isle of Wight NHS Trust | B52: R1F | C52: 0.080489375 | D52: 0.23844977 | E52: 0.50107997 | F52: 0.34399152 | G52: 0.82650515 | H52: 0.025253542
A53: James Paget University Hospitals NHS Foundation Trust | B53: RGP | C53: 0.062667166 | D53: 0.1613518 | E53: 0.62245688 | F53: 0.29777538 | G53: 0.9049268 | H53: 0.013089039
A54: Kent Community Health NHS Foundation Trust | B54: RYY | C54: #DIV/0! | D54: 0 | E54: 0.023782378 | F54: 0.0094429945 | G54: 0.99832125 | H54: 9.1806891e-05
A55: Kettering General Hospital NHS Foundation Trust | B55: RNQ | C55: 0.069054415 | D55: 0.27995811 | E55: 0.80112705 | F55: 0.58243561 | G55: 0.76826489 | H55: 0.034630789
A56: King's College Hospital NHS Foundation Trust | B56: RJZ | C56: 0.099609007 | D56: 0.33404592 | E56: 1.2698922 | F56: 0.21676373 | G56: 0.77614901 | H56: 0.027741656
A57: Kingston Hospital NHS Foundation Trust | B57: RAX | C57: 0.083558435 | D57: 0.20000064 | E57: 0.62518505 | F57: 0.32480566 | G57: 0.79727142 | H57: 0.01388224
A58: Lancashire Teaching Hospitals NHS Foundation Trust | B58: RXN | C58: 0.20774791 | D58: 0.37183069 | E58: 0.9720992 | F58: 0.69252853 | G58: 0.75357687 | H58: 0.025558249
A59: Leeds Teaching Hospitals NHS Trust | B59: RR8 | C59: 0.14925654 | D59: 0.24793433 | E59: 1.0304198 | F59: 0.64274742 | G59: 0.80601818 | H59: 0.024232459
A60: Lewisham and Greenwich NHS Trust | B60: RJ2 | C60: 0.081581614 | D60: 0.30165296 | E60: 0.97220869 | F60: 0.33092317 | G60: 0.80135923 | H60: 0.035788994
A61: Lincolnshire Community Health Services NHS Trust | B61: RY5 | C61: #DIV/0! | D61: 0 | E61: 0.099104298 | F61: 0.11358969 | G61: 0.99053911 | H61: 0.00012260328
A62: Luton and Dunstable University Hospital NHS Foundation Trust | B62: RC9 | C62: 0.092663872 | D62: 0.39284136 | E62: 0.90185649 | F62: 0.30387 | G62: 0.97741853 | H62: 0.00050371131
A63: Maidstone and Tunbridge Wells NHS Trust | B63: RWF | C63: 0.077552627 | D63: 0.24954908 | E63: 0.78858065 | F63: 0.35146219 | G63: 0.89224885 | H63: 0.030786043
A64: Medway NHS Foundation Trust | B64: RPA | C64: 0.054306238 | D64: 0.29464734 | E64: 0.59180044 | F64: 0.23376353 | G64: 0.83415204 | H64: 0.039388479
A65: Mid Cheshire Hospitals NHS Foundation Trust | B65: RBT | C65: 0.083343728 | D65: 0.14957648 | E65: 1.0674969 | F65: 0.74801928 | G65: 0.87225164 | H65: 0.0062819626
A66: Mid Essex Hospital Services NHS Trust | B66: RQ8 | C66: 0.068236859 | D66: 0.23302887 | E66: 0.57696128 | F66: 0.30398072 | G66: 0.81549746 | H66: 0.019741544
A67: Mid Yorkshire Hospitals NHS Trust | B67: RXF | C67: 0.07298022 | D67: 0.17860606 | E67: 0.5420622 | F67: 0.28669399 | G67: 0.85156657 | H67: 0.010713496
A68: Milton Keynes University Hospital NHS Foundation Trust | B68: RD8 | C68: 0.092426747 | D68: 0.27376458 | E68: 0.65923406 | F68: 0.36239707 | G68: 0.85303573 | H68: 0.022079085
A69: Moorfields Eye Hospital NHS Foundation Trust | B69: RP6 | C69: 0.065849252 | D69: 0.073321756 | E69: 0.52019857 | F69: 0.056131488 | G69: 0.98516024 | H69: 2.1049308e-05
A70: Newcastle Upon Tyne Hospitals NHS Foundation Trust | B70: RTD | C70: 0.084922883 | D70: 0.16283772 | E70: 0.56571903 | F70: 0.26316773 | G70: 0.93738082 | H70: 0.0001881525
A71: Norfolk and Norwich University Hospitals NHS Foundation Trust | B71: RM1 | C71: #DIV/0! | D71: 0.050867607 | E71: 0.83873768 | F71: 0.51032717 | G71: 0.80722892 | H71: 0.01498213
A72: North Bristol NHS Trust | B72: RVJ | C72: 0.1327778 | D72: 0.31761023 | E72: 1.2712175 | F72: 0.71443692 | G72: 0.75758894 | H72: 0.034316194
A73: North Cumbria University Hospitals NHS Trust | B73: RNL | C73: 0.099799455 | D73: 0.22804547 | E73: 0.64023006 | F73: 0.40074739 | G73: 0.88072175 | H73: 0.008010984
A74: North Middlesex University Hospital NHS Trust | B74: RAP | C74: 0.063589475 | D74: 0.22436629 | E74: 0.66171909 | F74: 0.29137152 | G74: 0.81008221 | H74: 0.0083980361
A75: North Tees and Hartlepool NHS Foundation Trust | B75: RVW | C75: 0.055769652 | D75: 0.17226841 | E75: 0.32957272 | F75: 0.29533097 | G75: 0.95419291 | H75: 0.00018235308
A76: North West Anglia NHS Foundation Trust | B76: RGN | C76: 0.082507701 | D76: 0.24745935 | E76: 0.91268505 | F76: 0.34358205 | G76: 0.80773539 | H76: 0.015614791
A77: Northampton General Hospital NHS Trust | B77: RNS | C77: 0.073015925 | D77: 0.20179427 | E77: 0.71899593 | F77: 0.34383062 | G77: 0.85110462 | H77: 0.034843689
A78: Northern Devon Healthcare NHS Trust | B78: RBZ | C78: 0.082724577 | D78: 0.23060041 | E78: 0.68503182 | F78: 0.16546701 | G78: 0.86917764 | H78: 0.032800521
A79: Northern Lincolnshire and Goole NHS Foundation Trust | B79: RJL | C79: 0.06546808 | D79: 0.17240884 | E79: 0.58485037 | F79: 0.21995502 | G79: 0.85511947 | H79: 0.002366156
A80: Northumbria Healthcare NHS Foundation Trust | B80: RTF | C80: 0.12357966 | D80: 0.27852012 | E80: 0.42191442 | F80: 0.38182372 | G80: 0.93233596 | H80: 0
A81: Nottingham University Hospitals NHS Trust | B81: RX1 | C81: 0.1024435 | D81: 0.17467911 | E81: 1.2501894 | F81: 0.55111967 | G81: 0.79868085 | H81: 0.0099516547
A82: Oxford University Hospitals NHS Foundation Trust | B82: RTH | C82: 0.1308785 | D82: 0.26284843 | E82: 0.93467569 | F82: 0.50424414 | G82: 0.80364548 | H82: 0.03799153
A83: Pennine Acute Hospitals NHS Trust | B83: RW6 | C83: 0.070070161 | D83: 0.25982293 | E83: 0.69272373 | F83: 0.33191061 | G83: 0.82308272 | H83: 0.018868785
... A88: Queen Elizabeth Hospital King's Lynn NHS Foundation Trust | B88: RCX | C88: 0.084237212 | D88: 0.24228227 | E88: 0.7523588 | F88: 0.31678551 | G88: 0.855112 | H88: 0.011456261
A89: Queen Victoria Hospital NHS Foundation Trust | B89: RPC | C89: #DIV/0! | D89: 0.0045670442 | E89: #DIV/0! | F89: 0.55671675 | G89: 0.99689441 | H89: 0
A90: Rotherham NHS Foundation Trust | B90: RFR | C90: 0.091890283 | D90: 0.14079177 | E90: 0.74994154 | F90: 0.5089065 | G90: 0.82019833 | H90: 0.010951708
A91: Royal Berkshire NHS Foundation Trust | B91: RHW | C91: 0.10014024 | D91: 0.28194927 | E91: 0.63713766 | F91: 0.34977667 | G91: 0.88420922 | H91: 0.0047803888
A92: Royal Bournemouth and Christchurch Hospitals NHS Foundation Trust | B92: RDZ | C92: 0.10095256 | D92: 0.24685429 | E92: 0.71582308 | F92: 0.49172812 | G92: 0.80650049 | H92: 0.027945536
A93: Royal Cornwall Hospitals NHS Trust | B93: REF | C93: 0.072812566 | D93: 0.22644345 | E93: 0.44322702 | F93: 0.33824389 | G93: 0.87375079 | H93: 0.012172755
A94: Royal Devon and Exeter NHS Foundation Trust | B94: RH8 | C94: 0.10237751 | D94: 0.28971648 | E94: 0.54616401 | F94: 0.31207772 | G94: 0.90162719 | H94: 0.0015096728
A95: Royal Free London NHS Foundation Trust | B95: RAL | C95: 0.067836949 | D95: 0.21817882 | E95: 0.68019113 | F95: 0.30696045 | G95: 0.86086604 | H95: 0.022662847
A96: Royal Liverpool and Broadgreen University Hospitals NHS Trust | B96: RQ6 | C96: 0.11861364 | D96: 0.32565673 | E96: 0.82812776 | F96: 0.55045762 | G96: 0.75589404 | H96: 0.072294785
A97: Royal Surrey County Hospital NHS Foundation Trust | B97: RA2 | C97: 0.14202943 | D97: 0.19743325 | E97: 0.92152155 | F97: 0.25053076 | G97: 0.94885531 | H97: 0.0022978459
A98: Royal United Hospitals Bath NHS Foundation Trust | B98: RD1 | C98: 0.12652452 | D98: 0.36125169 | E98: 0.98420632 | F98: 1.0786835 | G98: 0.79605354 | H98: 0.023479632
A99: Royal Wolverhampton NHS Trust | B99: RL4 | C99: 0.090772058 | D99: 0.18515437 | E99: 0.51653692 | F99: 0.26167096 | G99: 0.87153278 | H99: 0.0055893582
A100: Salford Royal NHS Foundation Trust | B100: RM3 | C100: 0.36099444 | D100: 0.26555027 | E100: 2.0678684 | F100: 1.3424041 | G100: 0.85284018 | H100: 0.0061312445
A101: Salisbury NHS Foundation Trust | B101: RNZ | C101: 0.19736984 | D101: 0.27462797 | E101: 0.84396746 | F101: 0.40696034 | G101: 0.91707222 | H101: 0.0025955486
... A106: Shrewsbury and Telford Hospital NHS Trust | B106: RXW | C106: 0.045083224 | D106: 0.23578526 | E106: 0.61195941 | F106: 0.32745293 | G106: 0.70467784 | H106: 0.041124917
A107: Shropshire Community Health NHS Trust | B107: R1D | C107: #DIV/0! | D107: 0 | E107: 0.08979462 | F107: 0.061438467 | G107: 0.99254638 | H107: 0.0014178077
A108: Somerset Partnership NHS Foundation Trust | B108: RH5 | C108: #DIV/0! | D108: 0 | E108: 0.62545502 | F108: 0.19496448 | G108: 0.99733489 | H108: 2.600104e-05
A109: South Tees Hospitals NHS Foundation Trust | B109: RTR | C109: 0.13903402 | D109: 0.17703089 | E109: 0.91575591 | F109: 0.57948064 | G109: 0.94999534 | H109: 0.0001862949
A110: South Tyneside NHS Foundation Trust | B110: RE9 | C110: 0.073375108 | D110: 0.17683401 | E110: 0.71261909 | F110: 0.29085893 | G110: 0.94229781 | H110: 0.0011153016
A111: South Warwickshire NHS Foundation Trust | B111: RJC | C111: 0.13198475 | D111: 0.1205371 | E111: 0.51966506 | F111: 0.43025222 | G111: 0.91403483 | H111: 0.0087002195
A112: Southend University Hospital NHS Foundation Trust | B112: RAJ | C112: 0.089088623 | D112: 0.34040407 | E112: 0.69847126 | F112: 0.45545299 | G112: 0.86850519 | H112: 0.0032863803
A113: Southern Health NHS Foundation Trust | B113: RW1 | C113: #DIV/0! | D113: 0 | E113: 0.74543041 | F113: 0.36655379 | G113: 0.99685905 | H113: 6.5436461e-05
A114: Southport and Ormskirk Hospital NHS Trust | B114: RVY | C114: 0.082790595 | D114: 0.27845237 | E114: 1.1060007 | F114: 0.56827716 | G114: 0.7875532 | H114: 0.032269934
A115: St George's University Hospitals NHS Foundation Trust | B115: RJ7 | C115: 0.13156571 | D115: 0.28544713 | E115: 0.72326816 | F115: 0.16431144 | G115: 0.82362988 | H115: 0.024606783
A116: St Helens and Knowsley Hospitals NHS Trust | B116: RBN | C116: 0.067388308 | D116: 0.23147277 | E116: 0.56298582 | F116: 0.31447876 | G116: 0.85150895 | H116: 0.030828633
A117: Stockport NHS Foundation Trust | B117: RWJ | C117: 0.078177365 | D117: 0.27507089 | E117: 1.0243189 | F117: 0.4724241 | G117: 0.79033772 | H117: 0.032348543
A118: Surrey and Sussex Healthcare NHS Trust | B118: RTP | C118: 0.091120786 | D118: 0.38483029 | E118: 0.76980164 | F118: 0.38972676 | G118: 0.91327326 | H118: 0.034403159
A119: Tameside and Glossop Integrated Care NHS Foundation Trust | B119: RMP | C119: 0.11120235 | D119: 0.17108054 | E119: 0.81514168 | F119: 0.63892872 | G119: 0.83427998 | H119: 0.01049294
A120: Taunton and Somerset NHS Foundation Trust | B120: RBA | C120: 0.12228299 | D120: 0.17129613 | E120: 0.79501526 | F120: 0.6516116 | G120: 0.90283612 | H120: 0.0003805926
A121: Torbay and South Devon NHS Foundation Trust | B121: RA9 | C121: 0.080752314 | D121: 0.2325638 | E121: 0.92966473 | F121: 0.85101849 | G121: 0.88784935 | H121: 0.0040135618
A122: United Lincolnshire Hospitals NHS Trust | B122: RWD | C122: 0.09048534 | D122: 0.25222501 | E122: 1.1513013 | F122: 1.0427501 | G122: 0.73940222 | H122: 0.023319848
A123: University College London Hospitals NHS Foundation Trust | B123: RRV | C123: 0.0933907 | D123: 0.16247983 | E123: 0.63949008 | F123: 0.3243189 | G123: 0.87568499 | H123: 0.010385627
A124: University Hospital Southampton NHS Foundation Trust | B124: RHM | C124: 0.13001969 | D124: 0.33381394 | E124: 0.93659649 | F124: 0.0092871206 | G124: 0.87863591 | H124: 0.0031427616
A125: University Hospitals Birmingham NHS Foundation Trust | B125: RRK | C125: 0.14179537 | D125: 0.30751045 | E125: 0.93559634 | F125: 0.54576202 | G125: 0.82896865 | H125: 0.010778321
... A145: London North West University Healthcare NHS Trust | B145: R1K | C145: 0.14132419 | D145: 0.38473557 | E145: 1.4396354 | F145: 0.78169177 | G145: 0.58551534 | H145: 0.078225423

Sheet Staff FTE_2
A1: Org name | B1: Org code | C1: Measure | D1: Staff Group | E1: Staff Rate | F1: Measure Rate
A2: Aintree University Hospital NHS Foundation Trust | B2: REM | C2: Staff per Attendance / 4 Hour Wait | D2: Consultant | E2: 0.089674839 | F2: 0.82522374
A3: Airedale NHS Foundation Trust | B3: RCF | C3: Staff per Attendance / 4 Hour Wait | D3: Consultant | E3: 0.1322084 | F3: 0.9188136
A4: Alder Hey Children's NHS Foundation Trust | B4: RBS | C4: Staff per Attendance / 4 Hour Wait | D4: Consultant | E4: 0.13675784 | F4: 0.94863242
A5: Ashford and St. Peter's Hospitals NHS Foundation Trust | B5: RTK | C5: Staff per Attendance / 4 Hour Wait | D5: Consultant | E5: 0.066733235 | F5: 0.8499738
A6: Barking, Havering and Redbridge University Hospitals NHS Trust | B6: RF4 | C6: Staff per Attendance / 4 Hour Wait | D6: Consultant | E6: 0.032908655 | F6: 0.79653049
A7: Barnsley Hospital NHS Foundation Trust | B7: RFF | C7: Staff per Attendance / 4 Hour Wait | D7: Consultant | E7: 0.14782713 | F7: 0.90477248
A8: Barts Health NHS Trust | B8: R1H | C8: Staff per Attendance / 4 Hour Wait | D8: Consultant | E8: 0.10633967 | F8: 0.81488207
A9: Basildon and Thurrock University Hospitals NHS Foundation Trust | B9: RDD | C9: Staff per Attendance / 4 Hour Wait | D9: Consultant | E9: 0.068707412 | F9: 0.85812324
A10: Bedford Hospital NHS Trust | B10: RC1 | C10: Staff per Attendance / 4 Hour Wait | D10: Consultant | E10: 0.072432276 | F10: 0.90379677
A11: Birmingham Women's and Children's NHS Foundation Trust | B11: RQ3 | C11: Staff per Attendance / 4 Hour Wait | D11: Consultant | E11: 0.093394785 | F11: 0.92844071
A12: Blackpool Teaching Hospitals NHS Foundation Trust | B12: RXL | C12: Staff per Attendance / 4 Hour Wait | D12: Consultant | E12: 0.087850461 | F12: 0.59016702
A13: Bolton NHS Foundation Trust | B13: RMC | C13: Staff per Attendance / 4 Hour Wait | D13: Consultant | E13: 0.091906079 | F13: 0.8150832
... A34: East Kent Hospitals University NHS Foundation Trust | B34: RVV | C34: Staff per Attendance / 4 Hour Wait | D34: Consultant | E34: 0.056241532 | F34: 0.70319299
A35: East Lancashire Hospitals NHS Trust | B35: RXR | C35: Staff per Attendance / 4 Hour Wait | D35: Consultant | E35: #DIV/0! | F35: 0.79475256
A36: East Sussex Healthcare NHS Trust | B36: RXC | C36: Staff per Attendance / 4 Hour Wait | D36: Consultant | E36: 0.073545018 | F36: 0.78580464
A37: Epsom and St Helier University Hospitals NHS Trust | B37: RVR | C37: Staff per Attendance / 4 Hour Wait | D37: Consultant | E37: 0.076228413 | F37: 0.92594491
A38: Frimley Health NHS Foundation Trust | B38: RDU | C38: Staff per Attendance / 4 Hour Wait | D38: Consultant | E38: 0.095993558 | F38: 0.88981919
A39: Gateshead Health NHS Foundation Trust | B39: RR7 | C39: Staff per Attendance / 4 Hour Wait | D39: Consultant | E39: 0.07006631 | F39: 0.946174
A40: George Eliot Hospital NHS Trust | B40: RLT | C40: Staff per Attendance / 4 Hour Wait | D40: Consultant | E40: 0.066389527 | F40: 0.87775641
A41: Gloucestershire Hospitals NHS Foundation Trust | B41: RTE | C41: Staff per Attendance / 4 Hour Wait | D41: Consultant | E41: 0.13663717 | F41: 0.86700177
A42: Great Western Hospitals NHS Foundation Trust | B42: RN3 | C42: Staff per Attendance / 4 Hour Wait | D42: Consultant | E42: 0.088328564 | F42: 0.84341256
A43: Guy's and St Thomas' NHS Foundation Trust | B43: RJ1 | C43: Staff per Attendance / 4 Hour Wait | D43: Consultant | E43: 0.13430039 | F43: 0.86287063
A44: Hampshire Hospitals NHS Foundation Trust | B44: RN5 | C44: Staff per Attendance / 4 Hour Wait | D44: Consultant | E44: 0.092877507 | F44: 0.86811394
A45: Harrogate and District NHS Foundation Trust | B45: RCD | C45: Staff per Attendance / 4 Hour Wait | D45: Consultant | E45: 0.12276447 | F45: 0.94180055
A46: Hillingdon Hospitals NHS Foundation Trust | B46: RAS | C46: Staff per Attendance / 4 Hour Wait | D46: Consultant | E46: 0.10035896 | F46: 0.74292177
A47: Homerton University Hospital NHS Foundation Trust | B47: RQX | C47: Staff per Attendance / 4 Hour Wait | D47: Consultant | E47: 0.081845726 | F47: 0.73223891
A48: Hounslow and Richmond Community Healthcare NHS Trust | B48: RY9 | C48: Staff per Attendance / 4 Hour Wait | D48: Consultant | E48: #DIV/0! | F48: 0.99276479
A49: Hull and East Yorkshire Hospitals NHS Trust | B49: RWA | C49: Staff per Attendance / 4 Hour Wait | D49: Consultant | E49: 0.11071066 | F49: 0.87165739
A50: Imperial College Healthcare NHS Trust | B50: RYJ | C50: Staff per Attendance / 4 Hour Wait | D50: Consultant | E50: 0.1058276 | F50: 0.8313508
A51: Ipswich Hospital NHS Trust | B51: RGQ | C51: Staff per Attendance / 4 Hour Wait | D51: Consultant | E51: 0.13890548 | F51: 0.90717909
A52: Isle of Wight NHS Trust | B52: R1F | C52: Staff per Attendance / 4 Hour Wait | D52: Consultant | E52: 0.080489375 | F52: 0.82650515
A53: James Paget University Hospitals NHS Foundation Trust | B53: RGP | C53: Staff per Attendance / 4 Hour Wait | D53: Consultant | E53: 0.062667166 | F53: 0.9049268
A54: Kent Community Health NHS Foundation Trust | B54: RYY | C54: Staff per Attendance / 4 Hour Wait | D54: Consultant | E54: #DIV/0! | F54: 0.99832125
A55: Kettering General Hospital NHS Foundation Trust | B55: RNQ | C55: Staff per Attendance / 4 Hour Wait | D55: Consultant | E55: 0.069054415 | F55: 0.76826489
A56: King's College Hospital NHS Foundation Trust | B56: RJZ | C56: Staff per Attendance / 4 Hour Wait | D56: Consultant | E56: 0.099609007 | F56: 0.77614901
A57: Kingston Hospital NHS Foundation Trust | B57: RAX | C57: Staff per Attendance / 4 Hour Wait | D57: Consultant | E57: 0.083558435 | F57: 0.79727142
A58: Lancashire Teaching Hospitals NHS Foundation Trust | B58: RXN | C58: Staff per Attendance / 4 Hour Wait | D58: Consultant | E58: 0.20774791 | F58: 0.75357687
A59: Leeds Teaching Hospitals NHS Trust | B59: RR8 | C59: Staff per Attendance / 4 Hour Wait | D59: Consultant | E59: 0.14925654 | F59: 0.80601818
A60: Lewisham and Greenwich NHS Trust | B60: RJ2 | C60: Staff per Attendance / 4 Hour Wait | D60: Consultant | E60: 0.081581614 | F60: 0.80135923
A61: Lincolnshire Community Health Services NHS Trust | B61: RY5 | C61: Staff per Attendance / 4 Hour Wait | D61: Consultant | E61: #DIV/0! | F61: 0.99053911
A62: Luton and Dunstable University Hospital NHS Foundation Trust | B62: RC9 | C62: Staff per Attendance / 4 Hour Wait | D62: Consultant | E62: 0.092663872 | F62: 0.97741853
A63: Maidstone and Tunbridge Wells NHS Trust | B63: RWF | C63: Staff per Attendance / 4 Hour Wait | D63: Consultant | E63: 0.077552627 | F63: 0.89224885
A64: Medway NHS Foundation Trust | B64: RPA | C64: Staff per Attendance / 4 Hour Wait | D64: Consultant | E64: 0.054306238 | F64: 0.83415204
A65: Mid Cheshire Hospitals NHS Foundation Trust | B65: RBT | C65: Staff per Attendance / 4 Hour Wait | D65: Consultant | E65: 0.083343728 | F65: 0.87225164
A66: Mid Essex Hospital Services NHS Trust | B66: RQ8 | C66: Staff per Attendance / 4 Hour Wait | D66: Consultant | E66: 0.068236859 | F66: 0.81549746
A67: Mid Yorkshire Hospitals NHS Trust | B67: RXF | C67: Staff per Attendance / 4 Hour Wait | D67: Consultant | E67: 0.07298022 | F67: 0.85156657
A68: Milton Keynes University Hospital NHS Foundation Trust | B68: RD8 | C68: Staff per Attendance / 4 Hour Wait | D68: Consultant | E68: 0.092426747 | F68: 0.85303573
A69: Moorfields Eye Hospital NHS Foundation Trust | B69: RP6 | C69: Staff per Attendance / 4 Hour Wait | D69: Consultant | E69: 0.065849252 | F69: 0.98516024
A70: Newcastle Upon Tyne Hospitals NHS Foundation Trust | B70: RTD | C70: Staff per Attendance / 4 Hour Wait | D70: Consultant | E70: 0.084922883 | F70: 0.93738082
A71: Norfolk and Norwich University Hospitals NHS Foundation Trust | B71: RM1 | C71: Staff per Attendance / 4 Hour Wait | D71: Consultant | E71: #DIV/0! | F71: 0.80722892
A72: North Bristol NHS Trust | B72: RVJ | C72: Staff per Attendance / 4 Hour Wait | D72: Consultant | E72: 0.1327778 | F72: 0.75758894
A73: North Cumbria University Hospitals NHS Trust | B73: RNL | C73: Staff per Attendance / 4 Hour Wait | D73: Consultant | E73: 0.099799455 | F73: 0.88072175
A74: North Middlesex University Hospital NHS Trust | B74: RAP | C74: Staff per Attendance / 4 Hour Wait | D74: Consultant | E74: 0.063589475 | F74: 0.81008221
A75: North Tees and Hartlepool NHS Foundation Trust | B75: RVW | C75: Staff per Attendance / 4 Hour Wait | D75: Consultant | E75: 0.055769652 | F75: 0.95419291
A76: North West Anglia NHS Foundation Trust | B76: RGN | C76: Staff per Attendance / 4 Hour Wait | D76: Consultant | E76: 0.082507701 | F76: 0.80773539
A77: Northampton General Hospital NHS Trust | B77: RNS | C77: Staff per Attendance / 4 Hour Wait | D77: Consultant | E77: 0.073015925 | F77: 0.85110462
A78: Northern Devon Healthcare NHS Trust | B78: RBZ | C78: Staff per Attendance / 4 Hour Wait | D78: Consultant | E78: 0.082724577 | F78: 0.86917764
A79: Northern Lincolnshire and Goole NHS Foundation Trust | B79: RJL | C79: Staff per Attendance / 4 Hour Wait | D79: Consultant | E79: 0.06546808 | F79: 0.85511947
A80: Northumbria Healthcare NHS Foundation Trust | B80: RTF | C80: Staff per Attendance / 4 Hour Wait | D80: Consultant | E80: 0.12357966 | F80: 0.93233596
A81: Nottingham University Hospitals NHS Trust | B81: RX1 | C81: Staff per Attendance / 4 Hour Wait | D81: Consultant | E81: 0.1024435 | F81: 0.79868085
A82: Oxford University Hospitals NHS Foundation Trust | B82: RTH | C82: Staff per Attendance / 4 Hour Wait | D82: Consultant | E82: 0.1308785 | F82: 0.80364548
A83: Pennine Acute Hospitals NHS Trust | B83: RW6 | C83: Staff per Attendance / 4 Hour Wait | D83: Consultant | E83: 0.070070161 | F83: 0.82308272
... A88: Queen Elizabeth Hospital King's Lynn NHS Foundation Trust | B88: RCX | C88: Staff per Attendance / 4 Hour Wait | D88: Consultant | E88: 0.084237212 | F88: 0.855112
A89: Queen Victoria Hospital NHS Foundation Trust | B89: RPC | C89: Staff per Attendance / 4 Hour Wait | D89: Consultant | E89: #DIV/0! | F89: 0.99689441
A90: Rotherham NHS Foundation Trust | B90: RFR | C90: Staff per Attendance / 4 Hour Wait | D90: Consultant | E90: 0.091890283 | F90: 0.82019833
A91: Royal Berkshire NHS Foundation Trust | B91: RHW | C91: Staff per Attendance / 4 Hour Wait | D91: Consultant | E91: 0.10014024 | F91: 0.88420922
A92: Royal Bournemouth and Christchurch Hospitals NHS Foundation Trust | B92: RDZ | C92: Staff per Attendance / 4 Hour Wait | D92: Consultant | E92: 0.10095256 | F92: 0.80650049
A93: Royal Cornwall Hospitals NHS Trust | B93: REF | C93: Staff per Attendance / 4 Hour Wait | D93: Consultant | E93: 0.072812566 | F93: 0.87375079
A94: Royal Devon and Exeter NHS Foundation Trust | B94: RH8 | C94: Staff per Attendance / 4 Hour Wait | D94: Consultant | E94: 0.10237751 | F94: 0.90162719
A95: Royal Free London NHS Foundation Trust | B95: RAL | C95: Staff per Attendance / 4 Hour Wait | D95: Consultant | E95: 0.067836949 | F95: 0.86086604
A96: Royal Liverpool and Broadgreen University Hospitals NHS Trust | B96: RQ6 | C96: Staff per Attendance / 4 Hour Wait | D96: Consultant | E96: 0.11861364 | F96: 0.75589404
A97: Royal Surrey County Hospital NHS Foundation Trust | B97: RA2 | C97: Staff per Attendance / 4 Hour Wait | D97: Consultant | E97: 0.14202943 | F97: 0.94885531
A98: Royal United Hospitals Bath NHS Foundation Trust | B98: RD1 | C98: Staff per Attendance / 4 Hour Wait | D98: Consultant | E98: 0.12652452 | F98: 0.79605354
A99: Royal Wolverhampton NHS Trust | B99: RL4 | C99: Staff per Attendance / 4 Hour Wait | D99: Consultant | E99: 0.090772058 | F99: 0.87153278
A100: Salford Royal NHS Foundation Trust | B100: RM3 | C100: Staff per Attendance / 4 Hour Wait | D100: Consultant | E100: 0.36099444 | F100: 0.85284018
A101: Salisbury NHS Foundation Trust | B101: RNZ | C101: Staff per Attendance / 4 Hour Wait | D101: Consultant | E101: 0.19736984 | F101: 0.91707222
... A106: Shrewsbury and Telford Hospital NHS Trust | B106: RXW | C106: Staff per Attendance / 4 Hour Wait | D106: Consultant | E106: 0.045083224 | F106: 0.70467784
A107: Shropshire Community Health NHS Trust | B107: R1D | C107: Staff per Attendance / 4 Hour Wait | D107: Consultant | E107: #DIV/0! | F107: 0.99254638
A108: Somerset Partnership NHS Foundation Trust | B108: RH5 | C108: Staff per Attendance / 4 Hour Wait | D108: Consultant | E108: #DIV/0! | F108: 0.99733489
A109: South Tees Hospitals NHS Foundation Trust | B109: RTR | C109: Staff per Attendance / 4 Hour Wait | D109: Consultant | E109: 0.13903402 | F109: 0.94999534
A110: South Tyneside NHS Foundation Trust | B110: RE9 | C110: Staff per Attendance / 4 Hour Wait | D110: Consultant | E110: 0.073375108 | F110: 0.94229781
A111: South Warwickshire NHS Foundation Trust | B111: RJC | C111: Staff per Attendance / 4 Hour Wait | D111: Consultant | E111: 0.13198475 | F111: 0.91403483
A112: Southend University Hospital NHS Foundation Trust | B112: RAJ | C112: Staff per Attendance / 4 Hour Wait | D112: Consultant | E112: 0.089088623 | F112: 0.86850519
A113: Southern Health NHS Foundation Trust | B113: RW1 | C113: Staff per Attendance / 4 Hour Wait | D113: Consultant | E113: #DIV/0! | F113: 0.99685905
A114: Southport and Ormskirk Hospital NHS Trust | B114: RVY | C114: Staff per Attendance / 4 Hour Wait | D114: Consultant | E114: 0.082790595 | F114: 0.7875532
A115: St George's University Hospitals NHS Foundation Trust | B115: RJ7 | C115: Staff per Attendance / 4 Hour Wait | D115: Consultant | E115: 0.13156571 | F115: 0.82362988
A116: St Helens and Knowsley Hospitals NHS Trust | B116: RBN | C116: Staff per Attendance / 4 Hour Wait | D116: Consultant | E116: 0.067388308 | F116: 0.85150895
A117: Stockport NHS Foundation Trust | B117: RWJ | C117: Staff per Attendance / 4 Hour Wait | D117: Consultant | E117: 0.078177365 | F117: 0.79033772
A118: Surrey and Sussex Healthcare NHS Trust | B118: RTP | C118: Staff per Attendance / 4 Hour Wait | D118: Consultant | E118: 0.091120786 | F118: 0.91327326
A119: Tameside and Glossop Integrated Care NHS Foundation Trust | B119: RMP | C119: Staff per Attendance / 4 Hour Wait | D119: Consultant | E119: 0.11120235 | F119: 0.83427998
A120: Taunton and Somerset NHS Foundation Trust | B120: RBA | C120: Staff per Attendance / 4 Hour Wait | D120: Consultant | E120: 0.12228299 | F120: 0.90283612
A121: Torbay and South Devon NHS Foundation Trust | B121: RA9 | C121: Staff per Attendance / 4 Hour Wait | D121: Consultant | E121: 0.080752314 | F121: 0.88784935
A122: United Lincolnshire Hospitals NHS Trust | B122: RWD | C122: Staff per Attendance / 4 Hour Wait | D122: Consultant | E122: 0.09048534 | F122: 0.73940222
A123: University College London Hospitals NHS Foundation Trust | B123: RRV | C123: Staff per Attendance / 4 Hour Wait | D123: Consultant | E123: 0.0933907 | F123: 0.87568499
A124: University Hospital Southampton NHS Foundation Trust | B124: RHM | C124: Staff per Attendance / 4 Hour Wait | D124: Consultant | E124: 0.13001969 | F124: 0.87863591
A125: University Hospitals Birmingham NHS Foundation Trust | B125: RRK | C125: Staff per Attendance / 4 Hour Wait | D125: Consultant | E125: 0.14179537 | F125: 0.82896865
... A376: Queen Elizabeth Hospital King's Lynn NHS Foundation Trust | B376: RCX | C376: Staff per Attendance / 4 Hour Wait | D376: Nurse | E376: 0.7523588 | F376: 0.855112
A377: Queen Victoria Hospital NHS Foundation Trust | B377: RPC | C377: Staff per Attendance / 4 Hour Wait | D377: Nurse | E377: #DIV/0! | F377: 0.99689441
A378: Rotherham NHS Foundation Trust | B378: RFR | C378: Staff per Attendance / 4 Hour Wait | D378: Nurse | E378: 0.74994154 | F378: 0.82019833
...

Sheet stability_1
A1: Organisation name | B1: Organisation code | C1: Doctor | D1: Nurse | E1: Clinical (excl. Doctor and Nurse) | F1: 4hr% or less (<=) | G1: Over 12hr% (>)
A2: Derby Teaching Hospitals NHS Foundation Trust | B2: RTG | C2: 0.92307692 | D2: 0.8013245 | E2: 0.87628866 | F2: 0.81002094 | G2: 0.0011558004
A3: Kettering General Hospital NHS Foundation Trust | B3: RNQ | C3: 0.86363636 | D3: 0.73333333 | E3: 0.69565217 | F3: 0.76826489 | G3: 0.034630789
A4: Lincolnshire Community Health Services NHS Trust | B4: RY5 | D4: 0.375 | E4: 0.88235294 | F4: 0.99053911 | G4: 0.00012260328
A5: Northampton General Hospital NHS Trust | B5: RNS | C5: 0.91666667 | D5: 0.77669903 | E5: 0.68627451 | F5: 0.85110462 | G5: 0.034843689
A6: Nottingham University Hospitals NHS Trust | B6: RX1 | C6: 1 | D6: 0.71031746 | E6: 0.79439252 | F6: 0.79868085 | G6: 0.0099516547
A7: Sherwood Forest Hospitals NHS Foundation Trust | B7: RK5 | C7: 0.625 | D7: 0.8125 | E7: 0.84722222 | F7: 0.90903148 | G7: 0.0017732815
A8: United Lincolnshire Hospitals NHS Trust | B8: RWD | C8: 0.88461538 | D8: 0.78142077 | E8: 0.83333333 | F8: 0.73940222 | G8: 0.023319848
A9: University Hospitals of Leicester NHS Trust | B9: RWE | C9: 0.83333333 | D9: 0.77922078 | E9: 0.7443609 | F9: 0.77543447 | G9: 0.012108671
A10: Basildon and Thurrock University Hospitals NHS Foundation Trust | B10: RDD | C10: 0.95 | D10: 0.65625 | E10: 0.78181818 | F10: 0.85812324 | G10: 0.025745071
A11: Bedford Hospital NHS Trust | B11: RC1 | C11: 1 | D11: 0.82978723 | E11: 0.8125 | F11: 0.90379677 | G11: 0.0024890364
A12: Cambridge University Hospitals NHS Foundation Trust | B12: RGT | C12: 0.9 | D12: 0.78395062 | E12: 0.725 | F12: 0.89118556 | G12: 0.0027384785
A13: Colchester Hospital University NHS Foundation Trust | B13: RDE | C13: 0.86363636 | D13: 0.82191781 | E13: 0.71428571 | F13: 0.8257062 | G13: 0.016790676
A14: East and North Hertfordshire NHS Trust | B14: RWH | C14: 0.75 | D14: 0.85074627 | E14: 0.7254902 | F14: 0.80487735 | G14: 0.019416574
A15: Ipswich Hospital NHS Trust | B15: RGQ | C15: 0.7826087 | D15: 0.81609195 | E15: 0.79166667 | F15: 0.90717909 | G15: 0.00034760317
A16: James Paget University Hospitals NHS Foundation Trust | B16: RGP | C16: 0.86666667 | D16: 0.89795918 | E16: 0.91666667 | F16: 0.9049268 | G16: 0.013089039
... A46: Salisbury NHS Foundation Trust | B46: RNZ | C46: 0.7 | D46: 0.7173913 | E46: 0.91304348 | F46: 0.91707222 | G46: 0.0025955486
A47: Southern Health NHS Foundation Trust | B47: RW1 | D47: 0.85714286 | E47: 0.85714286 | F47: 0.99685905 | G47: 6.5436461e-05
A48: University Hospital Southampton NHS Foundation Trust | B48: RHM | C48: 0.875 | D48: 0.74468085 | E48: 0.5 | F48: 0.87863591 | G48: 0.0031427616
A49: Buckinghamshire Healthcare NHS Trust | B49: RXQ | C49: 0.8125 | D49: 0.60273973 | E49: 0.66666667 | F49: 0.75078388 | G49: 0.054356533
A50: Milton Keynes University Hospital NHS Foundation Trust | B50: RD8 | C50: 1 | D50: 0.80645161 | E50: 0.85 | F50: 0.85303573 | G50: 0.022079085
A51: Oxford University Hospitals NHS Foundation Trust | B51: RTH | C51: 0.96 | D51: 0.73758865 | E51: 0.86170213 | F51: 0.80364548 | G51: 0.03799153
A52: Royal Berkshire NHS Foundation Trust | B52: RHW | C52: 0.84615385 | D52: 0.69148936 | E52: 0.76 | F52: 0.88420922 | G52: 0.0047803888
A53: Chelsea and Westminster Hospital NHS Foundation Trust | B53: RQM | C53: 0.77777778 | D53: 0.76646707 | E53: 0.6 | F53: 0.87054495 | G53: 0.0054383916
A54: Hillingdon Hospitals NHS Foundation Trust | B54: RAS | C54: 0.88 | D54: 0.76744186 | E54: 0.6 | F54: 0.74292177 | G54: 0.031753786
A55: Hounslow and Richmond Community Healthcare NHS Trust | B55: RY9 | C55: 0 | D55: 0.66666667 | E55: 0.77777778 | F55: 0.99276479 | G55: 5.2239781e-05
A56: Imperial College Healthcare NHS Trust | B56: RYJ | C56: 0.85185185 | D56: 0.69411765 | E56: 0.6875 | F56: 0.8313508 | G56: 0.015411665
A57: London North West University Healthcare NHS Trust | B57: R1K | C57: 0.87878788 | D57: 0.74568966 | E57: 0.75423729 | F57: 0.58551534 | G57: 0.078225423
A58: Croydon Health Services NHS Trust | B58: RJ6 | C58: 0.88888889 | D58: 0.61956522 | E58: 0.73913043 | F58: 0.89180482 | G58: 0.0097667125
A59: Epsom and St Helier University Hospitals NHS Trust | B59: RVR | C59: 0.85714286 | D59: 0.73636364 | E59: 0.6875 | F59: 0.92594491 | G59: 0.007544991
... A77: Frimley Health NHS Foundation Trust | B77: RDU | C77: 0.78125 | D77: 0.76271186 | E77: 0.82291667 | F77: 0.88981919 | G77: 0.011706659
A78: Kent Community Health NHS Foundation Trust | B78: RYY | D78: 0.66666667 | E78: 1 | F78: 0.99832125 | G78: 9.1806891e-05
A79: Maidstone and Tunbridge Wells NHS Trust | B79: RWF | C79: 0.88888889 | D79: 0.69127517 | E79: 0.80597015 | F79: 0.89224885 | G79: 0.030786043
A80: Medway NHS Foundation Trust | B80: RPA | C80: 0.95652174 | D80: 0.82539683 | E80: 0.48571429 | F80: 0.83415204 | G80: 0.039388479
A81: Queen Victoria Hospital NHS Foundation Trust | B81: RPC | C81: 0 | E81: 0.77777778 | F81: 0.99689441 | G81: 0
A82: Royal Surrey County Hospital NHS Foundation Trust | B82: RA2 | C82: 0.66666667 | D82: 0.84057971 | E82: 0.70588235 | F82: 0.94885531 | G82: 0.0022978459
A83: Surrey and Sussex Healthcare NHS Trust | B83: RTP | C83: 0.78571429 | D83: 0.73626374 | E83: 0.70212766 | F83: 0.91327326 | G83: 0.034403159
A84: Western Sussex Hospitals NHS Foundation Trust | B84: RYR | C84: 0.91304348 | D84: 0.76190476 | E84: 0.76190476 | F84: 0.91622699 | G84: 0.0027699613
A85: City Hospitals Sunderland NHS Foundation Trust | B85: RLN | C85: 0.92307692 | D85: 0.84090909 | E85: 0.97058824 | F85: 0.91211079 | G85: 0.00046965639
A86: County Durham and Darlington NHS Foundation Trust | B86: RXP | C86: 0.86363636 | D86: 0.8411215 | E86: 0.81666667 | F86: 0.91409366 | G86: 0.0051388829
A87: Gateshead Health NHS Foundation Trust | B87: RR7 | C87: 1 | D87: 0.71621622 | E87: 0.78378378 | F87: 0.946174 | G87: 0.00026800612
A88: Newcastle Upon Tyne Hospitals NHS Foundation Trust | B88: RTD | C88: 0.95454545 | D88: 0.85087719 | E88: 0.80645161 | F88: 0.93738082 | G88: 0.0001881525
A89: North Tees and Hartlepool NHS Foundation Trust | B89: RVW | C89: 0.875 | D89: 0.57142857 | E89: 0.83018868 | F89: 0.95419291 | G89: 0.00018235308
A90: Northumbria Healthcare NHS Foundation Trust | B90: RTF | C90: 0.96875 | D90: 0.85714286 | E90: 0.88235294 | F90: 0.93233596 | G90: 0
A91: South Tees Hospitals NHS Foundation Trust | B91: RTR | C91: 0.88888889 | D91: 0.75590551 | E91: 0.9125 | F91: 0.94999534 | G91: 0.0001862949
A92: South Tyneside NHS Foundation Trust | B92: RE9 | C92: 1 | D92: 0.77358491 | E92: 0.85714286 | F92: 0.94229781 | G92: 0.0011153016
A93: Aintree University Hospital NHS Foundation Trust | B93: REM | C93: 0.83333333 | D93: 0.7173913 | E93: 0.79545455 | F93: 0.82522374 | G93: 0.020254557
... A98: East Cheshire NHS Trust | B98: RJN | C98: 0.84615385 | D98: 0.33333333 | E98: 0.8 | F98: 0.8117066 | G98: 0.024694541
A99: East Lancashire Hospitals NHS Trust | B99: RXR | D99: 0.9 | E99: 0.75 | F99: 0.79475256 | G99: 0.01634297
A100: Lancashire Teaching Hospitals NHS Foundation Trust | B100: RXN | C100: 0.91666667 | D100: 0.7706422 | E100: 0.86486486 | F100: 0.75357687 | G100: 0.025558249
A101: Mid Cheshire Hospitals NHS Foundation Trust | B101: RBT | C101: 0.71428571 | D101: 0.75471698 | E101: 0.82142857 | F101: 0.87225164 | G101: 0.0062819626
A102: North Cumbria University Hospitals NHS Trust | B102: RNL | C102: 0.7 | D102: 0.63076923 | E102: 0.82051282 | F102: 0.88072175 | G102: 0.008010984
A103: Pennine Acute Hospitals NHS Trust | B103: RW6 | C103: 0.86111111 | D103: 0.78017241 | E103: 0.87704918 | F103: 0.82308272 | G103: 0.018868785
A104: Royal Liverpool and Broadgreen University Hospitals NHS Trust | B104: RQ6 | C104: 0.95 | D104: 0.66 | E104: 0.87692308 | F104: 0.75589404 | G104: 0.072294785
A105: Salford Royal NHS Foundation Trust | B105: RM3 | C105: 0.93617021 | D105: 0.79906542 | E105: 0.77857143 | F105: 0.85284018 | G105: 0.0061312445
A106: Southport and Ormskirk Hospital NHS Trust | B106: RVY | C106: 0.93333333 | D106: 0.77669903 | E106: 0.89583333 | F106: 0.7875532 | G106: 0.032269934
A107: St Helens and Knowsley Hospitals NHS Trust | B107: RBN | C107: 0.85714286 | D107: 0.73913043 | E107: 0.875 | F107: 0.85150895 | G107: 0.030828633
A108: Stockport NHS Foundation Trust | B108: RWJ | C108: 0.75 | D108: 0.70652174 | E108: 0.75 | F108: 0.79033772 | G108: 0.032348543
A109: Tameside and Glossop Integrated Care NHS Foundation Trust | B109: RMP | C109: 0.92307692 | D109: 0.66233766 | E109: 0.73134328 | F109: 0.83427998 | G109: 0.01049294
A110: University Hospitals of Morecambe Bay NHS Foundation Trust | B110: RTX | C110: 0.88461538 | D110: 0.78205128 | E110: 0.8 | F110: 0.82252672 | G110: 0.0085115546
A111: Warrington and Halton Hospitals NHS Foundation Trust | B111: RWW | C111: 0.8125 | D111: 0.85542169 | E111: 0.76315789 | F111: 0.88786454 | G111: 0.019591786
... A121: Shrewsbury and Telford Hospital NHS Trust | B121: RXW | C121: 0.8125 | D121: 0.84810127 | E121: 0.82608696 | F121: 0.70467784 | G121: 0.041124917
A122: Shropshire Community Health NHS Trust | B122: R1D | D122: 0.5 | E122: 1 | F122: 0.99254638 | G122: 0.0014178077
A123: South Warwickshire NHS Foundation Trust | B123: RJC | C123: 1 | D123: 0.63636364 | E123: 0.85714286 | F123: 0.91403483 | G123: 0.0087002195
A124: University Hospitals Birmingham NHS Foundation Trust | B124: RRK | C124: 0.86666667 | D124: 0.75641026 | E124: 0.88095238 | F124: 0.82896865 | G124: 0.010778321
A125: University Hospitals Coventry and Warwickshire NHS Trust | B125: RKB | C125: 0.85 | D125: 0.775 | E125: 0.8 | F125: 0.80049958 | G125: 0.023104086
A126: University Hospitals of North Midlands NHS Trust | B126: RJE | C126: 0.81081081 | D126: 0.69581749 | E126: 0.76315789 | F126: 0.66691973 | G126: 0.079279884
A127: Walsall Healthcare NHS Trust | B127: RBK | C127: 0.8 | D127: 0.76271186 | E127: 0.81132075 | F127: 0.69433536 | G127: 0.027187118
A128: Worcestershire Acute Hospitals NHS Trust | B128: RWP | C128: 0.92307692 | D128: 0.72222222 | E128: 0.79545455 | F128: 0.79083572 | G128: 0.053682326
A129: Wye Valley NHS Trust | B129: RLQ | C129: 0.875 | D129: 0.675 | E129: 0.92 | F129: 0.73422794 | G129: 0.025508057
A130: Gloucestershire Hospitals NHS Foundation Trust | B130: RTE | C130: 1 | D130: 0.85915493 | E130: 0.765625 | F130: 0.86700177 | G130: 0.0028743363
A131: Great Western Hospitals NHS Foundation Trust | B131: RN3 | C131: 1 | D131: 0.77272727 | E131: 0.83928571 | F131: 0.84341256 | G131: 0.02840914
A132: North Bristol NHS Trust | B132: RVJ | C132: 0.95 | D132: 0.775 | E132: 0.63636364 | F132: 0.75758894 | G132: 0.034316194
A133: Northern Devon Healthcare NHS Trust | B133: RBZ | C133: 0.69230769 | D133: 0.81395349 | E133: 0.86666667 | F133: 0.86917764 | G133: 0.032800521
A134: Royal Cornwall Hospitals NHS Trust | B134: REF | C134: 0.8 | D134: 0.7804878 | E134: 0.828125 | F134: 0.87375079 | G134: 0.012172755
... A136: Royal United Hospitals Bath NHS Foundation Trust | B136: RD1 | C136: 1 | D136: 0.73626374 | E136: 0.81609195 | F136: 0.79605354 | G136: 0.023479632
A137: Somerset Partnership NHS Foundation Trust | B137: RH5 | D137: 0.81034483 | E137: 0.8 | F137: 0.99733489 | G137: 2.600104e-05
A138: Taunton and Somerset NHS Foundation Trust | B138: RBA | C138: 1 | D138: 0.71875 | E138: 0.73333333 | F138: 0.90283612 | G138: 0.0003805926
A139: Torbay and South Devon NHS Foundation Trust | B139: RA9 | C139: 0.875 | D139: 0.78761062 | E139: 0.8317757 | F139: 0.88784935 | G139: 0.0040135618
A140: University Hospitals Bristol NHS Foundation Trust | B140: RA7 | C140: 0.95 | D140: 0.73376623 | E140: 0.68333333 | F140: 0.86644288 | G140: 0.0050725449
A141: University Hospitals Plymouth NHS Trust | B141: RK9 | C141: 0.96153846 | D141: 0.73333333 | E141: 0.71428571 | F141: 0.83413299 | G141: 0.0021470705
A142: Weston Area Health NHS Trust | B142: RA3 | C142: 0.85714286 | D142: 0.68 | E142: 0.62962963 | F142: 0.84232788 | G142: 0.027419389
A143: Yeovil District Hospital NHS Foundation Trust | B143: RA4 | C143: 0.77777778 | D143: 0.76271186 | E143: 0.73913043 | F143: 0.93913785 | G143: 0.0057926164

Sheet Timeseries_data
A1: Rate of: | B1: 2009-10 | C1: 2010-11 | D1: 2011-12 | E1: 2012-13 | F1: 2013-14 | G1: 2014-15 | H1: 2015-16 | I1: 2016-17 | J1: 2017-18
A2: Doctors | B2: 0.30123449 | C2: 0.30269764 | D2: 0.28023798 | E2: 0.27911374 | F2: 0.28325948 | G2: 0.28279896 | H2: 0.27271965 | I2: 0.2890925 | J2: 0.28506735 | L2: Bar chart
A3: Nurses | B3: 0.70466503 | C3: 0.70067787 | D3: 0.66028262 | E3: 0.6456685 | F3: 0.65655776 | G3: 0.64282129 | H3: 0.6345127 | I3: 0.6540814 | J3: 0.65847189 | L3: Bar chart
A4: Other clinical staff | B4: 0.4878615 | C4: 0.52897426 | D4: 0.4956074 | E4: 0.48776872 | F4: 0.50932515 | G4: 0.50892144 | H4: 0.49623361 | I4: 0.5284162 | J4: 0.52913798 | L4: Bar chart
A5: 4 hour target | B5: 0.95778446 | C5: 0.9423444 | D5: 0.94578255 | E5: 0.94230986 | F5: 0.9365582 | G5: 0.9137216 | H5: 0.89127036 | I5: 0.86271758 | J5: 0.85473868 | L5: line
A8: Rate of: | B8: 2009-10 | C8: 2010-11 | D8: 2011-12 | E8: 2012-13 | F8: 2013-14 | G8: 2014-15 | H8: 2015-16 | I8: 2016-17 | J8: 2017-18
A9: Doctors | B9: 0.30123449 | C9: 0.30269764 | D9: 0.28023798 | E9: 0.27911374 | F9: 0.28325948 | G9: 0.28279896 | H9: 0.27271965 | I9: 0.2890925 | J9: 0.28506735 | L9: Bar chart
A10: Nurses | B10: 0.70466503 | C10: 0.70067787 | D10: 0.66028262 | E10: 0.6456685 | F10: 0.65655776 | G10: 0.64282129 | H10: 0.6345127 | I10: 0.6540814 | J10: 0.65847189 | L10: Bar chart
A11: Other clinical staff | B11: 0.4878615 | C11: 0.52897426 | D11: 0.4956074 | E11: 0.48776872 | F11: 0.50932515 | G11: 0.50892144 | H11: 0.49623361 | I11: 0.5284162 | J11: 0.52913798 | L11: Bar chart
A12: 12 hour target | B12: 0.0035421336 | C12: 0.0086652339 | D12: 0.0033388775 | E12: 0.0036537856 | F12: 0.0056369189 | G12: 0.0089369158 | H12: 0.0097734186 | I12: 0.012733929 | J12: 0.015848071 | L12: line
A14: Total Unplanned | B14: 15079612 | C14: 15818846 | D14: 17286648 | E14: 18005435 | F14: 18197530 | G14: 19254853 | H14: 20168071 | I14: 20603774 | J14: 21011705
A15: <= 4 hours wait | B15: 14443018 | C15: 14906801 | D15: 16349410 | E15: 16966699 | F15: 17043046 | G15: 17593575 | H15: 17975204 | I15: 17775238 | J15: 17959517
A16: Over 12 hours wait | B16: 53414 | C16: 137074 | D16: 57718 | E16: 65788 | F16: 102578 | G16: 172079 | H16: 197111 | I16: 262367 | J16: 332995 | L16: Summary Report 9
A18: NHS Trusts and CCGs, as at the last day of September
A19: FTE | B19: 40057 | C19: 40422 | D19: 40787 | E19: 41153 | F19: 41518 | G19: 41883 | H19: 42248 | I19: 42614 | J19: 42979
A20: HCHS Doctors | B20: 4542.4993 | C20: 4788.3273 | D20: 4844.3753 | E20: 5025.5643 | F20: 5154.6228 | G20: 5445.2524 | H20: 5500.2292 | I20: 5956.3966 | J20: 5989.751
A21: Nurses & health visitors | B21: 10626.075 | C21: 11083.915 | D21: 11414.073 | E21: 11625.542 | F21: 11947.73 | G21: 12377.43 | H21: 12796.897 | I21: 13476.545 | J21: 13835.617
A22: Total clinical staff exl doctors and nurses | B22: 7356.7622 | C22: 8367.7624 | D22: 8567.3906 | E22: 8782.4879 | F22: 9268.4597 | G22: 9799.2075 | H22: 10008.075 | I22: 10887.368 | J22: 11118.091

Sheet Org_Control
A5: Measure | B5: Staff Group
A6: Staff per Attendance / TTS 4 Hour | B6: Consultant
B7: Doctor (excl. Consultant)
B8: Nurse
B9: Care Provider (excl. Doctor and Nurse)
A10: Staff per Attendance / TTS 4 Hour Total
A11: Staff per Attendance / TTS 12 Hour | B11: Consultant
B12: Doctor (excl. Consultant)
B13: Nurse
B14: Care Provider (excl. Doctor and Nurse)
A15: Staff per Attendance / TTS 12 Hour Total
A16: Stability Index / TTS 4 Hour | B16: Doctor
B17: Nurse
B18: Care Provider (excl. Doctor and Nurse)
A19: Stability Index / TTS 4 Hour Total
A20: Stability Index / TTS 12 Hour | B20: Doctor
B21: Nurse
B22: Care Provider (excl. Doctor and Nurse)
A23: Stability Index / TTS 12 Hour Total

Sheet Pivot_tables
A1: Select Measure | B1: (All) | E1: National | F1: =VLOOKUP(E1,E5:G226,2,FALSE) -> 7.6279785 | G1: =VLOOKUP(E1,E5:G211,3,FALSE) -> 6.0326221
A2: Selelct Staff Group | B2: (All)
B4: Values
A5: Organisation name | B5: Sum of Staff Rate | C5: Sum of Measure Rate | E5: =A5 -> Organisation name | F5: =B5 -> Sum of Staff Rate | G5: =C5 -> Sum of Measure Rate
A6: Aintree University Hospital NHS Foundation Trust | B6: 6.8078964 | C6: 5.9184253 | E6: =IF(A6="",NA(),A6) -> Aintree University Hospital NHS Foundation Trust | F6: =IF(B6="",NA(),B6) -> 6.8078964 | G6: =IF(C6="",NA(),C6) -> 5.9184253
A7: Airedale NHS Foundation Trust | B7: 8.4882421 | C7: 6.439245 | E7: =IF(A7="",NA(),A7) -> Airedale NHS Foundation Trust | F7: =IF(B7="",NA(),B7) -> 8.4882421 | G7: =IF(C7="",NA(),C7) -> 6.439245
A8: Alder Hey Children's NHS Foundation Trust | B8: 6.9820615 | C8: 6.640427 | E8: =IF(A8="",NA(),A8) -> Alder Hey Children's NHS Foundation Trust | F8: =IF(B8="",NA(),B8) -> 6.9820615 | G8: =IF(C8="",NA(),C8) -> 6.640427
A9: Ashford and St. Peter's Hospitals NHS Foundation Trust | B9: 7.4131313 | C9: 6.1608997 | E9: =IF(A9="",NA(),A9) -> Ashford and St. Peter's Hospitals NHS Foundation Trust | F9: =IF(B9="",NA(),B9) -> 7.4131313 | G9: =IF(C9="",NA(),C9) -> 6.1608997
A10: Barking, Havering and Redbridge University Hospitals NHS Trust | B10: 6.1752534 | C10: 5.7575514 | E10: =IF(A10="",NA(),A10) -> Barking, Havering and Redbridge University Hospitals NHS Trust | F10: =IF(B10="",NA(),B10) -> 6.1752534 | G10: =IF(C10="",NA(),C10) -> 5.7575514
A11: Barnsley Hospital NHS Foundation Trust | B11: 7.9832858 | C11: 6.3677657 | E11: =IF(A11="",NA(),A11) -> Barnsley Hospital NHS Foundation Trust | F11: =IF(B11="",NA(),B11) -> 7.9832858 | G11: =IF(C11="",NA(),C11) -> 6.3677657
A12: Barts Health NHS Trust | B12: 7.4084985 | C12: 5.7934733 | E12: =IF(A12="",NA(),A12) -> Barts Health NHS Trust | F12: =IF(B12="",NA(),B12) -> 7.4084985 | G12: =IF(C12="",NA(),C12) -> 5.7934733
A13: Basildon and Thurrock University Hospitals NHS Foundation Trust | B13: 7.1491709 | C13: 6.1869216 | E13: =IF(A13="",NA(),A13) -> Basildon and Thurrock University Hospitals NHS Foundation Trust | F13: =IF(B13="",NA(),B13) -> 7.1491709 | G13: =IF(C13="",NA(),C13) -> 6.1869216
A14: Bedford Hospital NHS Trust | B14: 7.7515892 | C14: 6.3441101 | E14: =IF(A14="",NA(),A14) -> Bedford Hospital NHS Trust | F14: =IF(B14="",NA(),B14) -> 7.7515892 | G14: =IF(C14="",NA(),C14) -> 6.3441101
A15: Birmingham Women's and Children's NHS Foundation Trust | B15: 7.6546236 | C15: 6.5022666 | E15: =IF(A15="",NA(),A15) -> Birmingham Women's and Children's NHS Foundation Trust | F15: =IF(B15="",NA(),B15) -> 7.6546236 | G15: =IF(C15="",NA(),C15) -> 6.5022666
A16: Blackpool Teaching Hospitals NHS Foundation Trust | B16: 7.9247872 | C16: 4.6410658 | E16: =IF(A16="",NA(),A16) -> Blackpool Teaching Hospitals NHS Foundation Trust | F16: =IF(B16="",NA(),B16) -> 7.9247872 | G16: =IF(C16="",NA(),C16) -> 4.6410658
A17: Bolton NHS Foundation Trust | B17: 7.9203745 | C17: 5.749514 | E17: =IF(A17="",NA(),A17) -> Bolton NHS Foundation Trust | F17: =IF(B17="",NA(),B17) -> 7.9203745 | G17: =IF(C17="",NA(),C17) -> 5.749514
... A150: National | B150: 7.6279785 | C150: 6.0326221 | E150: =IF(A150="",NA(),A150) -> National | F150: =IF(B150="",NA(),B150) -> 7.6279785 | G150: =IF(C150="",NA(),C150) -> 6.0326221
E151: =IF(A151="",NA(),A151) -> #N/A | F151: =IF(B151="",NA(),B151) -> #N/A | G151: =IF(C151="",NA(),C151) -> #N/A
E152: =IF(A152="",NA(),A152) -> #N/A | F152: =IF(B152="",NA(),B152) -> #N/A | G152: =IF(C152="",NA(),C152) -> #N/A
E153: =IF(A153="",NA(),A153) -> #N/A | F153: =IF(B153="",NA(),B153) -> #N/A | G153: =IF(C153="",NA(),C153) -> #N/A
E154: =IF(ISBLANK(A154),"",A154)

Sheet Org2_Control
A5: Measure | B5: Staff Group
A6: Staff per Attendance / TTS 4 Hour | B6: Consultant
B7: Doctor (excl. Consultant)
B8: Nurse
B9: Care Provider (excl. Doctor and Nurse)
A10: Staff per Attendance / TTS 12 Hour | B10: Consultant
B11: Doctor (excl. Consultant)
B12: Nurse
B13: Care Provider (excl. Doctor and Nurse)
A14: Stability Index / TTS 4 Hour | B14: Doctor
B15: Nurse
B16: Care Provider (excl. Doctor and Nurse)
A17: Stability Index / TTS 12 Hour | B17: Doctor
B18: Nurse
B19: Care Provider (excl. Doctor and Nurse)
A20: Grand Total

Sheet Pivot2_table
A1: Measure | B1: (All) | E1: National | F1: =VLOOKUP(E1,E5:G226,2,FALSE) -> 7.6279785 | G1: =VLOOKUP(E1,E5:G211,3,FALSE) -> 6.0326221
A2: Staff Group | B2: (All)
A4: Row Labels | B4: Sum of Staff Rate | C4: Sum of Measure Rate | E4: Organisation name | F4: =B4 -> Sum of Staff Rate | G4: =C4 -> Sum of Measure Rate
A5: Aintree University Hospital NHS Foundation Trust | B5: 6.8078964 | C5: 5.9184253 | E5: =IF(A5="",NA(),A5) -> Aintree University Hospital NHS Foundation Trust | F5: =IF(B5="",NA(),B5) -> 6.8078964 | G5: =IF(C5="",NA(),C5) -> 5.9184253
A6: Airedale NHS Foundation Trust | B6: 8.4882421 | C6: 6.439245 | E6: =IF(A6="",NA(),A6) -> Airedale NHS Foundation Trust | F6: =IF(B6="",NA(),B6) -> 8.4882421 | G6: =IF(C6="",NA(),C6) -> 6.439245
A7: Alder Hey Children's NHS Foundation Trust | B7: 6.9820615 | C7: 6.640427 | E7: =IF(A7="",NA(),A7) -> Alder Hey Children's NHS Foundation Trust | F7: =IF(B7="",NA(),B7) -> 6.9820615 | G7: =IF(C7="",NA(),C7) -> 6.640427
A8: Ashford and St. Peter's Hospitals NHS Foundation Trust | B8: 7.4131313 | C8: 6.1608997 | E8: =IF(A8="",NA(),A8) -> Ashford and St. Peter's Hospitals NHS Foundation Trust | F8: =IF(B8="",NA(),B8) -> 7.4131313 | G8: =IF(C8="",NA(),C8) -> 6.1608997
A9: Barking, Havering and Redbridge University Hospitals NHS Trust | B9: 6.1752534 | C9: 5.7575514 | E9: =IF(A9="",NA(),A9) -> Barking, Havering and Redbridge University Hospitals NHS Trust | F9: =IF(B9="",NA(),B9) -> 6.1752534 | G9: =IF(C9="",NA(),C9) -> 5.7575514
A10: Barnsley Hospital NHS Foundation Trust | B10: 7.9832858 | C10: 6.3677657 | E10: =IF(A10="",NA(),A10) -> Barnsley Hospital NHS Foundation Trust | F10: =IF(B10="",NA(),B10) -> 7.9832858 | G10: =IF(C10="",NA(),C10) -> 6.3677657
A11: Barts Health NHS Trust | B11: 7.4084985 | C11: 5.7934733 | E11: =IF(A11="",NA(),A11) -> Barts Health NHS Trust | F11: =IF(B11="",NA(),B11) -> 7.4084985 | G11: =IF(C11="",NA(),C11) -> 5.7934733
A12: Basildon and Thurrock University Hospitals NHS Foundation Trust | B12: 7.1491709 | C12: 6.1869216 | E12: =IF(A12="",NA(),A12) -> Basildon and Thurrock University Hospitals NHS Foundation Trust | F12: =IF(B12="",NA(),B12) -> 7.1491709 | G12: =IF(C12="",NA(),C12) -> 6.1869216
A13: Bedford Hospital NHS Trust | B13: 7.7515892 | C13: 6.3441101 | E13: =IF(A13="",NA(),A13) -> Bedford Hospital NHS Trust | F13: =IF(B13="",NA(),B13) -> 7.7515892 | G13: =IF(C13="",NA(),C13) -> 6.3441101
A14: Birmingham Women's and Children's NHS Foundation Trust | B14: 7.6546236 | C14: 6.5022666 | E14: =IF(A14="",NA(),A14) -> Birmingham Women's and Children's NHS Foundation Trust | F14: =IF(B14="",NA(),B14) -> 7.6546236 | G14: =IF(C14="",NA(),C14) -> 6.5022666
A15: Blackpool Teaching Hospitals NHS Foundation Trust | B15: 7.9247872 | C15: 4.6410658 | E15: =IF(A15="",NA(),A15) -> Blackpool Teaching Hospitals NHS Foundation Trust | F15: =IF(B15="",NA(),B15) -> 7.9247872 | G15: =IF(C15="",NA(),C15) -> 4.6410658
A16: Bolton NHS Foundation Trust | B16: 7.9203745 | C16: 5.749514 | E16: =IF(A16="",NA(),A16) -> Bolton NHS Foundation Trust | F16: =IF(B16="",NA(),B16) -> 7.9203745 | G16: =IF(C16="",NA(),C16) -> 5.749514
... A149: York Teaching Hospital NHS Foundation Trust | B149: 7.8398783 | C149: 5.6623669 | E149: =IF(A149="",NA(),A149) -> York Teaching Hospital NHS Foundation Trust | F149: =IF(B149="",NA(),B149) -> 7.8398783 | G149: =IF(C149="",NA(),C149) -> 5.6623669
E150: =IF(A150="",NA(),A150) -> #N/A | F150: =IF(B150="",NA(),B150) -> #N/A | G150: =IF(C150="",NA(),C150) -> #N/A
E151: =IF(A151="",NA(),A151) -> #N/A | F151: =IF(B151="",NA(),B151) -> #N/A | G151: =IF(C151="",NA(),C151) -> #N/A
E152: =IF(A152="",NA(),A152) -> #N/A | F152: =IF(B152="",NA(),B152) -> #N/A | G152: =IF(C152="",NA(),C152) -> #N/A
E153: =IF(A153="",NA(),A153) -> #N/A | F153: =IF(B153="",NA(),B153) -> #N/A | G153: =IF(C153="",NA(),C153) -> #N/A

Sheet Provider_data
A1: Organisation name | B1: Organisation code | C1: Region | D1: Measure | E1: Staff Group | F1: Staff Rate | G1: Measure Rate
A2: National | B2: National | C2: National | D2: Staff per Attendance / TTS 4 Hour | E2: Consultant | F2: 0.089418076 | G2: 0.84495774
A3: National | B3: National | C3: National | D3: Staff per Attendance / TTS 4 Hour | E3: Doctor (excl. Consultant) | F3: 0.23697189 | G3: 0.84495774
A4: National | B4: National | C4: National | D4: Staff per Attendance / TTS 4 Hour | E4: Nurse | F4: 0.74818728 | G4: 0.84495774
A5: National | B5: National | C5: National | D5: Staff per Attendance / TTS 4 Hour | E5: Care Provider (excl. Doctor and Nurse) | F5: 0.39741427 | G5: 0.84495774
A6: National | B6: National | C6: National | D6: Staff per Attendance / TTS 12 Hour | E6: Consultant | F6: 0.089418076 | G6: 0.016845423
A7: National | B7: National | C7: National | D7: Staff per Attendance / TTS 12 Hour | E7: Doctor (excl. Consultant) | F7: 0.23697189 | G7: 0.016845423
A8: National | B8: National | C8: National | D8: Staff per Attendance / TTS 12 Hour | E8: Nurse | F8: 0.74818728 | G8: 0.016845423
A9: National | B9: National | C9: National | D9: Staff per Attendance / TTS 12 Hour | E9: Care Provider (excl. Doctor and Nurse) | F9: 0.39741427 | G9: 0.016845423
A10: National | B10: National | C10: National | D10: Stability Index / TTS 4 Hour | E10: Doctor | F10: 0.84366472 | G10: 0.84495774
A11: National | B11: National | C11: National | D11: Stability Index / TTS 4 Hour | E11: Nurse | F11: 0.726593 | G11: 0.84495774
A12: National | B12: National | C12: National | D12: Stability Index / TTS 4 Hour | E12: Care Provider (excl. Doctor and Nurse) | F12: 0.77174 | G12: 0.84495774
A13: National | B13: National | C13: National | D13: Stability Index / TTS 12 Hour | E13: Doctor | F13: 0.84366472 | G13: 0.016845423
... A1979: London North West University Healthcare NHS Trust | B1979: R1K | C1979: London Commissioning Region | D1979: Staff per Attendance / TTS 12 Hour | E1979: Care Provider (excl. Doctor and Nurse) | F1979: 0.78169732 | G1979: 0.078225978

Sheet Pivot_table2
C3: Values
A4: Select Provider | B4: Org code | C4: Sum of Total Unplanned | D4: Sum of 4hr % | E4: Sum of 12hr % | F4: Sum of Consultant (including Directors of Public Health) | G4: Sum of Other Doctors | H4: Sum of Nurses & health visitors | I4: Sum of Other Clinical Staff | J4: Sum of Rate Total | K4: Sum of Rate Consultant | L4: Sum of Rate Other Doctors | M4: Sum of Rate Nurses | N4: Sum of Rate other Clinical | O4: Sum of Total Clinical Staff, excl. doc and nur (SI) | P4: Sum of HCHS Doctors1 (SI) | Q4: Sum of Total Clinical Staff (SI) | R4: Sum of Nurses & health visitors (SI)
A5: Aintree University Hospital NHS Foundation Trust | B5: REM | C5: 167270 | D5: 0.82522269 | E5: 0.020266635 | F5: 15 | G5: 21.036365 | H5: 99.479993 | I5: 41.416663 | J5: 1.057769 | K5: 0.089675375 | L5: 0.12576293 | M5: 0.59472704 | N5: 0.24760365 | O5: 0.79545455 | P5: 0.83333333 | Q5: 0.75324675 | R5: 0.7173913
A6: Airedale NHS Foundation Trust | B6: RCF | C6: 57485 | D6: 0.9188484 | E6: 0.0010437505 | F6: 7.6 | G6: 17.373438 | H6: 38.573325 | I6: 28.730007 | J6: 1.6052321 | K6: 0.1322084 | L6: 0.30222558 | M6: 0.67101548 | N6: 0.49978268 | O6: 0.80555556 | P6: 1 | Q6: 0.84615385 | R6: 0.83333333
A7: Alder Hey Children's NHS Foundation Trust | B7: RBS | C7: 59960 | D7: 0.94863242 | F7: 8.2 | G7: 5.182 | H7: 43.158317 | I7: 5.71333 | J7: 1.038253 | K7: 0.13675784 | L7: 0.086424283 | M7: 0.71978515 | N7: 0.09528569 | O7: 0.77777778 | P7: 0.8 | Q7: 0.84745763 | R7: 0.875
A8: Ashford and St. Peter's Hospitals NHS Foundation Trust | B8: RTK | C8: 101150 | D8: 0.84997528 | E8: 0.030153238 | F8: 6.75 | G8: 14.25 | H8: 69.853297 | I8: 29.265932 | J8: 1.1875356 | K8: 0.066732575 | L8: 0.14087988 | M8: 0.69059118 | N8: 0.28933201 | O8: 0.81081081 | P8: 0.9 | Q8: 0.825 | R8: 0.80821918
A9: Barking, Havering and Redbridge University Hospitals NHS Trust | B9: RF4 | C9: 255250 | D9: 0.79653281 | E9: 0.025974535 | F9: 8.4 | G9: 37.45 | H9: 140.36613 | I9: 64.991595 | J9: 0.98416348 | K9: 0.032908913 | L9: 0.1467189 | M9: 0.54991629 | N9: 0.25461937 | O9: 0.68831169 | P9: 0.68181818 | Q9: 0.71590909 | R9: 0.73333333
A10: Barnsley Hospital NHS Foundation Trust | B10: RFF | C10: 85530 | D10: 0.90477026 | E10: 0.0049105577 | F10: 12.64395 | G10: 22.075 | H10: 64.59 | I10: 39.216752 | J10: 1.6196154 | K10: 0.14783059 | L10: 0.25809657 | M10: 0.75517362 | N10: 0.45851459 | O10: 0.68085106 | P10: 1 | Q10: 0.71875 | R10: 0.69117647
A11: Barts Health NHS Trust | B11: R1H | C11: 437280 | D11: 0.81487834 | E11: 0.012760703 | F11: 46.5 | G11: 121 | H11: 300.05782 | I11: 140.34467 | J11: 1.3901905 | K11: 0.10633919 | L11: 0.27671057 | M11: 0.6861915 | N11: 0.32094922 | O11: 0.79861111 | P11: 0.82692308 | Q11: 0.73852295 | R11: 0.68852459
A12: Basildon and Thurrock University Hospitals NHS Foundation Trust | B12: RDD | C12: 123715 | D12: 0.85810128 | E12: 0.025744655 | F12: 8.5 | G12: 33 | H12: 57.823318 | I12: 47.466665 | J12: 1.1865173 | K12: 0.068706301 | L12: 0.26674211 | M12: 0.46739132 | N12: 0.38367752 | O12: 0.78181818 | P12: 0.95 | Q12: 0.75539568 | R12: 0.65625
A13: Bedford Hospital NHS Trust | B13: RC1 | C13: 75935 | D13: 0.9037993 | E13: 0.00250214 | F13: 5.5 | G13: 21.329688 | H13: 49.170027 | I13: 17.666667 | J13: 1.2335074 | K13: 0.072430368 | L13: 0.28089402 | M13: 0.64752785 | N13: 0.23265513 | O13: 0.8125 | P13: 1 | Q13: 0.875 | R13: 0.82978723
A14: Birmingham Women's and Children's NHS Foundation Trust | B14: RQ3 | C14: 59560 | D14: 0.92839154 | E14: 0.00050369375 | F14: 5.5625 | G14: 18.86875 | H14: 49.63334 | I14: 16.12 | J14: 1.5141805 | K14: 0.093393217 | L14: 0.31680238 | M14: 0.83333345 | N14: 0.27065144 | O14: 0.72222222 | P14: 0.9 | Q14: 0.72289157 | R14: 0.69090909
A15: Blackpool Teaching Hospitals NHS Foundation Trust | B15: RXL | C15: 79750 | D15: 0.59015674 | E15: 0.072852665 | F15: 7.00625 | G15: 29.925 | H15: 78.943335 | I15: 46.240007 | J15: 2.0327849 | K15: 0.087852665 | L15: 0.37523511 | M15: 0.98988508 | N15: 0.57981201 | O15: 0.39130435 | P15: 0.90909091 | Q15: 0.57534247 | R15: 0.62921348
A16: Bolton NHS Foundation Trust | B16: RMC | C16: 113160 | D16: 0.81508484 | E16: 0.0062743019 | F16: 10.4 | G16: 29.357812 | H16: 98.10334 | I16: 29.526663 | J16: 1.4792136 | K16: 0.091905267 | L16: 0.25943631 | M16: 0.86694362 | N16: 0.26092844 | O16: 0.75862069 | P16: 0.88235294 | Q16: 0.82876712 | R16: 0.84
A17: Bradford Teaching Hospitals NHS Foundation Trust | B17: RAE | C17: 134270 | D17: 0.79463022 | E17: 0.0059953824 | F17: 15.0125 | G17: 35.677625 | H17: 82.499995 | I17: 52.669645 | J17: 1.3842241 | K17: 0.1118083 | L17: 0.26571554 | M17: 0.61443357 | N17: 0.39226666 | O17: 0.75806452 | P17: 0.94736842 | Q17: 0.78531073 | R17: 0.77083333
A18: Brighton and Sussex University Hospitals NHS Trust | B18: RXH | C18: 158120 | D18: 0.82854794 | E18: 0.039874779 | F18: 19.24375 | G18: 77.561972 | H18: 192.42658 | I18: 84.798285 | J18: 2.3654857 | K18: 0.12170345 | L18: 0.49052601 | M18: 1.2169655 | N18: 0.5362907 | O18: 0.76404494 | P18: 0.92592593 | Q18: 0.77477477 | R18: 0.76036866
A19: Buckinghamshire Healthcare NHS Trust | B19: RXQ | C19: 87385 | D19: 0.75081536 | E19: 0.054357155 | F19: 9.05625 | G19: 24.9 | H19: 54.678635 | I19: 29.452658 | J19: 1.351348 | K19: 0.10363621 | L19: 0.28494593 | M19: 0.62572106 | N19: 0.33704477 | O19: 0.66666667 | P19: 0.8125 | Q19: 0.648 | R19: 0.60273973
... A23: Chelsea and Westminster Hospital NHS Foundation Trust | B23: RQM | C23: 206310 | D23: 0.87055887 | E23: 0.0054287238 | F23: 17.5625 | G23: 85.003125 | H23: 166.54072 | I23: 43.883333 | J23: 1.5170844 | K23: 0.085126751 | L23: 0.4120165 | M23: 0.80723534 | N23: 0.21270579 | O23: 0.6 | P23: 0.77777778 | Q23: 0.74418605 | R23: 0.76646707
A24: Chesterfield Royal Hospital NHS Foundation Trust | B24: RFS | C24: 81280 | D24: 0.91664616 | E24: 0.00036909449 | F24: 8.0825 | G24: 21.7 | H24: 50.2225 | I24: 40.8225 | J24: 1.4865588 | K24: 0.099440207 | L24: 0.26697835 | M24: 0.61789493 | N24: 0.50224532 | O24: #N/A | P24: #N/A | Q24: #N/A | R24: #N/A
A25: City Hospitals Sunderland NHS Foundation Trust | B25: RLN | C25: 157560 | D25: 0.91212871 | E25: 0.00047600914 | F25: 10.4 | G25: 28.659375 | H25: 117.91001 | I25: 40.323332 | J25: 1.2521751 | K25: 0.066006601 | L25: 0.18189499 | M25: 0.74834987 | N25: 0.25592366 | O25: 0.97058824 | P25: 0.92307692 | Q25: 0.87150838 | R25: 0.84090909
A26: Colchester Hospital University NHS Foundation Trust | B26: RDE | C26: 91120 | D26: 0.82572432 | E26: 0.016791045 | F26: 11.25 | G26: 23.94375 | H26: 91.754993 | I26: 56.06272 | J26: 2.0084664 | K26: 0.12346356 | L26: 0.26277162 | M26: 1.0069687 | N26: 0.61526251 | O26: 0.71428571 | P26: 0.86363636 | Q26: 0.80487805 | R26: 0.82191781
A27: Countess of Chester Hospital NHS Foundation Trust | B27: RJR | C27: 82725 | D27: 0.83723179 | E27: 0.002175884 | F27: 7.85 | G27: 21.2625 | H27: 64.485 | I27: 21.4 | J27: 1.3901179 | K27: 0.094892717 | L27: 0.25702629 | M27: 0.77951043 | N27: 0.25868843 | O27: 0.8 | P27: 0.64705882 | Q27: 0.78991597 | R27: 0.80519481
A28: County Durham and Darlington NHS Foundation Trust | B28: RXP | C28: 210355 | D28: 0.9140976 | E28: 0.0051341779 | F28: 10.81 | G28: 35.1625 | H28: 106.29667 | I28: 47.935685 | J28: 0.95174753 | K28: 0.051389318 | L28: 0.1671579 | M28: 0.50532038 | N28: 0.22787994 | O28: 0.81666667 | P28: 0.86363636 | Q28: 0.85714286 | R28: 0.8411215
A29: Croydon Health Services NHS Trust | B29: RJ6 | C29: 176005 | D29: 0.89182126 | E29: 0.0097724496 | F29: 7.525 | G29: 22.770313 | H29: 78.875107 | I29: 60.541648 | J29: 0.96424572 | K29: 0.042754467 | L29: 0.1293731 | M29: 0.44814129 | N29: 0.34397686 | O29: 0.73913043 | P29: 0.88888889 | Q29: 0.72352941 | R29: 0.61956522
A30: Dartford and Gravesham NHS Trust | B30: RN7 | C30: 125700 | D30: 0.87871917 | E30: 0.021519491 | F30: 8 | G30: 26.775 | H30: 63.993712 | I30: 42.44664 | J30: 1.1234316 | K30: 0.063643596 | L30: 0.21300716 | M30: 0.50909875 | N30: 0.3376821 | O30: 0.78 | P30: 0.77777778 | Q30: 0.81506849 | R30: 0.85507246
A31: Derby Teaching Hospitals NHS Foundation Trust | B31: RTG | C31: 133240 | D31: 0.81004203 | E31: 0.0011633143 | F31: 16.3083 | G31: 53.604688 | H31: 132.49934 | I31: 88.243313 | J31: 2.1814443 | K31: 0.12239793 | L31: 0.40231678 | M31: 0.99444118 | N31: 0.66228845 | O31: 0.87628866 | P31: 0.92307692 | Q31: 0.84320557 | R31: 0.8013245
A32: Doncaster and Bassetlaw Teaching Hospitals NHS Foundation Trust | B32: RP5 | C32: 159635 | D32: 0.91017008 | E32: 0.0016287155 | F32: 14.05 | G32: 41.25 | H32: 139.52013 | I32: 118.92139 | J32: 1.965368 | K32: 0.08801328 | L32: 0.25840198 | M32: 0.87399461 | N32: 0.74495811 | O32: 0.83076923 | P32: 0.90909091 | Q32: 0.84364821 | R32: 0.83870968
A33: Dorset County Hospital NHS Foundation Trust | B33: RBD | C33: 93875 | D33: 0.97667111 | E33: 0.00015978695 | F33: 7.66875 | G33: 20.41875 | H33: 43.669705 | I33: 13.133328 | J33: 0.90429329 | K33: 0.081691079 | L33: 0.21750999 | M33: 0.46518993 | N33: 0.13990229 | O33: 0.6875 | P33: 0.77777778 | Q33: 0.80519481 | R33: 0.86046512
A34: Dudley Group NHS Foundation Trust | B34: RNA | C34: 103455 | D34: 0.78391571 | E34: 0.024793388 | F34: 8 | G34: 23.559687 | H34: 71.8672 | I34: 61.1 | J34: 1.5903232 | K34: 0.077328307 | L34: 0.22772884 | M34: 0.69467111 | N34: 0.59059494 | O34: 0.83333333 | P34: 1 | Q34: 0.80124224 | R34: 0.74074074
A35: East and North Hertfordshire NHS Trust | B35: RWH | C35: 140035 | D35: 0.80487021 | E35: 0.019423715 | F35: 7.7 | G35: 35.986 | H35: 127.21066 | I35: 42.582337 | J35: 1.5244688 | K35: 0.054986253 | L35: 0.25697861 | M35: 0.90842043 | N35: 0.30408353 | O35: 0.7254902 | P35: 0.75 | Q35: 0.81094527 | R35: 0.85074627
A36: East Cheshire NHS Trust | B36: RJN | C36: 50415 | D36: 0.81176237 | E36: 0.024695031 | F36: 5.71875 | G36: 16.721875 | H36: 1.15 | I36: 11.78633 | J36: 0.70171487 | K36: 0.1134335 | L36: 0.33168452 | M36: 0.022810671 | N36: 0.23378617 | O36: 0.8 | P36: 0.84615385 | Q36: 0.77777778 | R36: 0.33333333
A37: East Kent Hospitals University NHS Foundation Trust | B37: RVV | C37: 195585 | D37: 0.7031981 | E37: 0.050463993 | F37: 11 | G37: 33.015625 | H37: 188.09813 | I37: 140.49669 | J37: 1.9051074 | K37: 0.056241532 | L37: 0.16880448 | M37: 0.96172063 | N37: 0.7183408 | O37: 0.73809524 | P37: 0.75 | Q37: 0.69248826 | R37: 0.65384615
A38: East Lancashire Hospitals NHS Trust | B38: RXR | C38: 171815 | D38: 0.79475017 | E38: 0.0163548 | G38: 11.675 | H38: 16.866663 | I38: 23.371675 | J38: 0.30214671 | L38: 0.067950994 | M38: 0.098167579 | N38: 0.13602814 | O38: 0.75 | P38: 0 | Q38: 0.84375 | R38: 0.9
A39: East Sussex Healthcare NHS Trust | B39: RXC | C39: 117785 | D39: 0.78579615 | E39: 0.040539967 | F39: 8.6625 | G39: 33.215625 | H39: 94.168795 | I39: 52.982722 | J39: 1.6048703 | K39: 0.073545018 | L39: 0.28200216 | M39: 0.79949735 | N39: 0.44982572 | O39: 0.89655172 | P39: 0.64705882 | Q39: 0.8125 | R39: 0.79207921
A40: Epsom and St Helier University Hospitals NHS Trust | B40: RVR | C40: 154140 | D40: 0.92594395 | E40: 0.0075580641 | F40: 11.75 | G40: 40.875 | H40: 100.36554 | I40: 39.875968 | J40: 1.2512424 | K40: 0.076229402 | L40: 0.265181 | M40: 0.65113233 | N40: 0.25869967 | O40: 0.6875 | P40: 0.85714286 | Q40: 0.74731183 | R40: 0.73636364
A41: Frimley Health NHS Foundation Trust | B41: RDU | C41: 238755 | D41: 0.88980335 | E41: 0.011706561 | F41: 22.91875 | G41: 72.0125 | H41: 200.03406 | I41: 83.989982 | J41: 1.587214 | K41: 0.095992754 | L41: 0.30161672 | M41: 0.83782144 | N41: 0.35178314 | O41: 0.82291667 | P41: 0.78125 | Q41: 0.78021978 | R41: 0.76271186
A42: Gateshead Health NHS Foundation Trust | B42: RR7 | C42: 115670 | D42: 0.94618311 | E42: 0.00025935852 | F42: 8.1045 | G42: 23.028125 | H42: 69.75 | I42: 32.698813 | J42: 1.1548495 | K42: 0.070065704 | L42: 0.19908468 | M42: 0.60300856 | N42: 0.28269052 | O42: 0.78378378 | P42: 1 | Q42: 0.75630252 | R42: 0.71621622
A43: George Eliot Hospital NHS Trust | B43: RLT | C43: 80585 | D43: 0.87776882 | E43: 0.023639635 | F43: 5.35 | G43: 6.1 | H43: 56.95001 | I43: 27.901663 | J43: 1.1950322 | K43: 0.066389527 | L43: 0.07569647 | M43: 0.70670733 | N43: 0.34623891 | O43: 0.76190476 | P43: 1 | Q43: 0.77118644 | R43: 0.75
A44: Gloucestershire Hospitals NHS Foundation Trust | B44: RTE | C44: 141250 | D44: 0.86700885 | E44: 0.0028672566 | F44: 19.3 | G44: 31 | H44: 116.72339 | I44: 47.888625 | J44: 1.521501 | K44: 0.13663717 | L44: 0.21946903 | M44: 0.82636027 | N44: 0.33903451 | O44: 0.765625 | P44: 1 | Q44: 0.84716157 | R44: 0.85915493
A45: Great Western Hospitals NHS Foundation Trust | B45: RN3 | C45: 115665 | D45: 0.84342714 | E45: 0.028400986 | F45: 10.2167 | G45: 23.53105 | H45: 62.69754 | I45: 48.648405 | J45: 1.2544304 | K45: 0.088330091 | L45: 0.2034414 | M45: 0.54206147 | N45: 0.42059746 | O45: 0.83928571 | P45: 1 | Q45: 0.82089552 | R45: 0.77272727
A46: Guy's and St Thomas' NHS Foundation Trust | B46: RJ1 | C46: 180100 | D46: 0.86288173 | E46: 0.00072182121 | F46: 24.1875 | G46: 67.290625 | H46: 169.35701 | I46: 50.323135 | J46: 1.7276972 | K46: 0.13430039 | L46: 0.37362923 | M46: 0.94034988 | N46: 0.27941774 | O46: 0.75409836 | P46: 0.91666667 | Q46: 0.75185185 | R46: 0.72972973
A47: Hampshire Hospitals NHS Foundation Trust | B47: RN5 | C47: 123820 | D47: 0.86811501 | E47: 0.009570344 | F47: 11.5 | G47: 29.941043 | H47: 104.36999 | I47: 49.508382 | J47: 1.5774464 | K47: 0.092876757 | L47: 0.24181104 | M47: 0.84291704 | N47: 0.39984156 | O47: 0.56410256 | P47: 1 | Q47: 0.73459716 | R47: 0.77419355
A48: Harrogate and District NHS Foundation Trust | B48: RCD | C48: 49485 | D48: 0.94180055 | E48: 0.00020208144 | F48: 6.075 | G48: 22.576563 | H48: 31.796673 | I48: 19.509995 | J48: 1.6158074 | K48: 0.12276447 | L48: 0.45623042 | M48: 0.64255173 | N48: 0.39426079 | O48: 0.73076923 | P48: 0.88235294 | Q48: 0.72289157 | R48: 0.65
A49: Hillingdon Hospitals NHS Foundation Trust | B49: RAS | C49: 94160 | D49: 0.74293755 | E49: 0.03175446 | F49: 9.45 | G49: 28.525 | H49: 79.206682 | I49: 35.69298 | J49: 1.6235627 | K49: 0.10036109 | L49: 0.3029418 | M49: 0.84119246 | N49: 0.37906733 | O49: 0.6 | P49: 0.88 | Q49: 0.72159091 | R49: 0.76744186
A50: Homerton University Hospital NHS Foundation Trust | B50: RQX | C50: 121950 | D50: 0.73226732 | E50: 0.03202132 | F50: 9.98125 | G50: 33.956565 | H50: 64.33333 | I50: 23.122205 | J50: 1.0774362 | K50: 0.081847068 | L50: 0.27844662 | M50: 0.52753858 | N50: 0.18960398 | O50: 0.625 | P50: 0.92857143 | Q50: 0.75 | R50: 0.77272727
A51: Hounslow and Richmond Community Healthcare NHS Trust | B51: RY9 | C51: 153140 | D51: 0.99275173 | E51: 6.5299726e-05 | G51: 0.06818 | H51: 8.7399875 | I51: 7.35 | J51: 0.10551239 | L51: 0.00044521353 | M51: 0.057071879 | N51: 0.047995298 | O51: 0.77777778 | P51: 0 | Q51: 0.68181818 | R51: 0.66666667
A52: Hull and East Yorkshire Hospitals NHS Trust | B52: RWA | C52: 146780 | D52: 0.87164464 | E52: 0.0048031067 | F52: 16.25 | G52: 36.435938 | H52: 92.283337 | I52: 31.043342 | J52: 1.1991594 | K52: 0.11070991 | L52: 0.24823503 | M52: 0.62871875 | N52: 0.21149572 | O52: 0.87096774 | P52: 1 | Q52: 0.82978723 | R52: 0.78723404
A53: Imperial College Healthcare NHS Trust | B53: RYJ | C53: 240015 | D53: 0.83134387 | E53: 0.015415703 | F53: 25.4 | G53: 77.92216 | H53: 162.92248 | I53: 59.468332 | J53: 1.3570526 | K53: 0.10582672 | L53: 0.32465538 | M53: 0.67880126 | N53: 0.24776923 | O53: 0.6875 | P53: 0.85185185 | Q53: 0.70881226 | R53: 0.69411765
A54: Ipswich Hospital NHS Trust | B54: RGQ | C54: 92060 | D54: 0.9071801 | E54: 0.00032587443 | F54: 12.7875 | G54: 33.45 | H54: 77.795758 | I54: 40.966543 | J54: 1.7923072 | K54: 0.13890398 | L54: 0.36334999 | M54: 0.84505494 | N54: 0.44499829 | O54: 0.79166667 | P54: 0.7826087 | Q54: 0.80379747 | R54: 0.81609195
A55: Isle of Wight NHS Trust | B55: R1F | C55: 49695 | D55: 0.82654191 | E55: 0.02525405 | F55: 4 | G55: 11.85 | H55: 24.90167 | I55: 17.095002 | J55: 1.1640341 | K55: 0.080490995 | L55: 0.23845457 | M55: 0.50109005 | N55: 0.34399844 | O55: 0.75 | P55: 1 | Q55: 0.70689655 | R55: 0.55555556
A56: James Paget University Hospitals NHS Foundation Trust | B56: RGP | C56: 77395 | D56: 0.90490342 | E56: 0.013114542 | F56: 4.85 | G56: 12.4875 | H56: 48.173805 | I56: 23.04573 | J56: 1.1442217 | K56: 0.062665547 | L56: 0.16134763 | M56: 0.62244079 | N56: 0.29776769 | O56: 0.91666667 | P56: 0.86666667 | Q56: 0.89473684 | R56: 0.89795918
A57: Kent Community Health NHS Foundation Trust | B57: RYY | C57: 76245 | D57: 0.99836055 | G57: 0 | H57: 1.813335 | I57: 0.72 | J57: 0.033226244 | L57: 0 | M57: 0.023783002 | N57: 0.0094432422 | O57: 1 | P57: 0 | Q57: 0.75 | R57: 0.66666667
A58: Kettering General Hospital NHS Foundation Trust | B58: RNQ | C58: 86890 | D58: 0.76827023 | E58: 0.034641501 | F58: 6 | G58: 24.325 | H58: 69.608328 | I58: 50.606665 | J58: 1.7325353 | K58: 0.069052825 | L58: 0.27995166 | M58: 0.80110861 | N58: 0.5824222 | O58: 0.69565217 | P58: 0.86363636 | Q58: 0.73493976 | R58: 0.73333333
A59: King's College Hospital NHS Foundation Trust | B59: RJZ | C59: 228395 | D59: 0.77613345 | E59: 0.027737035 | F59: 22.75 | G59: 76.29375 | H59: 290.03448 | I59: 49.507317 | J59: 1.920294 | K59: 0.099608135 | L59: 0.334043 | M59: 1.269881 | N59: 0.21676183 | O59: 0.6744186 | P59: 0.91666667 | Q59: 0.75342466 | R59: 0.74496644
A60: Kingston Hospital NHS Foundation Trust | B60: RAX | C60: 116985 | D60: 0.7972817 | E60: 0.01389067 | F60: 9.775 | G60: 23.396875 | H60: 73.136647 | I60: 37.997065 | J60: 1.2335392 | K60: 0.083557721 | L60: 0.19999893 | M60: 0.6251797 | N60: 0.32480288 | O60: 0.60869565 | P60: 0.92307692 | Q60: 0.69924812 | R60: 0.68918919
A61: Lancashire Teaching Hospitals NHS Foundation Trust | B61: RXN | C61: 93240 | D61: 0.75353925 | E61: 0.025579151 | F61: 19.37 | G61: 34.66875 | H61: 90.636585 | I61: 64.569975 | J61: 2.2441582 | K61: 0.20774346 | L61: 0.37182272 | M61: 0.97207835 | N61: 0.69251367 | O61: 0.86486486 | P61: 0.91666667 | Q61: 0.82125604 | R61: 0.7706422
A62: Leeds Teaching Hospitals NHS Trust | B62: RR8 | C62: 212855 | D62: 0.80601818 | E62: 0.024241855 | F62: 31.77 | G62: 52.774062 | H62: 219.33 | I62: 136.812 | J62: 2.0703581 | K62: 0.14925654 | L62: 0.24793433 | M62: 1.0304198 | N62: 0.64274742 | O62: 0.7761194 | P62: 0.89189189 | Q62: 0.72235872 | R62: 0.65254237
A63: Lewisham and Greenwich NHS Trust | B63: RJ2 | C63: 215120 | D63: 0.80136668 | E63: 0.035793975 | F63: 17.55 | G63: 64.892187 | H63: 209.14348 | I63: 71.188855 | J63: 1.6863821 | K63: 0.081582373 | L63: 0.30165576 | M63: 0.97221773 | N63: 0.33092625 | O63: 0.73076923 | P63: 0.85 | Q63: 0.7880597 | R63: 0.79324895
A64: Lincolnshire Community Health Services NHS Trust | B64: RY5 | C64: 146815 | D64: 0.9905323 | E64: 0.00013622586 | G64: 0 | H64: 14.549997 | I64: 16.67667 | J64: 0.21269399 | K64: 0 | L64: 0 | M64: 0.099104298 | N64: 0.11358969 | O64: 0.88235294 | P64: 0 | Q64: 0.58536585 | R64: 0.375
A65: London North West University Healthcare NHS Trust | B65: R1K | C65: 140810 | D65: 0.58550529 | E65: 0.078225978 | F65: 19.9 | G65: 54.175 | H65: 202.7165 | I65: 110.0708 | J65: 2.7474065 | K65: 0.14132519 | L65: 0.3847383 | M65: 1.4396456 | N65: 0.78169732 | O65: 0.75423729 | P65: 0.87878788 | Q65: 0.76762402 | R65: 0.74568966
A66: Luton and Dunstable University Hospital NHS Foundation Trust | B66: RC9 | C66: 105220 | D66: 0.97742825 | E66: 0.00052271431 | F66: 9.75 | G66: 41.334375 | H66: 94.892437 | I66: 31.972897 | J66: 1.6912156 | K66: 0.092662992 | L66: 0.39283763 | M66: 0.90184791 | N66: 0.30386711 | O66: 0.58333333 | P66: 1 | Q66: 0.62561576 | R66: 0.6015625
A67: Maidstone and Tunbridge Wells NHS Trust | B67: RWF | C67: 170205 | D67: 0.89224758 | E67: 0.030786405 | F67: 13.2 | G67: 42.475 | H67: 134.22195 | I67: 59.821325 | J67: 1.4671618 | K67: 0.077553538 | L67: 0.24955201 | M67: 0.78858992 | N67: 0.35146632 | O67: 0.80597015 | P67: 0.88888889 | Q67: 0.74786325 | R67: 0.69127517
A68: Manchester University NHS Foundation Trust | B68: R0A | C68: 364670 | D68: 0.88499191 | E68: 0.0079798174 | F68: 33.7125 | G68: 85.209375 | H68: 230.65732 | I68: 117.91092 | J68: 1.2819539 | K68: 0.092446596 | L68: 0.2336616 | M68: 0.63250973 | N68: 0.32333595 | O68: #N/A | P68: #N/A | Q68: #N/A | R68: #N/A
A69: Medway NHS Foundation Trust | B69: RPA | C69: 121535 | D69: 0.83412186 | E69: 0.039371375 | F69: 6.6 | G69: 35.809375 | H69: 71.923282 | I69: 28.409983 | J69: 1.1744982 | K69: 0.054305344 | L69: 0.29464249 | M69: 0.5917907 | N69: 0.23375968 | O69: 0.48571429 | P69: 0.95652174 | Q69: 0.78512397 | R69: 0.82539683
A70: Mid Cheshire Hospitals NHS Foundation Trust | B70: RBT | C70: 88190 | D70: 0.87226443 | E70: 0.0062932305 | F70: 7.35 | G70: 13.191 | H70: 94.141482 | I70: 65.967073 | J70: 2.0484131 | K70: 0.083342783 | L70: 0.14957478 | M70: 1.0674848 | N70: 0.7480108 | O70: 0.82142857 | P70: 0.71428571 | Q70: 0.77941176 | R70: 0.75471698
A71: Mid Essex Hospital Services NHS Trust | B71: RQ8 | C71: 100750 | D71: 0.8155335 | E71: 0.019751861 | F71: 6.875 | G71: 23.478125 | H71: 58.130003 | I71: 30.626665 | J71: 1.1822312 | K71: 0.068238213 | L71: 0.2330335 | M71: 0.57697273 | N71: 0.30398675 | O71: 0.6875 | P71: 0.8 | Q71: 0.71287129 | R71: 0.703125
A72: Mid Yorkshire Hospitals NHS Trust | B72: RXF | C72: 239790 | D72: 0.85157846 | E72: 0.010717711 | F72: 17.5 | G72: 42.828125 | H72: 129.98164 | I72: 68.746638 | J72: 1.080347 | K72: 0.072980525 | L72: 0.1786068 | M72: 0.54206446 | N72: 0.28669518 | O72: 0.83544304 | P72: 0.91304348 | Q72: 0.84033613 | R72: 0.83088235
A73: Milton Keynes University Hospital NHS Foundation Trust | B73: RD8 | C73: 87095 | D73: 0.85303404 | E73: 0.022102302 | F73: 8.05 | G73: 23.8438 | H73: 57.41665 | I73: 31.563335 | J73: 1.3878384 | K73: 0.092427809 | L73: 0.27376772 | M73: 0.65924163 | N73: 0.36240123 | O73: 0.85 | P73: 1 | Q73: 0.84615385 | R73: 0.80645161
A74: Moorfields Eye Hospital NHS Foundation Trust | B74: RP6 | C74: 95015 | D74: 0.98516024 | F74: 6.2566667 | G74: 6.9666667 | H74: 49.426667 | I74: 5.3333333 | J74: 0.71550106 | K74: 0.065849252 | L74: 0.073321756 | M74: 0.52019857 | N74: 0.056131488 | O74: #N/A | P74: #N/A | Q74: #N/A | R74: #N/A
A75: National | B75: National | C75: 18363445 | D75: 0.84495774 | E75: 0.016845423 | F75: 1642.0239 | G75: 4351.6203 | H75: 13739.296 | I75: 7297.8952 | J75: 1.4719915 | K75: 0.089418076 | L75: 0.23697189 | M75: 0.74818728 | N75: 0.39741427 | O75: 0.77174 | P75: 0.84366472 | Q75: 0.75814184 | R75: 0.726593
A76: Newcastle Upon Tyne Hospitals NHS Foundation Trust | B76: RTD | C76: 196650 | D76: 0.93737605 | E76: 0.00017798118 | F76: 16.7 | G76: 32.021875 | H76: 111.24808 | I76: 51.75167 | J76: 1.0766419 | K76: 0.084922451 | L76: 0.16283689 | M76: 0.56571616 | N76: 0.26316639 | O76: 0.80645161 | P76: 0.95454545 | Q76: 0.85353535 | R76: 0.85087719
A77: Norfolk and Norwich University Hospitals NHS Foundation Trust | B77: RM1 | C77: 131225 | D77: 0.80720137 | E77: 0.014974281 | G77: 6.675 | H77: 110.06168 | I77: 66.966662 | J77: 1.3999111 | K77: 0 | L77: 0.050866832 | M77: 0.8387249 | N77: 0.51031939 | O77: 0.84415584 | P77: 0.5 | Q77: 0.76666667 | R77: 0.72519084
A78: North Bristol NHS Trust | B78: RVJ | C78: 87365 | D78: 0.75756882 | E78: 0.034338694 | F78: 11.6 | G78: 27.7477 | H78: 111.05865 | I78: 62.416068 | J78: 2.4360146 | K78: 0.13277628 | L78: 0.31760659 | M78: 1.271203 | N78: 0.71442875 | O78: 0.63636364 | P78: 0.95 | Q78: 0.73684211 | R78: 0.775
A79: North Cumbria University Hospitals NHS Trust | B79: RNL | C79: 92500 | D79: 0.8807027 | E79: 0.008 | F79: 9.23125 | G79: 21.09375 | H79: 59.22 | I79: 37.068333 | J79: 1.3687928 | K79: 0.099797297 | L79: 0.22804054 | M79: 0.64021622 | N79: 0.40073873 | O79: 0.82051282 | P79: 0.7 | Q79: 0.71929825 | R79: 0.63076923
A80: North Middlesex University Hospital NHS Trust | B80: RAP | C80: 175160 | D80: 0.81008792 | E80: 0.008392327 | F80: 11.138333 | G80: 39.3 | H80: 115.90671 | I80: 51.036635 | J80: 1.2410464 | K80: 0.063589475 | L80: 0.22436629 | M80: 0.66171909 | N80: 0.29137152 | O80: 0.8125 | P80: 0.68421053 | Q80: 0.75 | R80: 0.73643411
A81: North Tees and Hartlepool NHS Foundation Trust | B81: RVW | C81: 164515 | D81: 0.95419871 | E81: 0.00018235419 | F81: 9.175 | G81: 28.34091 | H81: 54.219985 | I81: 48.58667 | J81: 0.85294693 | K81: 0.055769991 | L81: 0.17226946 | M81: 0.32957472 | N81: 0.29533277 | O81: 0.83018868 | P81: 0.875 | Q81: 0.71942446 | R81: 0.57142857
A82: North West Anglia NHS Foundation Trust | B82: RGN | C82: 149985 | D82: 0.80774744 | E82: 0.01560156 | F82: 12.375 | G82: 37.115437 | H82: 136.88998 | I82: 51.532498 | J82: 1.5862447 | K82: 0.082508251 | L82: 0.247461 | M82: 0.91269114 | N82: 0.34358434 | O82: 0.70967742 | P82: 0.71428571 | Q82: 0.72469636 | R82: 0.7195122
A83: Northampton General Hospital NHS Trust | B83: RNS | C83: 122575 | D83: 0.85111156 | E83: 0.034835815 | F83: 8.95 | G83: 24.735135 | H83: 88.131645 | I83: 42.145383 | J83: 1.3376477 | K83: 0.07301652 | L83: 0.20179592 | M83: 0.71900179 | N83: 0.34383343 | O83: 0.68627451 | P83: 0.91666667 | Q83: 0.76506024 | R83: 0.77669903
A84: Northern Devon Healthcare NHS Trust | B84: RBZ | C84: 55305 | D84: 0.86918 | E84: 0.032818009 | F84: 4.575 | G84: 12.753125 | H84: 37.885 | I84: 9.1509875 | J84: 1.1638028 | K84: 0.082723081 | L84: 0.23059624 | M84: 0.68501944 | N84: 0.16546402 | O84: 0.86666667 | P84: 0.69230769 | Q84: 0.8028169 | R84: 0.81395349
A85: Northern Lincolnshire and Goole NHS Foundation Trust | B85: RJL | C85: 150455 | D85: 0.85510618 | E85: 0.0023595095 | F85: 9.85 | G85: 25.939772 | H85: 87.993663 | I85: 33.093333 | J85: 1.0426823 | K85: 0.06546808 | L85: 0.17240884 | M85: 0.58485037 | N85: 0.21995502 | O85: 0.86842105 | P85: 0.89473684 | Q85: 0.83850932 | R85: 0.81730769
A86: Northumbria Healthcare NHS Foundation Trust | B86: RTF | C86: 193175 | D86: 0.93234114 | E86: 0 | F86: 23.8725 | G86: 53.803125 | H86: 81.503317 | I86: 73.758798 | J86: 1.2058379 | K86: 0.12357966 | L86: 0.27852012 | M86: 0.42191442 | N86: 0.38182372 | O86: 0.88235294 | P86: 0.96875 | Q86: 0.88557214 | R86: 0.85714286
A87: Nottingham University Hospitals NHS Trust | B87: RX1 | C87: 198160 | D87: 0.79867279 | E87: 0.0099414614 | F87: 20.3 | G87: 34.614063 | H87: 247.73503 | I87: 109.20877 | J87: 2.0784107 | K87: 0.10244247 | L87: 0.17467734 | M87: 1.2501768 | N87: 0.55111411 | O87: 0.79439252 | P87: 1 | Q87: 0.75260417 | R87: 0.71031746
A88: Oxford University Hospitals NHS Foundation Trust | B88: RTH | C88: 136005 | D88: 0.80364692 | E88: 0.037976545 | F88: 17.8 | G88: 35.748438 | H88: 127.11963 | I88: 68.57922 | J88: 1.8326333 | K88: 0.13087754 | L88: 0.26284649 | M88: 0.93466882 | N88: 0.50424043 | O88: 0.86170213 | P88: 0.96 | Q88: 0.80384615 | R88: 0.73758865
A89: Pennine Acute Hospitals NHS Trust | B89: RW6 | C89: 328955 | D89: 0.8230913 | E89: 0.018862762 | F89: 23.05 | G89: 85.470313 | H89: 227.87563 | I89: 109.18399 | J89: 1.3545316 | K89: 0.070070374 | L89: 0.25982372 | M89: 0.69272584 | N89: 0.33191162 | O89: 0.87704918 | P89: 0.86111111 | Q89: 0.82307692 | R89: 0.78017241
... A94: Queen Elizabeth Hospital King's Lynn NHS Foundation Trust | B94: RCX | C94: 62325 | D94: 0.85511432 | E94: 0.011472122 | F94: 5.25 | G94: 15.1 | H94: 46.89001 | I94: 19.74334 | J94: 1.3956414 | K94: 0.08423586 | L94: 0.24227838 | M94: 0.75234673 | N94: 0.31678043 | O94: 0.94444444 | P94: 1 | Q94: 0.80722892 | R94: 0.73684211
A95: Queen Victoria Hospital NHS Foundation Trust | B95: RPC | C95: 10950 | D95: 0.99680365 | E95: 0 | G95: 0.05 | I95: 6.094935 | J95: 0.56118128 | K95: 0 | L95: 0.00456621 | M95: 0 | N95: 0.55661507 | O95: 0.77777778 | P95: 0 | Q95: 0.7 | R95: 0
A96: Rotherham NHS Foundation Trust | B96: RFR | C96: 89850 | D96: 0.82020033 | E96: 0.010962716 | F96: 8.25625 | G96: 12.65 | H96: 67.381497 | I96: 45.72474 | J96: 1.4915135 | K96: 0.09188926 | L96: 0.14079021 | M96: 0.74993319 | N96: 0.50890083 | O96: 0.89795918 | P96: 0.90909091 | Q96: 0.80769231 | R96: 0.72857143
A97: Royal Berkshire NHS Foundation Trust | B97: RHW | C97: 129070 | D97: 0.88421012 | E97: 0.0047648563 | F97: 12.925 | G97: 36.39091 | H97: 82.23472 | I97: 45.145325 | J97: 1.3689932 | K97: 0.10013946 | L97: 0.28194708 | M97: 0.63713272 | N97: 0.34977396 | O97: 0.76 | P97: 0.84615385 | Q97: 0.73529412 | R97: 0.69148936
A98: Royal Bournemouth and Christchurch Hospitals NHS Foundation Trust | B98: RDZ | C98: 91070 | D98: 0.80652246 | E98: 0.027945536 | F98: 9.19375 | G98: 22.48102 | H98: 65.190007 | I98: 44.78168 | J98: 1.555358 | K98: 0.10095256 | L98: 0.24685429 | M98: 0.71582308 | N98: 0.49172812 | O98: 0.74545455 | P98: 0.76190476 | Q98: 0.73856209 | R98: 0.72727273
A99: Royal Cornwall Hospitals NHS Trust | B99: REF | C99: 165205 | D99: 0.8737629 | E99: 0.012166702 | F99: 12.029 | G99: 37.40959 | H99: 73.22332 | I99: 55.879583 | J99: 1.0807269 | K99: 0.072812566 | L99: 0.22644345 | M99: 0.44322702 | N99: 0.33824389 | O99: 0.828125 | P99: 0.8 | Q99: 0.80113636 | R99: 0.7804878
A100: Royal Devon and Exeter NHS Foundation Trust | B100: RH8 | C100: 110620 | D100: 0.90164527 | E100: 0.0014915928 | F100: 11.325 | G100: 32.048437 | H100: 60.416663 | I100: 34.522037 | J100: 1.2503357 | K100: 0.10237751 | L100: 0.28971648 | M100: 0.54616401 | N100: 0.31207772 | O100: 0.90697674 | P100: 0.95 | Q100: 0.78030303 | R100: 0.65217391
A101: Royal Free London NHS Foundation Trust | B101: RAL | C101: 263870 | D101: 0.86085951 | E101: 0.022662675 | F101: 17.9 | G101: 57.57041 | H101: 179.48067 | I101: 80.99704 | J101: 1.2731577 | K101: 0.067836435 | L101: 0.21817717 | M101: 0.68018597 | N101: 0.30695812 | O101: 0.74193548 | P101: 0.85714286 | Q101: 0.73899371 | R101: 0.70526316
A102: Royal Liverpool and Broadgreen University Hospitals NHS Trust | B102: RQ6 | C102: 109180 | D102: 0.75586188 | E102: 0.072311779 | F102: 12.95 | G102: 35.55455 | H102: 90.413333 | I102: 60.097862 | J102: 1.8228224 | K102: 0.11861147 | L102: 0.32565076 | M102: 0.82811259 | N102: 0.55044754 | O102: 0.87692308 | P102: 0.95 | Q102: 0.77297297 | R102: 0.66
A103: Royal Surrey County Hospital NHS Foundation Trust | B103: RA2 | C103: 70935 | D103: 0.94889688 | E103: 0.0023260732 | F103: 10.075 | G103: 14.005125 | H103: 65.369052 | I103: 17.77165 | J103: 1.5115363 | K103: 0.14203144 | L103: 0.19743603 | M103: 0.92153454 | N103: 0.25053429 | O103: 0.70588235 | P103: 0.66666667 | Q103: 0.79591837 | R103: 0.84057971
A104: Royal United Hospitals Bath NHS Foundation Trust | B104: RD1 | C104: 72320 | D104: 0.79604535 | E104: 0.023506637 | F104: 9.15 | G104: 26.125 | H104: 71.175832 | I104: 78.008233 | J104: 2.5505955 | K104: 0.12652102 | L104: 0.3612417 | M104: 0.9841791 | N104: 1.0786537 | O104: 0.81609195 | P104: 1 | Q104: 0.79473684 | R104: 0.73626374
A105: Royal Wolverhampton NHS Trust | B105: RL4 | C105: 181775 | D105: 0.87151699 | E105: 0.0055838262 | F105: 16.5 | G105: 33.65625 | H105: 93.892983 | I105: 47.564978 | J105: 1.0541285 | K105: 0.090771558 | L105: 0.18515335 | M105: 0.51653408 | N105: 0.26166952 | O105: 0.72413793 | P105: 0.88235294 | Q105: 0.75555556 | R105: 0.71428571
A106: Salford Royal NHS Foundation Trust | B106: RM3 | C106: 100470 | D106: 0.85284164 | E106: 0.0061212302 | F106: 36.26875 | G106: 26.67957 | H106: 207.75668 | I106: 134.86999 | J106: 4.036777 | K106: 0.36099084 | L106: 0.26554763 | M106: 2.0678479 | N106: 1.3423907 | O106: 0.77857143 | P106: 0.93617021 | Q106: 0.80798005 | R106: 0.79906542
A107: Salisbury NHS Foundation Trust | B107: RNZ | C107: 46235 | D107: 0.91705418 | E107: 0.0025954364 | F107: 9.125 | G107: 12.696875 | H107: 39.019148 | I107: 18.814998 | J107: 1.7228511 | K107: 0.19736131 | L107: 0.27461609 | M107: 0.84393095 | N107: 0.40694274 | O107: 0.91304348 | P107: 0.7 | Q107: 0.7721519 | R107: 0.7173913
A108: Sandwell and West Birmingham Hospitals NHS Trust | B108: RXK | C108: 220175 | D108: 0.83672079 | E108: 0.00072669467 | F108: 13.0375 | G108: 36.232813 | H108: 130.91995 | I108: 67.958798 | J108: 1.1270538 | K108: 0.059214261 | L108: 0.1645637 | M108: 0.59461769 | N108: 0.3086581 | O108: 0.80769231 | P108: 0.74193548 | Q108: 0.70980392 | R108: 0.65068493
A109: Sheffield Children's NHS Foundation Trust | B109: RCU | C109: 36720 | D109: 0.97576253 | F109: 8.035 | G109: 16.18364 | H109: 44.213325 | I109: 15.9167 | J109: 2.2970769 | K109: 0.21881808 | L109: 0.44073094 | M109: 1.2040666 | N109: 0.43346133 | O109: 0.83333333 | P109: 0.78571429 | Q109: 0.77777778 | R109: 0.75
...

Sheet Provider_data2
A1: Org name | B1: Org code | C1: Region | D1: Total | E1: Consultant (including Directors of Public Health) | F1: Other Doctors | G1: Nurses & health visitors | H1: Other Clinical Staff | I1: Rate Total | J1: Rate Consultant | K1: Rate Other Doctors | L1: Rate Nurses | M1: Rate other Clinical | N1: Total Unplanned | O1: 4hr % | P1: 12hr % | Q1: Total Clinical Staff (SI) | R1: HCHS Doctors1 (SI) | S1: Nurses & health visitors (SI) | T1: Total Clinical Staff, excl. doc and nur (SI) | U1: Count 4 hrs | V1: Count 12 hours
A2: National | B2: National | C2: National | D2: 27030.835 | E2: 1642.0239 | F2: 4351.6203 | G2: 13739.296 | H2: 7297.8952 | I2: 1.4719915 | J2: 0.089418076 | K2: 0.23697189 | L2: 0.74818728 | M2: 0.39741427 | N2: 18363445 | O2: 0.84495774 | P2: 0.016845423 | Q2: 0.75814184 | R2: 0.84366472 | S2: 0.726593 | T2: 0.77174 | U2: 15516335 | V2: 309340
A3: Aintree University Hospital NHS Foundation Trust | B3: REM | C3: North of England Commissioning Region | D3: 176.93302 | E3: 15 | F3: 21.036365 | G3: 99.479993 | H3: 41.416663 | I3: 1.057769 | J3: 0.089675375 | K3: 0.12576293 | L3: 0.59472704 | M3: 0.24760365 | N3: 167270 | O3: 0.82522269 | P3: 0.020266635 | Q3: 0.75324675 | R3: 0.83333333 | S3: 0.7173913 | T3: 0.79545455 | U3: 138035 | V3: 3390
A4: Airedale NHS Foundation Trust | B4: RCF | C4: North of England Commissioning Region | D4: 92.27677 | E4: 7.6 | F4: 17.373438 | G4: 38.573325 | H4: 28.730007 | I4: 1.6052321 | J4: 0.1322084 | K4: 0.30222558 | L4: 0.67101548 | M4: 0.49978268 | N4: 57485 | O4: 0.9188484 | P4: 0.0010437505 | Q4: 0.84615385 | R4: 1 | S4: 0.83333333 | T4: 0.80555556 | U4: 52820 | V4: 60
A5: Alder Hey Children's NHS Foundation Trust | B5: RBS | C5: North of England Commissioning Region | D5: 62.253647 | E5: 8.2 | F5: 5.182 | G5: 43.158317 | H5: 5.71333 | I5: 1.038253 | J5: 0.13675784 | K5: 0.086424283 | L5: 0.71978515 | M5: 0.09528569 | N5: 59960 | O5: 0.94863242 | Q5: 0.84745763 | R5: 0.8 | S5: 0.875 | T5: 0.77777778 | U5: 56880 | V5: *
A6: Ashford and St. Peter's Hospitals NHS Foundation Trust | B6: RTK | C6: South of England Commissioning Region | D6: 120.11923 | E6: 6.75 | F6: 14.25 | G6: 69.853297 | H6: 29.265932 | I6: 1.1875356 | J6: 0.066732575 | K6: 0.14087988 | L6: 0.69059118 | M6: 0.28933201 | N6: 101150 | O6: 0.84997528 | P6: 0.030153238 | Q6: 0.825 | R6: 0.9 | S6: 0.80821918 | T6: 0.81081081 | U6: 85975 | V6: 3050
A7: Barking, Havering and Redbridge University Hospitals NHS Trust | B7: RF4 | C7: London Commissioning Region | D7: 251.20773 | E7: 8.4 | F7: 37.45 | G7: 140.36613 | H7: 64.991595 | I7: 0.98416348 | J7: 0.032908913 | K7: 0.1467189 | L7: 0.54991629 | M7: 0.25461937 | N7: 255250 | O7: 0.79653281 | P7: 0.025974535 | Q7: 0.71590909 | R7: 0.68181818 | S7: 0.73333333 | T7: 0.68831169 | U7: 203315 | V7: 6630
A8: Barnsley Hospital NHS Foundation Trust | B8: RFF | C8: North of England Commissioning Region | D8: 138.5257 | E8: 12.64395 | F8: 22.075 | G8: 64.59 | H8: 39.216752 | I8: 1.6196154 | J8: 0.14783059 | K8: 0.25809657 | L8: 0.75517362 | M8: 0.45851459 | N8: 85530 | O8: 0.90477026 | P8: 0.0049105577 | Q8: 0.71875 | R8: 1 | S8: 0.69117647 | T8: 0.68085106 | U8: 77385 | V8: 420
A9: Barts Health NHS Trust | B9: R1H | C9: London Commissioning Region | D9: 607.90249 | E9: 46.5 | F9: 121 | G9: 300.05782 | H9: 140.34467 | I9: 1.3901905 | J9: 0.10633919 | K9: 0.27671057 | L9: 0.6861915 | M9: 0.32094922 | N9: 437280 | O9: 0.81487834 | P9: 0.012760703 | Q9: 0.73852295 | R9: 0.82692308 | S9: 0.68852459 | T9: 0.79861111 | U9: 356330 | V9: 5580
A10: Basildon and Thurrock University Hospitals NHS Foundation Trust | B10: RDD | C10: Midlands and East of England Commissioning Region | D10: 146.78998 | E10: 8.5 | F10: 33 | G10: 57.823318 | H10: 47.466665 | I10: 1.1865173 | J10: 0.068706301 | K10: 0.26674211 | L10: 0.46739132 | M10: 0.38367752 | N10: 123715 | O10: 0.85810128 | P10: 0.025744655 | Q10: 0.75539568 | R10: 0.95 | S10: 0.65625 | T10: 0.78181818 | U10: 106160 | V10: 3185
A11: Bedford Hospital NHS Trust | B11: RC1 | C11: Midlands and East of England Commissioning Region | D11: 93.666382 | E11: 5.5 | F11: 21.329688 | G11: 49.170027 | H11: 17.666667 | I11: 1.2335074 | J11: 0.072430368 | K11: 0.28089402 | L11: 0.64752785 | M11: 0.23265513 | N11: 75935 | O11: 0.9037993 | P11: 0.00250214 | Q11: 0.875 | R11: 1 | S11: 0.82978723 | T11: 0.8125 | U11: 68630 | V11: 190
A12: Birmingham Women's and Children's NHS Foundation Trust | B12: RQ3 | C12: Midlands and East of England Commissioning Region | D12: 90.18459 | E12: 5.5625 | F12: 18.86875 | G12: 49.63334 | H12: 16.12 | I12: 1.5141805 | J12: 0.093393217 | K12: 0.31680238 | L12: 0.83333345 | M12: 0.27065144 | N12: 59560 | O12: 0.92839154 | P12: 0.00050369375 | Q12: 0.72289157 | R12: 0.9 | S12: 0.69090909 | T12: 0.72222222 | U12: 55295 | V12: 30
A13: Blackpool Teaching Hospitals NHS Foundation Trust | B13: RXL | C13: North of England Commissioning Region | D13: 162.11459 | E13: 7.00625 | F13: 29.925 | G13: 78.943335 | H13: 46.240007 | I13: 2.0327849 | J13: 0.087852665 | K13: 0.37523511 | L13: 0.98988508 | M13: 0.57981201 | N13: 79750 | O13: 0.59015674 | P13: 0.072852665 | Q13: 0.57534247 | R13: 0.90909091 | S13: 0.62921348 | T13: 0.39130435 | U13: 47065 | V13: 5810
A14: Bolton NHS Foundation Trust | B14: RMC | C14: North of England Commissioning Region | D14: 167.38781 | E14: 10.4 | F14: 29.357812 | G14: 98.10334 | H14: 29.526663 | I14: 1.4792136 | J14: 0.091905267 | K14: 0.25943631 | L14: 0.86694362 | M14: 0.26092844 | N14: 113160 | O14: 0.81508484 | P14: 0.0062743019 | Q14: 0.82876712 | R14: 0.88235294 | S14: 0.84 | T14: 0.75862069 | U14: 92235 | V14: 710
A15: Bradford Teaching Hospitals NHS Foundation Trust | B15: RAE | C15: North of England Commissioning Region | D15: 185.85976 | E15: 15.0125 | F15: 35.677625 | G15: 82.499995 | H15: 52.669645 | I15: 1.3842241 | J15: 0.1118083 | K15: 0.26571554 | L15: 0.61443357 | M15: 0.39226666 | N15: 134270 | O15: 0.79463022 | P15: 0.0059953824 | Q15: 0.78531073 | R15: 0.94736842 | S15: 0.77083333 | T15: 0.75806452 | U15: 106695 | V15: 805
A16: Brighton and Sussex University Hospitals NHS Trust | B16: RXH | C16: South of England Commissioning Region | D16: 374.03059 | E16: 19.24375 | F16: 77.561972 | G16: 192.42658 | H16: 84.798285 | I16: 2.3654857 | J16: 0.12170345 | K16: 0.49052601 | L16: 1.2169655 | M16: 0.5362907 | N16: 158120 | O16: 0.82854794 | P16: 0.039874779 | Q16: 0.77477477 | R16: 0.92592593 | S16: 0.76036866 | T16: 0.76404494 | U16: 131010 | V16: 6305
A17: Buckinghamshire Healthcare NHS Trust | B17: RXQ | C17: South of England Commissioning Region | D17: 118.08754 | E17: 9.05625 | F17: 24.9 | G17: 54.678635 | H17: 29.452658 | I17: 1.351348 | J17: 0.10363621 | K17: 0.28494593 | L17: 0.62572106 | M17: 0.33704477 | N17: 87385 | O17: 0.75081536 | P17: 0.054357155 | Q17: 0.648 | R17: 0.8125 | S17: 0.60273973 | T17: 0.66666667 | U17: 65610 | V17: 4750
... A21: Chelsea and Westminster Hospital NHS Foundation Trust | B21: RQM | C21: London Commissioning Region | D21: 312.98968 | E21: 17.5625 | F21: 85.003125 | G21: 166.54072 | H21: 43.883333 | I21: 1.5170844 | J21: 0.085126751 | K21: 0.4120165 | L21: 0.80723534 | M21: 0.21270579 | N21: 206310 | O21: 0.87055887 | P21: 0.0054287238 | Q21: 0.74418605 | R21: 0.77777778 | S21: 0.76646707 | T21: 0.6 | U21: 179605 | V21: 1120
A22: Chesterfield Royal Hospital NHS Foundation Trust | B22: RFS | C22: Midlands and East of England Commissioning Region | D22: 120.8275 | E22: 8.0825 | F22: 21.7 | G22: 50.2225 | H22: 40.8225 | I22: 1.4865588 | J22: 0.099440207 | K22: 0.26697835 | L22: 0.61789493 | M22: 0.50224532 | N22: 81280 | O22: 0.91664616 | P22: 0.00036909449 | Q22: #N/A | R22: #N/A | S22: #N/A | T22: #N/A | U22: 74505 | V22: 30
A23: City Hospitals Sunderland NHS Foundation Trust | B23: RLN | C23: North of England Commissioning Region | D23: 197.29271 | E23: 10.4 | F23: 28.659375 | G23: 117.91001 | H23: 40.323332 | I23: 1.2521751 | J23: 0.066006601 | K23: 0.18189499 | L23: 0.74834987 | M23: 0.25592366 | N23: 157560 | O23: 0.91212871 | P23: 0.00047600914 | Q23: 0.87150838 | R23: 0.92307692 | S23: 0.84090909 | T23: 0.97058824 | U23: 143715 | V23: 75
A24: Colchester Hospital University NHS Foundation Trust | B24: RDE | C24: Midlands and East of England Commissioning Region | D24: 183.01146 | E24: 11.25 | F24: 23.94375 | G24: 91.754993 | H24: 56.06272 | I24: 2.0084664 | J24: 0.12346356 | K24: 0.26277162 | L24: 1.0069687 | M24: 0.61526251 | N24: 91120 | O24: 0.82572432 | P24: 0.016791045 | Q24: 0.80487805 | R24: 0.86363636 | S24: 0.82191781 | T24: 0.71428571 | U24: 75240 | V24: 1530
A25: Countess of Chester Hospital NHS Foundation Trust | B25: RJR | C25: North of England Commissioning Region | D25: 114.9975 | E25: 7.85 | F25: 21.2625 | G25: 64.485 | H25: 21.4 | I25: 1.3901179 | J25: 0.094892717 | K25: 0.25702629 | L25: 0.77951043 | M25: 0.25868843 | N25: 82725 | O25: 0.83723179 | P25: 0.002175884 | Q25: 0.78991597 | R25: 0.64705882 | S25: 0.80519481 | T25: 0.8 | U25: 69260 | V25: 180
A26: County Durham and Darlington NHS Foundation Trust | B26: RXP | C26: North of England Commissioning Region | D26: 200.20485 | E26: 10.81 | F26: 35.1625 | G26: 106.29667 | H26: 47.935685 | I26: 0.95174753 | J26: 0.051389318 | K26: 0.1671579 | L26: 0.50532038 | M26: 0.22787994 | N26: 210355 | O26: 0.9140976 | P26: 0.0051341779 | Q26: 0.85714286 | R26: 0.86363636 | S26: 0.8411215 | T26: 0.81666667 | U26: 192285 | V26: 1080
A27: Croydon Health Services NHS Trust | B27: RJ6 | C27: London Commissioning Region | D27: 169.71207 | E27: 7.525 | F27: 22.770313 | G27: 78.875107 | H27: 60.541648 | I27: 0.96424572 | J27: 0.042754467 | K27: 0.1293731 | L27: 0.44814129 | M27: 0.34397686 | N27: 176005 | O27: 0.89182126 | P27: 0.0097724496 | Q27: 0.72352941 | R27: 0.88888889 | S27: 0.61956522 | T27: 0.73913043 | U27: 156965 | V27: 1720
A28: Dartford and Gravesham NHS Trust | B28: RN7 | C28: South of England Commissioning Region | D28: 141.21535 | E28: 8 | F28: 26.775 | G28: 63.993712 | H28: 42.44664 | I28: 1.1234316 | J28: 0.063643596 | K28: 0.21300716 | L28: 0.50909875 | M28: 0.3376821 | N28: 125700 | O28: 0.87871917 | P28: 0.021519491 | Q28: 0.81506849 | R28: 0.77777778 | S28: 0.85507246 | T28: 0.78 | U28: 110455 | V28: 2705
A29: Derby Teaching Hospitals NHS Foundation Trust | B29: RTG | C29: Midlands and East of England Commissioning Region | D29: 290.65564 | E29: 16.3083 | F29: 53.604688 | G29: 132.49934 | H29: 88.243313 | I29: 2.1814443 | J29: 0.12239793 | K29: 0.40231678 | L29: 0.99444118 | M29: 0.66228845 | N29: 133240 | O29: 0.81004203 | P29: 0.0011633143 | Q29: 0.84320557 | R29: 0.92307692 | S29: 0.8013245 | T29: 0.87628866 | U29: 107930 | V29: 155
A30: Doncaster and Bassetlaw Teaching Hospitals NHS Foundation Trust | B30: RP5 | C30: North of England Commissioning Region | D30: 313.74152 | E30: 14.05 | F30: 41.25 | G30: 139.52013 | H30: 118.92139 | I30: 1.965368 | J30: 0.08801328 | K30: 0.25840198 | L30: 0.87399461 | M30: 0.74495811 | N30: 159635 | O30: 0.91017008 | P30: 0.0016287155 | Q30: 0.84364821 | R30: 0.90909091 | S30: 0.83870968 | T30: 0.83076923 | U30: 145295 | V30: 260
A31: Dorset County Hospital NHS Foundation Trust | B31: RBD | C31: South of England Commissioning Region | D31: 84.890533 | E31: 7.66875 | F31: 20.41875 | G31: 43.669705 | H31: 13.133328 | I31: 0.90429329 | J31: 0.081691079 | K31: 0.21750999 | L31: 0.46518993 | M31: 0.13990229 | N31: 93875 | O31: 0.97667111 | P31: 0.00015978695 | Q31: 0.80519481 | R31: 0.77777778 | S31: 0.86046512 | T31: 0.6875 | U31: 91685 | V31: 15
A32: Dudley Group NHS Foundation Trust | B32: RNA | C32: Midlands and East of England Commissioning Region | D32: 164.52689 | E32: 8 | F32: 23.559687 | G32: 71.8672 | H32: 61.1 | I32: 1.5903232 | J32: 0.077328307 | K32: 0.22772884 | L32: 0.69467111 | M32: 0.59059494 | N32: 103455 | O32: 0.78391571 | P32: 0.024793388 | Q32: 0.80124224 | R32: 1 | S32: 0.74074074 | T32: 0.83333333 | U32: 81100 | V32: 2565
A33: East and North Hertfordshire NHS Trust | B33: RWH | C33: Midlands and East of England Commissioning Region | D33: 213.47899 | E33: 7.7 | F33: 35.986 | G33: 127.21066 | H33: 42.582337 | I33: 1.5244688 | J33: 0.054986253 | K33: 0.25697861 | L33: 0.90842043 | M33: 0.30408353 | N33: 140035 | O33: 0.80487021 | P33: 0.019423715 | Q33: 0.81094527 | R33: 0.75 | S33: 0.85074627 | T33: 0.7254902 | U33: 112710 | V33: 2720
A34: East Cheshire NHS Trust | B34: RJN | C34: North of England Commissioning Region | D34: 35.376955 | E34: 5.71875 | F34: 16.721875 | G34: 1.15 | H34: 11.78633 | I34: 0.70171487 | J34: 0.1134335 | K34: 0.33168452 | L34: 0.022810671 | M34: 0.23378617 | N34: 50415 | O34: 0.81176237 | P34: 0.024695031 | Q34: 0.77777778 | R34: 0.84615385 | S34: 0.33333333 | T34: 0.8 | U34: 40925 | V34: 1245
A35: East Kent Hospitals University NHS Foundation Trust | B35: RVV | C35: South of England Commissioning Region | D35: 372.61044 | E35: 11 | F35: 33.015625 | G35: 188.09813 | H35: 140.49669 | I35: 1.9051074 | J35: 0.056241532 | K35: 0.16880448 | L35: 0.96172063 | M35: 0.7183408 | N35: 195585 | O35: 0.7031981 | P35: 0.050463993 | Q35: 0.69248826 | R35: 0.75 | S35: 0.65384615 | T35: 0.73809524 | U35: 137535 | V35: 9870
A36: East Lancashire Hospitals NHS Trust | B36: RXR | C36: North of England Commissioning Region | D36: 51.913337 | F36: 11.675 | G36: 16.866663 | H36: 23.371675 | I36: 0.30214671 | K36: 0.067950994 | L36: 0.098167579 | M36: 0.13602814 | N36: 171815 | O36: 0.79475017 | P36: 0.0163548 | Q36: 0.84375 | R36: 0 | S36: 0.9 | T36: 0.75 | U36: 136550 | V36: 2810
A37: East Sussex Healthcare NHS Trust | B37: RXC | C37: South of England Commissioning Region | D37: 189.02964 | E37: 8.6625 | F37: 33.215625 | G37: 94.168795 | H37: 52.982722 | I37: 1.6048703 | J37: 0.073545018 | K37: 0.28200216 | L37: 0.79949735 | M37: 0.44982572 | N37: 117785 | O37: 0.78579615 | P37: 0.040539967 | Q37: 0.8125 | R37: 0.64705882 | S37: 0.79207921 | T37: 0.89655172 | U37: 92555 | V37: 4775
A38: Epsom and St Helier University Hospitals NHS Trust | B38: RVR | C38: London Commissioning Region | D38: 192.86651 | E38: 11.75 | F38: 40.875 | G38: 100.36554 | H38: 39.875968 | I38: 1.2512424 | J38: 0.076229402 | K38: 0.265181 | L38: 0.65113233 | M38: 0.25869967 | N38: 154140 | O38: 0.92594395 | P38: 0.0075580641 | Q38: 0.74731183 | R38: 0.85714286 | S38: 0.73636364 | T38: 0.6875 | U38: 142725 | V38: 1165
A39: Frimley Health NHS Foundation Trust | B39: RDU | C39: South of England Commissioning Region | D39: 378.95529 | E39: 22.91875 | F39: 72.0125 | G39: 200.03406 | H39: 83.989982 | I39: 1.587214 | J39: 0.095992754 | K39: 0.30161672 | L39: 0.83782144 | M39: 0.35178314 | N39: 238755 | O39: 0.88980335 | P39: 0.011706561 | Q39: 0.78021978 | R39: 0.78125 | S39: 0.76271186 | T39: 0.82291667 | U39: 212445 | V39: 2795
A40: Gateshead Health NHS Foundation Trust | B40: RR7 | C40: North of England Commissioning Region | D40: 133.58144 | E40: 8.1045 | F40: 23.028125 | G40: 69.75 | H40: 32.698813 | I40: 1.1548495 | J40: 0.070065704 | K40: 0.19908468 | L40: 0.60300856 | M40: 0.28269052 | N40: 115670 | O40: 0.94618311 | P40: 0.00025935852 | Q40: 0.75630252 | R40: 1 | S40: 0.71621622 | T40: 0.78378378 | U40: 109445 | V40: 30
A41: George Eliot Hospital NHS Trust | B41: RLT | C41: Midlands and East of England Commissioning Region | D41: 96.301672 | E41: 5.35 | F41: 6.1 | G41: 56.95001 | H41: 27.901663 | I41: 1.1950322 | J41: 0.066389527 | K41: 0.07569647 | L41: 0.70670733 | M41: 0.34623891 | N41: 80585 | O41: 0.87776882 | P41: 0.023639635 | Q41: 0.77118644 | R41: 1 | S41: 0.75 | T41: 0.76190476 | U41: 70735 | V41: 1905
A42: Gloucestershire Hospitals NHS Foundation Trust | B42: RTE | C42: South of England Commissioning Region | D42: 214.91201 | E42: 19.3 | F42: 31 | G42: 116.72339 | H42: 47.888625 | I42: 1.521501 | J42: 0.13663717 | K42: 0.21946903 | L42: 0.82636027 | M42: 0.33903451 | N42: 141250 | O42: 0.86700885 | P42: 0.0028672566 | Q42: 0.84716157 | R42: 1 | S42: 0.85915493 | T42: 0.765625 | U42: 122465 | V42: 405
A43: Great Western Hospitals NHS Foundation Trust | B43: RN3 | C43: South of England Commissioning Region | D43: 145.09369 | E43: 10.2167 | F43: 23.53105 | G43: 62.69754 | H43: 48.648405 | I43: 1.2544304 | J43: 0.088330091 | K43: 0.2034414 | L43: 0.54206147 | M43: 0.42059746 | N43: 115665 | O43: 0.84342714 | P43: 0.028400986 | Q43: 0.82089552 | R43: 1 | S43: 0.77272727 | T43: 0.83928571 | U43: 97555 | V43: 3285
A44: Guy's and St Thomas' NHS Foundation Trust | B44: RJ1 | C44: London Commissioning Region | D44: 311.15827 | E44: 24.1875 | F44: 67.290625 | G44: 169.35701 | H44: 50.323135 | I44: 1.7276972 | J44: 0.13430039 | K44: 0.37362923 | L44: 0.94034988 | M44: 0.27941774 | N44: 180100 | O44: 0.86288173 | P44: 0.00072182121 | Q44: 0.75185185 | R44: 0.91666667 | S44: 0.72972973 | T44: 0.75409836 | U44: 155405 | V44: 130
A45: Hampshire Hospitals NHS Foundation Trust | B45: RN5 | C45: South of England Commissioning Region | D45: 195.31941 | E45: 11.5 | F45: 29.941043 | G45: 104.36999 | H45: 49.508382 | I45: 1.5774464 | J45: 0.092876757 | K45: 0.24181104 | L45: 0.84291704 | M45: 0.39984156 | N45: 123820 | O45: 0.86811501 | P45: 0.009570344 | Q45: 0.73459716 | R45: 1 | S45: 0.77419355 | T45: 0.56410256 | U45: 107490 | V45: 1185
A46: Harrogate and District NHS Foundation Trust | B46: RCD | C46: North of England Commissioning Region | D46: 79.95823 | E46: 6.075 | F46: 22.576563 | G46: 31.796673 | H46: 19.509995 | I46: 1.6158074 | J46: 0.12276447 | K46: 0.45623042 | L46: 0.64255173 | M46: 0.39426079 | N46: 49485 | O46: 0.94180055 | P46: 0.00020208144 | Q46: 0.72289157 | R46: 0.88235294 | S46: 0.65 | T46: 0.73076923 | U46: 46605 | V46: 10
A47: Hillingdon Hospitals NHS Foundation Trust | B47: RAS | C47: London Commissioning Region | D47: 152.87466 | E47: 9.45 | F47: 28.525 | G47: 79.206682 | H47: 35.69298 | I47: 1.6235627 | J47: 0.10036109 | K47: 0.3029418 | L47: 0.84119246 | M47: 0.37906733 | N47: 94160 | O47: 0.74293755 | P47: 0.03175446 | Q47: 0.72159091 | R47: 0.88 | S47: 0.76744186 | T47: 0.6 | U47: 69955 | V47: 2990
A48: Homerton University Hospital NHS Foundation Trust | B48: RQX | C48: London Commissioning Region | D48: 131.39335 | E48: 9.98125 | F48: 33.956565 | G48: 64.33333 | H48: 23.122205 | I48: 1.0774362 | J48: 0.081847068 | K48: 0.27844662 | L48: 0.52753858 | M48: 0.18960398 | N48: 121950 | O48: 0.73226732 | P48: 0.03202132 | Q48: 0.75 | R48: 0.92857143 | S48: 0.77272727 | T48: 0.625 | U48: 89300 | V48: 3905
A49: Hounslow and Richmond Community Healthcare NHS Trust | B49: RY9 | C49: London Commissioning Region | D49: 16.158167 | F49: 0.06818 | G49: 8.7399875 | H49: 7.35 | I49: 0.10551239 | K49: 0.00044521353 | L49: 0.057071879 | M49: 0.047995298 | N49: 153140 | O49: 0.99275173 | P49: 6.5299726e-05 | Q49: 0.68181818 | R49: 0 | S49: 0.66666667 | T49: 0.77777778 | U49: 152030 | V49: 10
A50: Hull and East Yorkshire Hospitals NHS Trust | B50: RWA | C50: North of England Commissioning Region | D50: 176.01262 | E50: 16.25 | F50: 36.435938 | G50: 92.283337 | H50: 31.043342 | I50: 1.1991594 | J50: 0.11070991 | K50: 0.24823503 | L50: 0.62871875 | M50: 0.21149572 | N50: 146780 | O50: 0.87164464 | P50: 0.0048031067 | Q50: 0.82978723 | R50: 1 | S50: 0.78723404 | T50: 0.87096774 | U50: 127940 | V50: 705
A51: Imperial College Healthcare NHS Trust | B51: RYJ | C51: London Commissioning Region | D51: 325.71298 | E51: 25.4 | F51: 77.92216 | G51: 162.92248 | H51: 59.468332 | I51: 1.3570526 | J51: 0.10582672 | K51: 0.32465538 | L51: 0.67880126 | M51: 0.24776923 | N51: 240015 | O51: 0.83134387 | P51: 0.015415703 | Q51: 0.70881226 | R51: 0.85185185 | S51: 0.69411765 | T51: 0.6875 | U51: 199535 | V51: 3700
A52: Ipswich Hospital NHS Trust | B52: RGQ | C52: Midlands and East of England Commissioning Region | D52: 164.9998 | E52: 12.7875 | F52: 33.45 | G52: 77.795758 | H52: 40.966543 | I52: 1.7923072 | J52: 0.13890398 | K52: 0.36334999 | L52: 0.84505494 | M52: 0.44499829 | N52: 92060 | O52: 0.9071801 | P52: 0.00032587443 | Q52: 0.80379747 | R52: 0.7826087 | S52: 0.81609195 | T52: 0.79166667 | U52: 83515 | V52: 30
A53: Isle of Wight NHS Trust | B53: R1F | C53: South of England Commissioning Region | D53: 57.846672 | E53: 4 | F53: 11.85 | G53: 24.90167 | H53: 17.095002 | I53: 1.1640341 | J53: 0.080490995 | K53: 0.23845457 | L53: 0.50109005 | M53: 0.34399844 | N53: 49695 | O53: 0.82654191 | P53: 0.02525405 | Q53: 0.70689655 | R53: 1 | S53: 0.55555556 | T53: 0.75 | U53: 41075 | V53: 1255
A54: James Paget University Hospitals NHS Foundation Trust | B54: RGP | C54: Midlands and East of England Commissioning Region | D54: 88.557035 | E54: 4.85 | F54: 12.4875 | G54: 48.173805 | H54: 23.04573 | I54: 1.1442217 | J54: 0.062665547 | K54: 0.16134763 | L54: 0.62244079 | M54: 0.29776769 | N54: 77395 | O54: 0.90490342 | P54: 0.013114542 | Q54: 0.89473684 | R54: 0.86666667 | S54: 0.89795918 | T54: 0.91666667 | U54: 70035 | V54: 1015
A55: Kent Community Health NHS Foundation Trust | B55: RYY | C55: South of England Commissioning Region | D55: 2.533335 | F55: 0 | G55: 1.813335 | H55: 0.72 | I55: 0.033226244 | K55: 0 | L55: 0.023783002 | M55: 0.0094432422 | N55: 76245 | O55: 0.99836055 | Q55: 0.75 | R55: 0 | S55: 0.66666667 | T55: 1 | U55: 76120 | V55: *
A56: Kettering General Hospital NHS Foundation Trust | B56: RNQ | C56: Midlands and East of England Commissioning Region | D56: 150.53999 | E56: 6 | F56: 24.325 | G56: 69.608328 | H56: 50.606665 | I56: 1.7325353 | J56: 0.069052825 | K56: 0.27995166 | L56: 0.80110861 | M56: 0.5824222 | N56: 86890 | O56: 0.76827023 | P56: 0.034641501 | Q56: 0.73493976 | R56: 0.86363636 | S56: 0.73333333 | T56: 0.69565217 | U56: 66755 | V56: 3010
A57: King's College Hospital NHS Foundation Trust | B57: RJZ | C57: London Commissioning Region | D57: 438.58555 | E57: 22.75 | F57: 76.29375 | G57: 290.03448 | H57: 49.507317 | I57: 1.920294 | J57: 0.099608135 | K57: 0.334043 | L57: 1.269881 | M57: 0.21676183 | N57: 228395 | O57: 0.77613345 | P57: 0.027737035 | Q57: 0.75342466 | R57: 0.91666667 | S57: 0.74496644 | T57: 0.6744186 | U57: 177265 | V57: 6335
A58: Kingston Hospital NHS Foundation Trust | B58: RAX | C58: London Commissioning Region | D58: 144.30559 | E58: 9.775 | F58: 23.396875 | G58: 73.136647 | H58: 37.997065 | I58: 1.2335392 | J58: 0.083557721 | K58: 0.19999893 | L58: 0.6251797 | M58: 0.32480288 | N58: 116985 | O58: 0.7972817 | P58: 0.01389067 | Q58: 0.69924812 | R58: 0.92307692 | S58: 0.68918919 | T58: 0.60869565 | U58: 93270 | V58: 1625
A59: Lancashire Teaching Hospitals NHS Foundation Trust | B59: RXN | C59: North of England Commissioning Region | D59: 209.24531 | E59: 19.37 | F59: 34.66875 | G59: 90.636585 | H59: 64.569975 | I59: 2.2441582 | J59: 0.20774346 | K59: 0.37182272 | L59: 0.97207835 | M59: 0.69251367 | N59: 93240 | O59: 0.75353925 | P59: 0.025579151 | Q59: 0.82125604 | R59: 0.91666667 | S59: 0.7706422 | T59: 0.86486486 | U59: 70260 | V59: 2385
A60: Leeds Teaching Hospitals NHS Trust | B60: RR8 | C60: North of England Commissioning Region | D60: 440.68607 | E60: 31.77 | F60: 52.774062 | G60: 219.33 | H60: 136.812 | I60: 2.0703581 | J60: 0.14925654 | K60: 0.24793433 | L60: 1.0304198 | M60: 0.64274742 | N60: 212855 | O60: 0.80601818 | P60: 0.024241855 | Q60: 0.72235872 | R60: 0.89189189 | S60: 0.65254237 | T60: 0.7761194 | U60: 171565 | V60: 5160
A61: Lewisham and Greenwich NHS Trust | B61: RJ2 | C61: London Commissioning Region | D61: 362.77452 | E61: 17.55 | F61: 64.892187 | G61: 209.14348 | H61: 71.188855 | I61: 1.6863821 | J61: 0.081582373 | K61: 0.30165576 | L61: 0.97221773 | M61: 0.33092625 | N61: 215120 | O61: 0.80136668 | P61: 0.035793975 | Q61: 0.7880597 | R61: 0.85 | S61: 0.79324895 | T61: 0.73076923 | U61: 172390 | V61: 7700
A62: Lincolnshire Community Health Services NHS Trust | B62: RY5 | C62: Midlands and East of England Commissioning Region | D62: 31.226668 | F62: 0 | G62: 14.549997 | H62: 16.67667 | I62: 0.21269399 | J62: 0 | K62: 0 | L62: 0.099104298 | M62: 0.11358969 | N62: 146815 | O62: 0.9905323 | P62: 0.00013622586 | Q62: 0.58536585 | R62: 0 | S62: 0.375 | T62: 0.88235294 | U62: 145425 | V62: 20
A63: Luton and Dunstable University Hospital NHS Foundation Trust | B63: RC9 | C63: Midlands and East of England Commissioning Region | D63: 177.94971 | E63: 9.75 | F63: 41.334375 | G63: 94.892437 | H63: 31.972897 | I63: 1.6912156 | J63: 0.092662992 | K63: 0.39283763 | L63: 0.90184791 | M63: 0.30386711 | N63: 105220 | O63: 0.97742825 | P63: 0.00052271431 | Q63: 0.62561576 | R63: 1 | S63: 0.6015625 | T63: 0.58333333 | U63: 102845 | V63: 55
A64: Maidstone and Tunbridge Wells NHS Trust | B64: RWF | C64: South of England Commissioning Region | D64: 249.71827 | E64: 13.2 | F64: 42.475 | G64: 134.22195 | H64: 59.821325 | I64: 1.4671618 | J64: 0.077553538 | K64: 0.24955201 | L64: 0.78858992 | M64: 0.35146632 | N64: 170205 | O64: 0.89224758 | P64: 0.030786405 | Q64: 0.74786325 | R64: 0.88888889 | S64: 0.69127517 | T64: 0.80597015 | U64: 151865 | V64: 5240
A65: Medway NHS Foundation Trust | B65: RPA | C65: South of England Commissioning Region | D65: 142.74264 | E65: 6.6 | F65: 35.809375 | G65: 71.923282 | H65: 28.409983 | I65: 1.1744982 | J65: 0.054305344 | K65: 0.29464249 | L65: 0.5917907 | M65: 0.23375968 | N65: 121535 | O65: 0.83412186 | P65: 0.039371375 | Q65: 0.78512397 | R65: 0.95652174 | S65: 0.82539683 | T65: 0.48571429 | U65: 101375 | V65: 4785
A66: Mid Cheshire Hospitals NHS Foundation Trust | B66: RBT | C66: North of England Commissioning Region | D66: 180.64955 | E66: 7.35 | F66: 13.191 | G66: 94.141482 | H66: 65.967073 | I66: 2.0484131 | J66: 0.083342783 | K66: 0.14957478 | L66: 1.0674848 | M66: 0.7480108 | N66: 88190 | O66: 0.87226443 | P66: 0.0062932305 | Q66: 0.77941176 | R66: 0.71428571 | S66: 0.75471698 | T66: 0.82142857 | U66: 76925 | V66: 555
A67: Mid Essex Hospital Services NHS Trust | B67: RQ8 | C67: Midlands and East of England Commissioning Region | D67: 119.10979 | E67: 6.875 | F67: 23.478125 | G67: 58.130003 | H67: 30.626665 | I67: 1.1822312 | J67: 0.068238213 | K67: 0.2330335 | L67: 0.57697273 | M67: 0.30398675 | N67: 100750 | O67: 0.8155335 | P67: 0.019751861 | Q67: 0.71287129 | R67: 0.8 | S67: 0.703125 | T67: 0.6875 | U67: 82165 | V67: 1990
A68: Mid Yorkshire Hospitals NHS Trust | B68: RXF | C68: North of England Commissioning Region | D68: 259.0564 | E68: 17.5 | F68: 42.828125 | G68: 129.98164 | H68: 68.746638 | I68: 1.080347 | J68: 0.072980525 | K68: 0.1786068 | L68: 0.54206446 | M68: 0.28669518 | N68: 239790 | O68: 0.85157846 | P68: 0.010717711 | Q68: 0.84033613 | R68: 0.91304348 | S68: 0.83088235 | T68: 0.83544304 | U68: 204200 | V68: 2570
A69: Milton Keynes University Hospital NHS Foundation Trust | B69: RD8 | C69: Midlands and East of England Commissioning Region | D69: 120.87378 | E69: 8.05 | F69: 23.8438 | G69: 57.41665 | H69: 31.563335 | I69: 1.3878384 | J69: 0.092427809 | K69: 0.27376772 | L69: 0.65924163 | M69: 0.36240123 | N69: 87095 | O69: 0.85303404 | P69: 0.022102302 | Q69: 0.84615385 | R69: 1 | S69: 0.80645161 | T69: 0.85 | U69: 74295 | V69: 1925
A70: Moorfields Eye Hospital NHS Foundation Trust | B70: RP6 | C70: London Commissioning Region | D70: 67.983333 | E70: 6.2566667 | F70: 6.9666667 | G70: 49.426667 | H70: 5.3333333 | I70: 0.71550106 | J70: 0.065849252 | K70: 0.073321756 | L70: 0.52019857 | M70: 0.056131488 | N70: 95015 | O70: 0.98516024 | Q70: #N/A | R70: #N/A | S70: #N/A | T70: #N/A | U70: 93605 | V70: *
A71: Newcastle Upon Tyne Hospitals NHS Foundation Trust | B71: RTD | C71: North of England Commissioning Region | D71: 211.72163 | E71: 16.7 | F71: 32.021875 | G71: 111.24808 | H71: 51.75167 | I71: 1.0766419 | J71: 0.084922451 | K71: 0.16283689 | L71: 0.56571616 | M71: 0.26316639 | N71: 196650 | O71: 0.93737605 | P71: 0.00017798118 | Q71: 0.85353535 | R71: 0.95454545 | S71: 0.85087719 | T71: 0.80645161 | U71: 184335 | V71: 35
A72: Norfolk and Norwich University Hospitals NHS Foundation Trust | B72: RM1 | C72: Midlands and East of England Commissioning Region | D72: 183.70334 | F72: 6.675 | G72: 110.06168 | H72: 66.966662 | I72: 1.3999111 | J72: 0 | K72: 0.050866832 | L72: 0.8387249 | M72: 0.51031939 | N72: 131225 | O72: 0.80720137 | P72: 0.014974281 | Q72: 0.76666667 | R72: 0.5 | S72: 0.72519084 | T72: 0.84415584 | U72: 105925 | V72: 1965
A73: North Bristol NHS Trust | B73: RVJ | C73: South of England Commissioning Region | D73: 212.82242 | E73: 11.6 | F73: 27.7477 | G73: 111.05865 | H73: 62.416068 | I73: 2.4360146 | J73: 0.13277628 | K73: 0.31760659 | L73: 1.271203 | M73: 0.71442875 | N73: 87365 | O73: 0.75756882 | P73: 0.034338694 | Q73: 0.73684211 | R73: 0.95 | S73: 0.775 | T73: 0.63636364 | U73: 66185 | V73: 3000
A74: North Cumbria University Hospitals NHS Trust | B74: RNL | C74: North of England Commissioning Region | D74: 126.61333 | E74: 9.23125 | F74: 21.09375 | G74: 59.22 | H74: 37.068333 | I74: 1.3687928 | J74: 0.099797297 | K74: 0.22804054 | L74: 0.64021622 | M74: 0.40073873 | N74: 92500 | O74: 0.8807027 | P74: 0.008 | Q74: 0.71929825 | R74: 0.7 | S74: 0.63076923 | T74: 0.82051282 | U74: 81465 | V74: 740
A75: North Middlesex University Hospital NHS Trust | B75: RAP | C75: London Commissioning Region | D75: 217.38168 | E75: 11.138333 | F75: 39.3 | G75: 115.90671 | H75: 51.036635 | I75: 1.2410464 | J75: 0.063589475 | K75: 0.22436629 | L75: 0.66171909 | M75: 0.29137152 | N75: 175160 | O75: 0.81008792 | P75: 0.008392327 | Q75: 0.75 | R75: 0.68421053 | S75: 0.73643411 | T75: 0.8125 | U75: 141895 | V75: 1470
A76: North Tees and Hartlepool NHS Foundation Trust | B76: RVW | C76: North of England Commissioning Region | D76: 140.32256 | E76: 9.175 | F76: 28.34091 | G76: 54.219985 | H76: 48.58667 | I76: 0.85294693 | J76: 0.055769991 | K76: 0.17226946 | L76: 0.32957472 | M76: 0.29533277 | N76: 164515 | O76: 0.95419871 | P76: 0.00018235419 | Q76: 0.71942446 | R76: 0.875 | S76: 0.57142857 | T76: 0.83018868 | U76: 156980 | V76: 30
A77: North West Anglia NHS Foundation Trust | B77: RGN | C77: Midlands and East of England Commissioning Region | D77: 237.91292 | E77: 12.375 | F77: 37.115437 | G77: 136.88998 | H77: 51.532498 | I77: 1.5862447 | J77: 0.082508251 | K77: 0.247461 | L77: 0.91269114 | M77: 0.34358434 | N77: 149985 | O77: 0.80774744 | P77: 0.01560156 | Q77: 0.72469636 | R77: 0.71428571 | S77: 0.7195122 | T77: 0.70967742 | U77: 121150 | V77: 2340
A78: Northampton General Hospital NHS Trust | B78: RNS | C78: Midlands and East of England Commissioning Region | D78: 163.96216 | E78: 8.95 | F78: 24.735135 | G78: 88.131645 | H78: 42.145383 | I78: 1.3376477 | J78: 0.07301652 | K78: 0.20179592 | L78: 0.71900179 | M78: 0.34383343 | N78: 122575 | O78: 0.85111156 | P78: 0.034835815 | Q78: 0.76506024 | R78: 0.91666667 | S78: 0.77669903 | T78: 0.68627451 | U78: 104325 | V78: 4270
A79: Northern Devon Healthcare NHS Trust | B79: RBZ | C79: South of England Commissioning Region | D79: 64.364113 | E79: 4.575 | F79: 12.753125 | G79: 37.885 | H79: 9.1509875 | I79: 1.1638028 | J79: 0.082723081 | K79: 0.23059624 | L79: 0.68501944 | M79: 0.16546402 | N79: 55305 | O79: 0.86918 | P79: 0.032818009 | Q79: 0.8028169 | R79: 0.69230769 | S79: 0.81395349 | T79: 0.86666667 | U79: 48070 | V79: 1815
A80: Northern Lincolnshire and Goole NHS Foundation Trust | B80: RJL | C80: North of England Commissioning Region | D80: 156.87677 | E80: 9.85 | F80: 25.939772 | G80: 87.993663 | H80: 33.093333 | I80: 1.0426823 | J80: 0.06546808 | K80: 0.17240884 | L80: 0.58485037 | M80: 0.21995502 | N80: 150455 | O80: 0.85510618 | P80: 0.0023595095 | Q80: 0.83850932 | R80: 0.89473684 | S80: 0.81730769 | T80: 0.86842105 | U80: 128655 | V80: 355
A81: Northumbria Healthcare NHS Foundation Trust | B81: RTF | C81: North of England Commissioning Region | D81: 232.93774 | E81: 23.8725 | F81: 53.803125 | G81: 81.503317 | H81: 73.758798 | I81: 1.2058379 | J81: 0.12357966 | K81: 0.27852012 | L81: 0.42191442 | M81: 0.38182372 | N81: 193175 | O81: 0.93234114 | P81: 0 | Q81: 0.88557214 | R81: 0.96875 | S81: 0.85714286 | T81: 0.88235294 | U81: 180105 | V81: 0
A82: Nottingham University Hospitals NHS Trust | B82: RX1 | C82: Midlands and East of England Commissioning Region | D82: 411.85786 | E82: 20.3 | F82: 34.614063 | G82: 247.73503 | H82: 109.20877 | I82: 2.0784107 | J82: 0.10244247 | K82: 0.17467734 | L82: 1.2501768 | M82: 0.55111411 | N82: 198160 | O82: 0.79867279 | P82: 0.0099414614 | Q82: 0.75260417 | R82: 1 | S82: 0.71031746 | T82: 0.79439252 | U82: 158265 | V82: 1970
A83: Oxford University Hospitals NHS Foundation Trust | B83: RTH | C83: South of England Commissioning Region | D83: 249.24729 | E83: 17.8 | F83: 35.748438 | G83: 127.11963 | H83: 68.57922 | I83: 1.8326333 | J83: 0.13087754 | K83: 0.26284649 | L83: 0.93466882 | M83: 0.50424043 | N83: 136005 | O83: 0.80364692 | P83: 0.037976545 | Q83: 0.80384615 | R83: 0.96 | S83: 0.73758865 | T83: 0.86170213 | U83: 109300 | V83: 5165
A84: Pennine Acute Hospitals NHS Trust | B84: RW6 | C84: North of England Commissioning Region | D84: 445.57993 | E84: 23.05 | F84: 85.470313 | G84: 227.87563 | H84: 109.18399 | I84: 1.3545316 | J84: 0.070070374 | K84: 0.25982372 | L84: 0.69272584 | M84: 0.33191162 | N84: 328955 | O84: 0.8230913 | P84: 0.018862762 | Q84: 0.82307692 | R84: 0.86111111 | S84: 0.78017241 | T84: 0.87704918 | U84: 270760 | V84: 6205
... A89: Queen Elizabeth Hospital King's Lynn NHS Foundation Trust | B89: RCX | C89: Midlands and East of England Commissioning Region | D89: 86.98335 | E89: 5.25 | F89: 15.1 | G89: 46.89001 | H89: 19.74334 | I89: 1.3956414 | J89: 0.08423586 | K89: 0.24227838 | L89: 0.75234673 | M89: 0.31678043 | N89: 62325 | O89: 0.85511432 | P89: 0.011472122 | Q89: 0.80722892 | R89: 1 | S89: 0.73684211 | T89: 0.94444444 | U89: 53295 | V89: 715
A90: Queen Victoria Hospital NHS Foundation Trust | B90: RPC | C90: South of England Commissioning Region | D90: 6.144935 | F90: 0.05 | H90: 6.094935 | I90: 0.56118128 | J90: 0 | K90: 0.00456621 | L90: 0 | M90: 0.55661507 | N90: 10950 | O90: 0.99680365 | P90: 0 | Q90: 0.7 | R90: 0 | S90: 0 | T90: 0.77777778 | U90: 10915 | V90: 0
A91: Rotherham NHS Foundation Trust | B91: RFR | C91: North of England Commissioning Region | D91: 134.01249 | E91: 8.25625 | F91: 12.65 | G91: 67.381497 | H91: 45.72474 | I91: 1.4915135 | J91: 0.09188926 | K91: 0.14079021 | L91: 0.74993319 | M91: 0.50890083 | N91: 89850 | O91: 0.82020033 | P91: 0.010962716 | Q91: 0.80769231 | R91: 0.90909091 | S91: 0.72857143 | T91: 0.89795918 | U91: 73695 | V91: 985
A92: Royal Berkshire NHS Foundation Trust | B92: RHW | C92: South of England Commissioning Region | D92: 176.69596 | E92: 12.925 | F92: 36.39091 | G92: 82.23472 | H92: 45.145325 | I92: 1.3689932 | J92: 0.10013946 | K92: 0.28194708 | L92: 0.63713272 | M92: 0.34977396 | N92: 129070 | O92: 0.88421012 | P92: 0.0047648563 | Q92: 0.73529412 | R92: 0.84615385 | S92: 0.69148936 | T92: 0.76 | U92: 114125 | V92: 615
A93: Royal Bournemouth and Christchurch Hospitals NHS Foundation Trust | B93: RDZ | C93: South of England Commissioning Region | D93: 141.64646 | E93: 9.19375 | F93: 22.48102 | G93: 65.190007 | H93: 44.78168 | I93: 1.555358 | J93: 0.10095256 | K93: 0.24685429 | L93: 0.71582308 | M93: 0.49172812 | N93: 91070 | O93: 0.80652246 | P93: 0.027945536 | Q93: 0.73856209 | R93: 0.76190476 | S93: 0.72727273 | T93: 0.74545455 | U93: 73450 | V93: 2545
A94: Royal Cornwall Hospitals NHS Trust | B94: REF | C94: South of England Commissioning Region | D94: 178.54149 | E94: 12.029 | F94: 37.40959 | G94: 73.22332 | H94: 55.879583 | I94: 1.0807269 | J94: 0.072812566 | K94: 0.22644345 | L94: 0.44322702 | M94: 0.33824389 | N94: 165205 | O94: 0.8737629 | P94: 0.012166702 | Q94: 0.80113636 | R94: 0.8 | S94: 0.7804878 | T94: 0.828125 | U94: 144350 | V94: 2010
A95: Royal Devon and Exeter NHS Foundation Trust | B95: RH8 | C95: South of England Commissioning Region | D95: 138.31214 | E95: 11.325 | F95: 32.048437 | G95: 60.416663 | H95: 34.522037 | I95: 1.2503357 | J95: 0.10237751 | K95: 0.28971648 | L95: 0.54616401 | M95: 0.31207772 | N95: 110620 | O95: 0.90164527 | P95: 0.0014915928 | Q95: 0.78030303 | R95: 0.95 | S95: 0.65217391 | T95: 0.90697674 | U95: 99740 | V95: 165
A96: Royal Free London NHS Foundation Trust | B96: RAL | C96: London Commissioning Region | D96: 335.94812 | E96: 17.9 | F96: 57.57041 | G96: 179.48067 | H96: 80.99704 | I96: 1.2731577 | J96: 0.067836435 | K96: 0.21817717 | L96: 0.68018597 | M96: 0.30695812 | N96: 263870 | O96: 0.86085951 | P96: 0.022662675 | Q96: 0.73899371 | R96: 0.85714286 | S96: 0.70526316 | T96: 0.74193548 | U96: 227155 | V96: 5980
A97: Royal Liverpool and Broadgreen University Hospitals NHS Trust | B97: RQ6 | C97: North of England Commissioning Region | D97: 199.01575 | E97: 12.95 | F97: 35.55455 | G97: 90.413333 | H97: 60.097862 | I97: 1.8228224 | J97: 0.11861147 | K97: 0.32565076 | L97: 0.82811259 | M97: 0.55044754 | N97: 109180 | O97: 0.75586188 | P97: 0.072311779 | Q97: 0.77297297 | R97: 0.95 | S97: 0.66 | T97: 0.87692308 | U97: 82525 | V97: 7895
A98: Royal Surrey County Hospital NHS Foundation Trust | B98: RA2 | C98: South of England Commissioning Region | D98: 107.22083 | E98: 10.075 | F98: 14.005125 | G98: 65.369052 | H98: 17.77165 | I98: 1.5115363 | J98: 0.14203144 | K98: 0.19743603 | L98: 0.92153454 | M98: 0.25053429 | N98: 70935 | O98: 0.94889688 | P98: 0.0023260732 | Q98: 0.79591837 | R98: 0.66666667 | S98: 0.84057971 | T98: 0.70588235 | U98: 67310 | V98: 165
A99: Royal United Hospitals Bath NHS Foundation Trust | B99: RD1 | C99: South of England Commissioning Region | D99: 184.45907 | E99: 9.15 | F99: 26.125 | G99: 71.175832 | H99: 78.008233 | I99: 2.5505955 | J99: 0.12652102 | K99: 0.3612417 | L99: 0.9841791 | M99: 1.0786537 | N99: 72320 | O99: 0.79604535 | P99: 0.023506637 | Q99: 0.79473684 | R99: 1 | S99: 0.73626374 | T99: 0.81609195 | U99: 57570 | V99: 1700
A100: Royal Wolverhampton NHS Trust | B100: RL4 | C100: Midlands and East of England Commissioning Region | D100: 191.61421 | E100: 16.5 | F100: 33.65625 | G100: 93.892983 | H100: 47.564978 | I100: 1.0541285 | J100: 0.090771558 | K100: 0.18515335 | L100: 0.51653408 | M100: 0.26166952 | N100: 181775 | O100: 0.87151699 | P100: 0.0055838262 | Q100: 0.75555556 | R100: 0.88235294 | S100: 0.71428571 | T100: 0.72413793 | U100: 158420 | V100: 1015
A101: Salford Royal NHS Foundation Trust | B101: RM3 | C101: North of England Commissioning Region | D101: 405.57499 | E101: 36.26875 | F101: 26.67957 | G101: 207.75668 | H101: 134.86999 | I101: 4.036777 | J101: 0.36099084 | K101: 0.26554763 | L101: 2.0678479 | M101: 1.3423907 | N101: 100470 | O101: 0.85284164 | P101: 0.0061212302 | Q101: 0.80798005 | R101: 0.93617021 | S101: 0.79906542 | T101: 0.77857143 | U101: 85685 | V101: 615
A102: Salisbury NHS Foundation Trust | B102: RNZ | C102: South of England Commissioning Region | D102: 79.65602 | E102: 9.125 | F102: 12.696875 | G102: 39.019148 | H102: 18.814998 | I102: 1.7228511 | J102: 0.19736131 | K102: 0.27461609 | L102: 0.84393095 | M102: 0.40694274 | N102: 46235 | O102: 0.91705418 | P102: 0.0025954364 | Q102: 0.7721519 | R102: 0.7 | S102: 0.7173913 | T102: 0.91304348 | U102: 42400 | V102: 120
A103: Sandwell and West Birmingham Hospitals NHS Trust | B103: RXK | C103: Midlands and East of England Commissioning Region | D103: 248.14906 | E103: 13.0375 | F103: 36.232813 | G103: 130.91995 | H103: 67.958798 | I103: 1.1270538 | J103: 0.059214261 | K103: 0.1645637 | L103: 0.59461769 | M103: 0.3086581 | N103: 220175 | O103: 0.83672079 | P103: 0.00072669467 | Q103: 0.70980392 | R103: 0.74193548 | S103: 0.65068493 | T103: 0.80769231 | U103: 184225 | V103: 160
A104: Sheffield Children's NHS Foundation Trust | B104: RCU | C104: North of England Commissioning Region | D104: 84.348665 | E104: 8.035 | F104: 16.18364 | G104: 44.213325 | H104: 15.9167 | I104: 2.2970769 | J104: 0.21881808 | K104: 0.44073094 | L104: 1.2040666 | M104: 0.43346133 | N104: 36720 | O104: 0.97576253 | Q104: 0.77777778 | R104: 0.78571429 | S104: 0.75 | T104: 0.83333333 | U104: 35830 | V104: *
A105: Sheffield Teaching Hospitals NHS Foundation Trust | B105: RHQ | C105: North of England Commissioning Region | D105: 279.88355 | E105: 15.525 | F105: 39.368423 | G105: 113.77258 | H105: 111.21755 | I105: 1.9243257 | J105: 0.10674138 | K105: 0.27067567 | L105: 0.78223786 | M105: 0.7646708 | N105: 145445 | O105: 0.81085634 | P105: 0.0054659837 | Q105: 0.83805668 | R105: 1 | S105: 0.76068376 | T105: 0.89565217 | U105: 117935 | V105: 795
A106: Sherwood Forest Hospitals NHS Foundation Trust | B106: RK5 | C106: Midlands and East of England Commissioning Region | D106: 180.94857 | E106: 6.8 | F106: 22.482813 | G106: 90.815735 | H106: 60.850017 | I106: 1.4787004 | J106: 0.055569175 | K106: 0.18372814 | L106: 0.74214052 | M106: 0.49726254 | N106: 122370 | O106: 0.90904633 | P106: 0.0017569666 | Q106: 0.80978261 | R106: 0.625 | S106: 0.8125 | T106: 0.84722222 | U106: 111240 | V106: 215
A107: Shrewsbury and Telford Hospital NHS Trust | B107: RXW | C107: Midlands and East of England Commissioning Region | D107: 135.33647 | E107: 5 | F107: 26.15 | G107: 67.86997 | H107: 36.316495 | I107: 1.2202918 | J107: 0.04508363 | K107: 0.23578739 | L107: 0.61196492 | M107: 0.32745589 | N107: 110905 | O107: 0.70470222 | P107: 0.041116271 | Q107: 0.83687943 | R107: 0.8125 | S107: 0.84810127 | T107: 0.82608696 | U107: 78155 | V107: 4560
...

Sheet 4 and 12 hour
A1: Procode | B1: SUM_of_4hrs or less | C1: SUM_of_AEATTEND_EXC_PLANNED | D1: 4hr % | E1: Att_Over12HRS | F1: 12hr%
A2: RQW | B2: 71977 | C2: 100992 | D2: 0.71270002 | E2: 6860 | F2: 0.067926172
A3: R1J | B3: 69993 | C3: 70504 | D3: 0.99275218 | E3: 0 | F3: 0
A4: NLO07 | B4: 30054 | C4: 31476 | D4: 0.95482272 | E4: 254 | F4: 0.0080696404
A5: RD8 | B5: 74296 | C5: 87096 | D5: 0.85303573 | E5: 1923 | F5: 0.022079085
A6: NNF94 | B6: 1722 | C6: 1722 | D6: 1 | E6: 0 | F6: 0
A7: RAL | B7: 227155 | C7: 263868 | D7: 0.86086604 | E7: 5980 | F7: 0.022662847
A8: RAJ | B8: 87739 | C8: 101023 | D8: 0.86850519 | E8: 332 | F8: 0.0032863803
A9: RC9 | B9: 102843 | C9: 105219 | D9: 0.97741853 | E9: 53 | F9: 0.00050371131
A10: RBZ | B10: 48069 | C10: 55304 | D10: 0.86917764 | E10: 1814 | F10: 0.032800521
A11: REP | B11: 12346 | C11: 12557 | D11: 0.98319662 | E11: 1 | F11: 7.9636856e-05
A12: RNZ | B12: 42399 | C12: 46233 | D12: 0.91707222 | E12: 120 | F12: 0.0025955486
A13: NJS05 | B13: 46639 | C13: 48115 | D13: 0.9693235 | E13: 3 | F13: 6.2350618e-05
... A212: RXH | B212: 131011 | C212: 158122 | D212: 0.82854378 | E212: 6307 | F212: 0.039886923

Sheet etrust
A1: R0A | B1: MANCHESTER UNIVERSITY NHS FOUNDATION TRUST | C1: Y54
A2: R0A01 | B2: MANCHESTER UNIVERSITY HOSPITAL NHS FT (HQ) | C2: Y54
A3: R0A02 | B3: MANCHESTER ROYAL INFIRMARY | C3: Y54
A4: R0A03 | B4: ROYAL MANCHESTER CHILDREN'S HOSPITAL | C4: Y54
A5: R0A04 | B5: MANCHESTER ROYAL EYE HOSPITAL | C5: Y54
A6: R0A05 | B6: ST MARY'S HOSPITAL | C6: Y54
A7: R0A06 | B7: UNIVERSITY DENTAL HOSPITAL OF MANCHESTER | C7: Y54
A8: R0A07 | B8: WYTHENSHAWE HOSPITAL | C8: Y54
A9: R0A08 | B9: WITHINGTON COMMUNITY HOSPITAL | C9: Y54
A10: R0A09 | B10: TRAFFORD GENERAL HOSPITAL | C10: Y54
A11: R0A10 | B11: ALTRINCHAM HOSPITAL | C11: Y54
A12: R0A12 | B12: CLITHEROE COMMUNITY CLINIC | C12: Y54
... A18783: RW1VR | B18783: MIDHANTS CLDT | C18783: Y57
A18784: RW1VT | B18784: 37316 | C18784: Y57
A18785: RW1VV | B18785: HAVANT & PETERSFIELD OPMH 2 | C18785: Y57
A18786: RW1VW | B18786: SOTON EAST CMHT OPMH | C18786: Y57
A18787: RW1VX | B18787: CMHT ANDOVER AMH | C18787: Y57
A18788: RW1VY | B18788: PSYCHOTHERAPY | C18788: Y57
A18789: RW1W2 | B18789: FAREHAM REACH | C18789: Y57
A18790: RW1W3 | B18790: BURGESS ROAD SURGERY | C18790: Y57
A18791: RW1W4 | B18791: THORNHILL PARK SURGERY | C18791: Y57
A18792: RW1W5 | B18792: STONEHAM LANE SURGERY | C18792: Y57
A18793: RW1W6 | B18793: WOOLSTON LODGE SURGERY | C18793: Y57
A18794: RW1W7 | B18794: CANUTE SURGERY | C18794: Y57
A18795: RW1W8 | B18795: GROVE MEDICAL PRACTICE | C18795: Y57
A18796: RW1W9 | B18796: CHESSEL PRACTICE | C18796: Y57
... A29835: RYYMV | B29835: SIR LUDWIG GUTTMAN CENTRE | C29835: Y57

Sheet Regions
A1: Y54 | B1: North of England Commissioning Region
A2: Y55 | B2: Midlands and East of England Commissioning Region
A3: Y56 | B3: London Commissioning Region
A4: Y57 | B4: South of England Commissioning Region

Sheet stability_index
A1: Organisation name | B1: Organisation code | C1: Total Clinical Staff | D1: HCHS Doctors1 | E1: Nurses & health visitors | F1: Total Clinical Staff, excl. doc and nur | J1: This is used to populate the last 4 columns in Provider_data2 tab
A2: Derby Teaching Hospitals NHS Foundation Trust | B2: RTG | C2: 0.84320557 | D2: 0.92307692 | E2: 0.8013245 | F2: 0.87628866
A3: Kettering General Hospital NHS Foundation Trust | B3: RNQ | C3: 0.73493976 | D3: 0.86363636 | E3: 0.73333333 | F3: 0.69565217
A4: Lincolnshire Community Health Services NHS Trust | B4: RY5 | C4: 0.58536585 | E4: 0.375 | F4: 0.88235294
A5: Northampton General Hospital NHS Trust | B5: RNS | C5: 0.76506024 | D5: 0.91666667 | E5: 0.77669903 | F5: 0.68627451
A6: Nottingham University Hospitals NHS Trust | B6: RX1 | C6: 0.75260417 | D6: 1 | E6: 0.71031746 | F6: 0.79439252
A7: Sherwood Forest Hospitals NHS Foundation Trust | B7: RK5 | C7: 0.80978261 | D7: 0.625 | E7: 0.8125 | F7: 0.84722222
A8: United Lincolnshire Hospitals NHS Trust | B8: RWD | C8: 0.81748072 | D8: 0.88461538 | E8: 0.78142077 | F8: 0.83333333
A9: University Hospitals of Leicester NHS Trust | B9: RWE | C9: 0.77708978 | D9: 0.83333333 | E9: 0.77922078 | F9: 0.7443609
A10: Basildon and Thurrock University Hospitals NHS Foundation Trust | B10: RDD | C10: 0.75539568 | D10: 0.95 | E10: 0.65625 | F10: 0.78181818
A11: Bedford Hospital NHS Trust | B11: RC1 | C11: 0.875 | D11: 1 | E11: 0.82978723 | F11: 0.8125
A12: Cambridge University Hospitals NHS Foundation Trust | B12: RGT | C12: 0.78625954 | D12: 0.9 | E12: 0.78395062 | F12: 0.725
A13: Colchester Hospital University NHS Foundation Trust | B13: RDE | C13: 0.80487805 | D13: 0.86363636 | E13: 0.82191781 | F13: 0.71428571
A14: East and North Hertfordshire NHS Trust | B14: RWH | C14: 0.81094527 | D14: 0.75 | E14: 0.85074627 | F14: 0.7254902
A15: Hertfordshire Community NHS Trust | B15: RY4 | C15: #N/A | F15: #N/A
A16: Ipswich Hospital NHS Trust | B16: RGQ | C16: 0.80379747 | D16: 0.7826087 | E16: 0.81609195 | F16: 0.79166667
A17: James Paget University Hospitals NHS Foundation Trust | B17: RGP | C17: 0.89473684 | D17: 0.86666667 | E17: 0.89795918 | F17: 0.91666667
A18: Luton and Dunstable University Hospital NHS Foundation Trust | B18: RC9 | C18: 0.62561576 | D18: 1 | E18: 0.6015625 | F18: 0.58333333
A19: Mid Essex Hospital Services NHS Trust | B19: RQ8 | C19: 0.71287129 | D19: 0.8 | E19: 0.703125 | F19: 0.6875
A20: Norfolk and Norwich University Hospitals NHS Foundation Trust | B20: RM1 | C20: 0.76666667 | D20: 0.5 | E20: 0.72519084 | F20: 0.84415584
A21: North West Anglia NHS Foundation Trust | B21: RGN | C21: 0.72469636 | D21: 0.71428571 | E21: 0.7195122 | F21: 0.70967742
A22: Princess Alexandra Hospital NHS Trust | B22: RQW | C22: 0.736 | D22: 0.88235294 | E22: 0.69565217 | F22: 0.71794872
A23: Queen Elizabeth Hospital King's Lynn NHS Foundation Trust | B23: RCX | C23: 0.80722892 | D23: 1 | E23: 0.73684211 | F23: 0.94444444
A24: Southend University Hospital NHS Foundation Trust | B24: RAJ | C24: 0.70394737 | D24: 0.76190476 | E24: 0.70886076 | F24: 0.67307692
A25: West Hertfordshire Hospitals NHS Trust | B25: RWG | C25: 0.73943662 | D25: 0.91666667 | E25: 0.71428571 | F25: 0.75555556
A26: West Suffolk NHS Foundation Trust | B26: RGR | C26: 0.64864865 | D26: 1 | E26: 0.61428571 | F26: 0.63636364
A27: Airedale NHS Foundation Trust | B27: RCF | C27: 0.84615385 | D27: 1 | E27: 0.83333333 | F27: 0.80555556
... A38: Sheffield Children's NHS Foundation Trust | B38: RCU | C38: 0.77777778 | D38: 0.78571429 | E38: 0.75 | F38: 0.83333333
A39: Sheffield Health and Social Care NHS Foundation Trust | B39: TAH | C39: 0.75 | E39: 0.72727273 | F39: 1
A40: Sheffield Teaching Hospitals NHS Foundation Trust | B40: RHQ | C40: 0.83805668 | D40: 1 | E40: 0.76068376 | F40: 0.89565217
A41: York Teaching Hospital NHS Foundation Trust | B41: RCB | C41: 0.78061224 | D41: 0.91666667 | E41: 0.74576271 | F41: 0.77777778
A42: Dorset County Hospital NHS Foundation Trust | B42: RBD | C42: 0.80519481 | D42: 0.77777778 | E42: 0.86046512 | F42: 0.6875
A43: Dorset Healthcare University NHS Foundation Trust | B43: RDY | C43: 0.73684211 | E43: 0.66666667 | F43: 1
A44: Hampshire Hospitals NHS Foundation Trust | B44: RN5 | C44: 0.73459716 | D44: 1 | E44: 0.77419355 | F44: 0.56410256
A45: Isle of Wight NHS Trust | B45: R1F | C45: 0.70689655 | D45: 1 | E45: 0.55555556 | F45: 0.75
A46: Poole Hospital NHS Foundation Trust | B46: RD3 | C46: 0.78861789 | D46: 0.9 | E46: 0.77777778 | F46: 0.7804878
A47: Portsmouth Hospitals NHS Trust | B47: RHU | C47: 0.83969466 | D47: 0.9375 | E47: 0.82822086 | F47: 0.81927711
A48: Royal Bournemouth and Christchurch Hospitals NHS Foundation Trust | B48: RDZ | C48: 0.73856209 | D48: 0.76190476 | E48: 0.72727273 | F48: 0.74545455
A49: Salisbury NHS Foundation Trust | B49: RNZ | C49: 0.7721519 | D49: 0.7 | E49: 0.7173913 | F49: 0.91304348
A50: Southern Health NHS Foundation Trust | B50: RW1 | C50: 0.85714286 | E50: 0.85714286 | F50: 0.85714286
A51: University Hospital Southampton NHS Foundation Trust | B51: RHM | C51: 0.76047904 | D51: 0.875 | E51: 0.74468085 | F51: 0.5
A52: Buckinghamshire Healthcare NHS Trust | B52: RXQ | C52: 0.648 | D52: 0.8125 | E52: 0.60273973 | F52: 0.66666667
A53: Milton Keynes University Hospital NHS Foundation Trust | B53: RD8 | C53: 0.84615385 | D53: 1 | E53: 0.80645161 | F53: 0.85
A54: Oxford University Hospitals NHS Foundation Trust | B54: RTH | C54: 0.80384615 | D54: 0.96 | E54: 0.73758865 | F54: 0.86170213
A55: Royal Berkshire NHS Foundation Trust | B55: RHW | C55: 0.73529412 | D55: 0.84615385 | E55: 0.69148936 | F55: 0.76
A56: Chelsea and Westminster Hospital NHS Foundation Trust | B56: RQM | C56: 0.74418605 | D56: 0.77777778 | E56: 0.76646707 | F56: 0.6
A57: Hillingdon Hospitals NHS Foundation Trust | B57: RAS | C57: 0.72159091 | D57: 0.88 | E57: 0.76744186 | F57: 0.6
A58: Hounslow and Richmond Community Healthcare NHS Trust | B58: RY9 | C58: 0.68181818 | D58: 0 | E58: 0.66666667 | F58: 0.77777778
A59: Imperial College Healthcare NHS Trust | B59: RYJ | C59: 0.70881226 | D59: 0.85185185 | E59: 0.69411765 | F59: 0.6875
A60: London Ambulance Service NHS Trust | B60: RRU | C60: 0 | F60: 0
A61: London North West University Healthcare NHS Trust | B61: R1K | C61: 0.76762402 | D61: 0.87878788 | E61: 0.74568966 | F61: 0.75423729
A62: Croydon Health Services NHS Trust | B62: RJ6 | C62: 0.72352941 | D62: 0.88888889 | E62: 0.61956522 | F62: 0.73913043
A63: Epsom and St Helier University Hospitals NHS Trust | B63: RVR | C63: 0.74731183 | D63: 0.85714286 | E63: 0.73636364 | F63: 0.6875
A64: Guy's and St Thomas' NHS Foundation Trust | B64: RJ1 | C64: 0.75185185 | D64: 0.91666667 | E64: 0.72972973 | F64: 0.75409836
A65: King's College Hospital NHS Foundation Trust | B65: RJZ | C65: 0.75342466 | D65: 0.91666667 | E65: 0.74496644 | F65: 0.6744186
A66: Kingston Hospital NHS Foundation Trust | B66: RAX | C66: 0.69924812 | D66: 0.92307692 | E66: 0.68918919 | F66: 0.60869565
A67: Lewisham and Greenwich NHS Trust | B67: RJ2 | C67: 0.7880597 | D67: 0.85 | E67: 0.79324895 | F67: 0.73076923
A68: South West London and St George's Mental Health NHS Trust | B68: RQY | C68: 0 | F68: 0
A69: St George's University Hospitals NHS Foundation Trust | B69: RJ7 | C69: 0.71515152 | D69: 0.76 | E69: 0.66964286 | F69: 0.85714286
A70: Barking, Havering and Redbridge University Hospitals NHS Trust | B70: RF4 | C70: 0.71590909 | D70: 0.68181818 | E70: 0.73333333 | F70: 0.68831169
A71: Barts Health NHS Trust | B71: R1H | C71: 0.73852295 | D71: 0.82692308 | E71: 0.68852459 | F71: 0.79861111
A72: Homerton University Hospital NHS Foundation Trust | B72: RQX | C72: 0.75 | D72: 0.92857143 | E72: 0.77272727 | F72: 0.625
A73: North Middlesex University Hospital NHS Trust | B73: RAP | C73: 0.75 | D73: 0.68421053 | E73: 0.73643411 | F73: 0.8125
A74: Royal Free London NHS Foundation Trust | B74: RAL | C74: 0.73899371 | D74: 0.85714286 | E74: 0.70526316 | F74: 0.74193548
A75: University College London Hospitals NHS Foundation Trust | B75: RRV | C75: 0.74375 | D75: 0.95238095 | E75: 0.6741573 | F75: 0.78
A76: Whittington Health NHS Trust | B76: RKE | C76: 0.76612903 | D76: 0.66666667 | E76: 0.81481481 | F76: 0.67741935
A77: Ashford and St. Peter's Hospitals NHS Foundation Trust | B77: RTK | C77: 0.825 | D77: 0.9 | E77: 0.80821918 | F77: 0.81081081
A78: Brighton and Sussex University Hospitals NHS Trust | B78: RXH | C78: 0.77477477 | D78: 0.92592593 | E78: 0.76036866 | F78: 0.76404494
A79: Dartford and Gravesham NHS Trust | B79: RN7 | C79: 0.81506849 | D79: 0.77777778 | E79: 0.85507246 | F79: 0.78
A80: East Kent Hospitals University NHS Foundation Trust | B80: RVV | C80: 0.69248826 | D80: 0.75 | E80: 0.65384615 | F80: 0.73809524
... A82: Frimley Health NHS Foundation Trust | B82: RDU | C82: 0.78021978 | D82: 0.78125 | E82: 0.76271186 | F82: 0.82291667
A83: Kent Community Health NHS Foundation Trust | B83: RYY | C83: 0.75 | E83: 0.66666667 | F83: 1
A84: Maidstone and Tunbridge Wells NHS Trust | B84: RWF | C84: 0.74786325 | D84: 0.88888889 | E84: 0.69127517 | F84: 0.80597015
A85: Medway NHS Foundation Trust | B85: RPA | C85: 0.78512397 | D85: 0.95652174 | E85: 0.82539683 | F85: 0.48571429
A86: NHS Canterbury and Coastal CCG | B86: 09E | C86: #N/A | F86: #N/A
A87: Queen Victoria Hospital NHS Foundation Trust | B87: RPC | C87: 0.7 | D87: 0 | F87: 0.77777778
A88: Royal Surrey County Hospital NHS Foundation Trust | B88: RA2 | C88: 0.79591837 | D88: 0.66666667 | E88: 0.84057971 | F88: 0.70588235
A89: Surrey and Sussex Healthcare NHS Trust | B89: RTP | C89: 0.75903614 | D89: 0.78571429 | E89: 0.73626374 | F89: 0.70212766
A90: Western Sussex Hospitals NHS Foundation Trust | B90: RYR | C90: 0.77830189 | D90: 0.91304348 | E90: 0.76190476 | F90: 0.76190476
A91: City Hospitals Sunderland NHS Foundation Trust | B91: RLN | C91: 0.87150838 | D91: 0.92307692 | E91: 0.84090909 | F91: 0.97058824
A92: County Durham and Darlington NHS Foundation Trust | B92: RXP | C92: 0.85714286 | D92: 0.86363636 | E92: 0.8411215 | F92: 0.81666667
A93: Gateshead Health NHS Foundation Trust | B93: RR7 | C93: 0.75630252 | D93: 1 | E93: 0.71621622 | F93: 0.78378378
A94: Newcastle Upon Tyne Hospitals NHS Foundation Trust | B94: RTD | C94: 0.85353535 | D94: 0.95454545 | E94: 0.85087719 | F94: 0.80645161
A95: North Tees and Hartlepool NHS Foundation Trust | B95: RVW | C95: 0.71942446 | D95: 0.875 | E95: 0.57142857 | F95: 0.83018868
A96: Northumbria Healthcare NHS Foundation Trust | B96: RTF | C96: 0.88557214 | D96: 0.96875 | E96: 0.85714286 | F96: 0.88235294
A97: South Tees Hospitals NHS Foundation Trust | B97: RTR | C97: 0.82478632 | D97: 0.88888889 | E97: 0.75590551 | F97: 0.9125
A98: South Tyneside NHS Foundation Trust | B98: RE9 | C98: 0.83333333 | D98: 1 | E98: 0.77358491 | F98: 0.85714286
A99: Aintree University Hospital NHS Foundation Trust | B99: REM | C99: 0.75324675 | D99: 0.83333333 | E99: 0.7173913 | F99: 0.79545455
... A105: East Cheshire NHS Trust | B105: RJN | C105: 0.77777778 | D105: 0.84615385 | E105: 0.33333333 | F105: 0.8
A106: East Lancashire Hospitals NHS Trust | B106: RXR | C106: 0.84375 | E106: 0.9 | F106: 0.75
A107: Lancashire Teaching Hospitals NHS Foundation Trust | B107: RXN | C107: 0.82125604 | D107: 0.91666667 | E107: 0.7706422 | F107: 0.86486486
A108: Mid Cheshire Hospitals NHS Foundation Trust | B108: RBT | C108: 0.77941176 | D108: 0.71428571 | E108: 0.75471698 | F108: 0.82142857
A109: North Cumbria University Hospitals NHS Trust | B109: RNL | C109: 0.71929825 | D109: 0.7 | E109: 0.63076923 | F109: 0.82051282
A110: Pennine Acute Hospitals NHS Trust | B110: RW6 | C110: 0.82307692 | D110: 0.86111111 | E110: 0.78017241 | F110: 0.87704918
A111: Pennine Care NHS Foundation Trust | B111: RT2 | C111: 1 | E111: 1 | F111: 1
A112: Royal Liverpool and Broadgreen University Hospitals NHS Trust | B112: RQ6 | C112: 0.77297297 | D112: 0.95 | E112: 0.66 | F112: 0.87692308
A113: Salford Royal NHS Foundation Trust | B113: RM3 | C113: 0.80798005 | D113: 0.93617021 | E113: 0.79906542 | F113: 0.77857143
A114: Southport and Ormskirk Hospital NHS Trust | B114: RVY | C114: 0.8253012 | D114: 0.93333333 | E114: 0.77669903 | F114: 0.89583333
A115: St Helens and Knowsley Hospitals NHS Trust | B115: RBN | C115: 0.8 | D115: 0.85714286 | E115: 0.73913043 | F115: 0.875
A116: Stockport NHS Foundation Trust | B116: RWJ | C116: 0.72222222 | D116: 0.75 | E116: 0.70652174 | F116: 0.75
...
